Workbook

Sheet SE_Kompetenzen_SE4OWL
B2: Kompetenzen | C2: Definition | D2: Repräsentiert INCOSE Kompetenzen | F2: Beschriebung Reifegrad | G2: Stufe 0 | H2: Stufe 1 | I2: Stufe 2 | J2: Stufe 3 | K2: Stufe 4
G3: Nicht bewusst vorhanden | H3: Individuell/Ad Hoc | I3: Fragmentiert | J3: Etabliert | K3: Systematische Förderung
A4: Kern Kompetenzen | B4: Systemisches Denken | C4: Die Kompetenz fundamentale Konzepte des Systemdenkens im Systems Engineering anzuwenden und die Rolle des eigenen Systems in seinem Gesamtkontext zu verstehen. | D4: Systemisches Denken, Capability Engineering | F4: Wichtiger Bestandteil der SE-Philosophie ist die Verbreitung und Verwendung des Systemdenkens. Darunter wird eine Denkweise verstanden, die es ermöglicht, komplexe Systeme besser zu verstehen und zu gestalten und somit ein ganzheitliches Systemverständnis zu erzeugen [Gei19; HWF+19; WRF+15]. | G4: Ansätze, Methoden und Verhaltensmuster des Systemdenkens sind im Unternehmen nicht verbreitet. Ein einheitliches Systemverständnis fehlt. Einzelne Prinzipien des Systemdenkens werden, wenn überhaupt nur unbewusst genutzt. | H4: Einzelne Personen nutzen Ansätze und Methoden des Systemdenkens für ihre individuellen Tätigkeiten, wie z.B. der Erhöhung des individuellen Systemverständnisses. Grundlegende Tätigkeiten, wie die Systemdefinition werden ausgeführt. Eine ganzheitliche Systembetrachtung findet nicht statt. | I4: Einzelne Organisationseinheiten nutzen Ansätze und Methoden des Systemdenkens für einzelne Projekte. Innerhalb dieser Projekte werden Systeme schon ganzheitlich betrachtet, so dass innerhalb des Projektteams ein gutes Systemverständnis besteht. | J4: Das Systemdenken wird unternehmensweit gelebt. Wesentliche Begriffe der Systembeschreibung sind bei allen beteiligten Personen einheitlich definiert und bekannt. Ansätze und Methoden dieser Denkweise werden automatisch genutzt, um ein System ganzheitlich zu betrachten und das Systemverständnis zu erhöhen. | K4: Zusätzlich zu der unternehmensweiten Verbreitung der mit dem Systemdenken und dem ganzheitlichen Systemverständnis verbundenen Ansätze und Methoden werden bestehende Strukturen kontinuierlich optimiert und neue Ansätze und Methoden systematisch integriert.
B5: Systemmodellierung und -analyse | C5: Die Kompetenz exakte Daten und Informationen mit HIlfe von domäne-übergreifenden Modellen bereitzustellen, um das technische Verständnis und das Treffen von Entscheidungen zu unterstützen. | D5: Systemmodellierung und -analyse | F5: Modellbasiertes Arbeiten dient dem Zweck, die Aktivitäten zur Beschreibung der Systemspezifikation von Beginn der konzeptionellen Architekturgestaltung über die Entwicklung bis hin zu späten Phasen des System-Lebenszyklus zu unterstützen und durch eine formalisierte Anwendung der einzelnen Aktivitäten Entscheidungsprozesse und Analysen kostengünstig und zeitgenau verfügbar zu machen. | G5: Die Systemspezifikation wird nicht disziplinübergreifend modellbasiert beschrieben. | H5: Einzelne Aspekte der Systemspezifikation werden durch disziplinübergreifende Modelle beschrieben. Das modellbasierte Arbeiten erfolgt nicht auf Basis einer expliziten MBSE-Methode. | I5: Einzelne Aspekte der Systemspezifikation werden durch modellbasiertes Arbeiten unterstützt. Es werden einzelne Schritte einer MBSE-Methode angewandt. | J5: Die Beschreibung der disziplinübergreifenden Systemspezifikation erfolgt durchgehend auf Basis einer MBSE-Methode. Durch Richtlinien und Vorgaben ist definiert, in welcher Form und Ausprägung die modellbasierte Systemspezifikation das System-of-Interest beschreibt. | K5: Die MBSE-Methode ist unternehmens-spezifisch angepasst. Die Leistungsfähigkeit der Methode wird kontinuierlich optimiert.
B6: Berücksichtigung von Systemlebenszyklusphasen | C6: Die Kompetenz während der Realisierung eines Systems die anderen Lebenszyklen außer der Betriebsphase in den Systemanforderungen, -architekturen und -designs zu berücksichtigen. | D6: Lebenszyklen, Geschäfts- und Unternehmensintegration
B7: Agiles Denken / Kunden-Nutzenorientierung | C7: Die Kompetenz die agilen Werte / den Kundennutzen in den Mittelpunkt der Entwicklung zu stellen.
A8: Fachkompetenzen | B8: Anforderungsmanagement | C8: Die Kompetenz Bedürfnisse und Erwartungen der Stakeholder zu analysieren und daraus Anforderungen für ein System festzulegen. | D8: Definition von Anforderungen, Geschäfts- und Unternehmensintegration | F8: Ermittlung von Anforderungen sowie deren Dokumentation und Erstellung entsprechender Anforderungsdokumente (als strukturierte Menge von Anforderungen). | G8: Es gibt keinen systematischen und strukturierten Ansatz, um Anforderungen im Rahmen des SE zu ermitteln und zu dokumentieren. Die Dokumentation von Anforderungen erfolgt nicht oder unstrukturiert. | H8: Zur Dokumentation von Anforderungen stehen Dokumentenvorlagen bereit. Vereinzelte RE-Prozess- und Methodenbausteine sind vorhanden und werden genutzt. | I8: Ein RE-Prozess von der Identifikation bis zur Abstimmung von Anforderungen existiert, kann projektspezifisch angepasst werden und wird größtenteils angewandt. Anforderungen werden unter Nutzung des Systemdenkens strukturiert und mittels formeller Vorgaben dokumentiert. Definierte Qualitätskriterien für Anforderungen und Anforderungsdokumente sind vorhanden. | J8: Der RE-Prozess ist unternehmensweit etabliert. Es existieren unternehmensweite Vorgaben zur Strukturierung von Anforderungen mittels Systemdenkens. Es existiert ein Sicherheitsprozess und geeignete Maßnahmen zur Einhaltung der Qualitätskriterien. | K8: Ein systematischer und strukturierter Ansatz zur Ermittlung und Dokumentation von Anforderungen ist vorhanden und wird unternehmensweit verfolg. Attributschema und Einbindung in den RE-Prozess sind klar definiert. Sowohl Interne als auch Externe nutzen dieses Attributschema. Der RE-Ansatz wird kontinuierlich optimiert.
B9: System-Architekturgestaltung | C9: Die Kompetenz die zu einem System zugehörigen Elemente, ihrer Hierarchie, sowie ihrer Schnittstellen oder ihres Verhaltens und der damit verbundenen abgeleiteten Anforderungen zur Entwicklung einer implementierbaren Lösung zu definieren. | D9: System-Architektur, Schnittstellen | F9: Die (System-) Architektur umfasst sowohl die Struktur als auch das Verhalten des Systems. Sie soll dabei einen konkreten Zweck erfüllen, z.B. die Beschreibung des Zusammenwirkens einzelner Systemelemente. Im Kontext des SE ist die Architektur Teil der Systemgestaltung. Dabei kann die Architektur tool-gestützt, (semi-) formal, durchgängig und rückverfolgbar gestaltet werden [Alt12], [HWF+19]. Die Architekturgestaltung wird durch verschiedene Methoden unterstützt. | G9: Das System wird nicht durch eine abstrakte und disziplinneutrale Architektur im Sinne des SE beschrieben. | H9: Einzelne Aspekte des Systems, wie z.B. die Wirkstruktur oder die Systemzustände, werden gem. einer SE-gerechten Architektur vorwiegend nach Bedarf beschrieben. Ein methodischer Ansatz wird dabei nicht (bewusst) verfolgt. | I9: In einzelnen Abteilungen erfolgt ein methodisches Vorgehen auf Basis des Systemdenkens, um einzelne Aspekte der Systemarchitektur systematisch zu erstellen. Die Systemarchitektur-gestaltung erfolgt auf Basis eines definierten Gedankenmodells (z.B. RFLP), um mit der Architekturgestaltung Mehrwerte für die Produktentwicklung zu heben. | J9: Die Systemarchitektur wird unternehmens-weit, ganzheitlich aus Sicht des Systems und semi-formal (z.B. mit SysML) mit Hilfe geeigneter Methoden beschrieben und analysiert. Für verschiedene Zwecke sind Viewpoints definiert. Es erfolgt eine logische Verknüpfung der einzelnen Aspekte z.B. zwischen funktionaler und physischer Architektur. Es werden alternative Lösungsmöglichkeiten betrachtet. | K9: Die Systemarchitektur wird formal durch eine bedarfsgerechte, angepasste Notation tool-gestützt beschrieben. Die Methoden sowie der Architekturgestaltungs-prozess werden regelmäßig evaluiert und angepasst.
B10: Integration, Verifikation & Validierung | C10: Die Kompetenz eine Menge von Systemelementen zu einer verifizier- oder validierbaren Einheit zu integrieren bzw. den objektiven Nachweis, das ein System die spezifizierten Anforderungen erfüllt (Validierung), oder seiner beabsichtigten Eigenschaften in der vorgesehenen Einsatzumgebung erreicht (Validierung), durchzuführen. | D10: Integration, Verifizierung, Validierung | F10: Beurteilung eines Produktes hinsichtlich spezifischer Produkteigenschaften (Verifikation) und der Einsetzbarkeit des Produktes (Validierung) | G10: Keine besondere Expertise hinsichtlich V&V-Techniken vorhanden. Es ist im Unternehmen keine unabhängige Testinstanz vorhanden. Testprozeduren sind nicht reproduzierbar. Eine Dokumentation findet nur rudimentär und mit stark aggregierten Ergebnissen statt. | H10: Es liegen teilweise reproduzierbare Testprozeduren vor. Es erfolgt eine individuelle Dokumentation und Ablage der V&V-Tätigkeiten. | I10: In vereinzelten Unternehmensbereichen werden V&V-Prozeduren standardisiert dokumentiert und innerhalb dieser Bereiche zentral bereitgestellt. Die Input-Parameter für die V&V-Prozeduren sind oftmals definiert (z.B. in Form von Anforderungen). | J10: Die V&V ist ein fester Bestandteil des Entwicklungsprozesses und wird von einer unabhängigen Testinstanz durchgeführt. Tiefe, spezialisierte V&V-Expertise ist vorhanden. Es werden überwiegend standardisierte Testprozeduren genutzt. Dokumentationen werden zentral bereitgestellt und sind über z.B. Projekt- oder Bauteilbezüge wieder auffindbar. Die Input-Parameter für die V&V-Prozeduren sind definiert. | K10: Das dokumentierte Wissen ist ohne kontextspezifisches Vorwissen auffindbar. Wo immer möglich, werden V&V-Prozeduren sowie -Dokumentationen wiederverwendet. Die Durchführung und Dokumentation von V&V-Tätigkeiten werden ständig weiteroptimiert.
B11: Betrieb, Service und Instandhaltung | C11: Die Kompetenz das System in Betrieb zu nehmen, zu betreiben und seine Fähigkeiten/Funktionalitäten über seine Lebensdauer aufrechterhalten wird. | D11: Überleitung, Betrieb und Support
B12: Agile Methodenkompetenz | C12: Die Kompetenz Methoden anzuwenden, welche die Agilenwerte im Projektkontext unterstützen und paralleles arbeiten ermöglichen | D12: Gleichzeitige-Entwicklung
A13: Sozial- und Selbstkompetenzen | B13: Selbstorganisation | C13: Die Kompetenz sich selbst zu organisieren und Aufgaben | D13: Veränderung, Selbstkompetenz, Selbstorganisation, Gleichzeitige Entwicklung
B14: Kommunikation & Zusammenarbeit | C14: Die Kompetenz konstruktiv, effizient und bewusst, auch domaineübergreifend, zu kommunizieren und dabei die Gefühle anderer Menschen zu erfassen und zu berücksichtzigen sowie Beziehungen zu Kollegen und Vorgesetzten nachhaltig und fair zu gestalten. | D14: Kommunikation, Ethik und Professionalität, Emotionale Intelligenz
B15: Führen | C15: Die Kompetenz geeignete Ziele für ein System bzw. Systemelement auszuwählen, bei Bedarf zu verhandeln und mit einem Team effizient zu erreichen und dabei ggf. Teammitglieder bei der Lösung von Problemen anzuleiten. | D15: Technische Führung, Unterstützung/ Vermittlung, Teamdynamik, Verhandlung, Coaching und Mentoring,
A16: Managementkompetenzen | B16: Projektmanagement | C16: Die Kompetenz Aktivitäten zu identifizieren, planen, koordinieren und anzupassen um ein zufriedenstellendes System, Produkt oder Service mit angemessener Qualität, Finanzen und Zeit zu liefern. | D16: Projektmanagement, Finanzen, Qualität, Planung, Überwachung und Steuerung , Gleichzeitige Entwicklung | F16: In der SE-Philosophie ist das Projektmanagement eng mit dem der Systemgestaltung des SE verknüpft. Für die erfolgreiche Entwicklung von Systemen ist es daher wichtig, dass SE bei der organisatorischen Projektplanung und -gestaltung berücksichtigt wird und einzelne Tätigkeiten beider Bereiche miteinander integriert und entsprechende Rollenkonzepte und Aufgabenbeschreibungen definiert, sowie abgegrenzt sind. | G16: Die Koordination, Gestaltung und Planung von SE-Prozessen werden im Rahmen des Projektmanagements nicht berücksichtigt. Die Tätigkeiten und Aufgaben des Projektmanagements sind dabei nicht mit denen des SE abgestimmt. | H16: In einigen SE-Pionier-Projekten erfolgt die Koordination, Gestaltung und Planung von SE-Prozessen im Rahmen des Projektmanagements. Die Tätigkeiten und Aufgaben des Projektmanagements sind dabei im gesamten Unternehmen noch nicht mit denen des SE abgestimmt. | I16: Die Koordination, Gestaltung und Planung von SE-Prozessen ist organisatorisch mit dem Projektmanagement verankert. In der Praxis sind die Tätigkeiten und Aufgaben des Projektmanagements dabei im gesamten Unternehmen noch nicht mit denen des SE abgestimmt. | J16: Die Koordination, Gestaltung und Planung von SE-Prozessen sind ein fester, gelebter Bestandteil des Projektmanagements. Die Tätigkeiten und Aufgaben des Projektmanagements sind dabei im gesamten Unternehmen mit denen des SE abgestimmt. | K16: Die Koordination, Gestaltung und Planung von SE-Prozessen werden als fester Bestandteil des Projektmanagements zusätzlich kontinuierlich an sich verändernde äußere Rahmenbedingungen angepasst und systematisch optimiert.
B17: Entscheidungsmanagement | C17: Die Kompetenz strukturiert und analytisch ein objektives Set von Alternativen zu identifizieren, zu charakterisieren und zu evaluieren und dabei Risiken und Chancen zu berücksichtigen | D17: Risiko- und Chancenmanagement
B18: Informationsmanagement | C18: Die Fähigkeit alle Aspekten von Informationen für bestimmte Stakeholder zu adressieren, um die richtigen Informationen zum passenden Zeitpunkt, in der passenden Sicherheit zu liefern. | D18: Beschaffung und Versorgung, Entwurf für...
B19: Konfigurationsmanagement | C19: Die Fähigkeit Systemfunktionen, Leistung und physikalischen Eigenschaften über den Lebenszyklus stimmig zu gestalten und die Konsistenz sicherzustellen.

Sheet Rollen-Prozess-Matrix
B1: Lifecyle-Prozess | C1: 0 = nicht relevant 1 = unterstützt 2 = verantwortlich 3= gestaltet | D1: Activity and Tasks (ISO 15288, 2015) | E1: Prozess | F1: Aktivität | G1: Erläuterung (als Satz) | H1: Kunde | I1: Kundenvertreter | J1: Projektleiter | K1: Interner Support (IT, Qualifikation, SE) | L1: Prozess- & Richtlinien-verantwortlicher​ | M1: System-Ingenieur | N1: Entwickler | O1: Produktionskoordinator/ -planer | P1: V&V-Mitarbeiter | Q1: Produktionsmitarbeiter | R1: Servicetechniker | S1: Qualitätsmanager | T1: Innovations- und (Strategie)management | U1: Management
A2: Anwendung | B2: 6.1 Vertrags-Prozesse | C2: Akquisition | D2: Prepare for the acquisition | E2: 6.1.1 Akquisition | F2: Vorbereiten der Anschaffung | H2: 0 | I2: 0 | J2: 0 | K2: 0 | L2: 3 | M2: 1 | N2: 1 | O2: 2 | P2: 1 | Q2: 0 | R2: 0 | S2: 0 | T2: 0 | U2: 0
C3: Lieferung | D3: Prepare for the supply | E3: 6.1.2 Lieferung | F3: Vorbereiten der Lieferung | H3: 0 | I3: 2 | J3: 1 | K3: 0 | L3: 3 | M3: 1 | N3: 0 | O3: 1 | P3: 0 | Q3: 0 | R3: 1 | S3: 0 | T3: 0 | U3: 0
B4: 6.2 Organisatorische Projektbefähigungs-Prozesse | C4: Lebenszyklus-Modell-Management | D4: Establish the process | E4: 6.2.1 Lebenszyklus-Modell-Management | F4: Definition eines Prozess | H4: 0 | I4: 0 | J4: 0 | K4: 1 | L4: 3 | M4: 0 | N4: 0 | O4: 0 | P4: 0 | Q4: 0 | R4: 0 | S4: 0 | T4: 0 | U4: 0
C5: Verwaltung der Infrastruktur | D5: Establish the infrastructure | E5: 6.2.2 Verwaltung der Infrastruktur | F5: Einrichten der Infrastruktur | H5: 0 | I5: 0 | J5: 0 | K5: 2 | L5: 3 | M5: 0 | N5: 0 | O5: 0 | P5: 0 | Q5: 0 | R5: 0 | S5: 0 | T5: 0 | U5: 0
C6: Portfoliomanagement | D6: Define and authorize projects | E6: 6.2.3 Portfoliomanagement | F6: Definition und Genehmigung von Projekten | H6: 0 | I6: 1 | J6: 1 | K6: 0 | L6: 3 | M6: 0 | N6: 0 | O6: 0 | P6: 0 | Q6: 0 | R6: 0 | S6: 0 | T6: 2 | U6: 1
C7: Personalwesen-Management | D7: Identify skills | E7: 6.2.4 Personalwesen-Management | F7: Idenfizierung von Fähigkeiten | H7: 0 | I7: 0 | J7: 0 | K7: 2 | L7: 3 | M7: 0 | N7: 0 | O7: 0 | P7: 0 | Q7: 0 | R7: 0 | S7: 0 | T7: 0 | U7: 1
C8: Qualitätsmanagement | D8: Plan quality management | E8: 6.2.5 Qualitätsmanagement | F8: Planung des Qualitätsmanagement | H8: 0 | I8: 0 | J8: 0 | K8: 0 | L8: 3 | M8: 0 | N8: 0 | O8: 0 | P8: 1 | Q8: 0 | R8: 0 | S8: 2 | T8: 0 | U8: 0
C9: Wissensmanagement | D9: Plan knowledge management | E9: 6.2.6 Wissensmanagement | F9: Planung des Wissensmanagement | H9: 0 | I9: 0 | J9: 0 | K9: 2 | L9: 3 | M9: 0 | N9: 0 | O9: 0 | P9: 0 | Q9: 0 | R9: 0 | S9: 0 | T9: 0 | U9: 0
B10: 6.3 Technischen Management Prozesse | C10: Projektierung/Projektplanung | D10: Define the project | E10: 6.3.1 Projektierung/Projektplanung | F10: Definieren des Projekts | H10: 0 | I10: 0 | J10: 2 | K10: 0 | L10: 3 | M10: 0 | N10: 0 | O10: 0 | P10: 0 | Q10: 0 | R10: 0 | S10: 0 | T10: 0 | U10: 0
C11: Projektbewertung und Steuerung | D11: Plan for project assesment and control | E11: 6.3.2 Projektbewertung und Steuerung | F11: Planung zur Projektbewertung und -steuerung | H11: 0 | I11: 0 | J11: 2 | K11: 0 | L11: 3 | M11: 0 | N11: 0 | O11: 0 | P11: 0 | Q11: 0 | R11: 0 | S11: 0 | T11: 0 | U11: 1
C12: Entscheidungsmanagement | D12: Prepare for decisions | E12: 6.3.3 Entscheidungs-management | F12: Vorbereiten der Entscheidungen | H12: 0 | I12: 2 | J12: 2 | K12: 0 | L12: 3 | M12: 2 | N12: 1 | O12: 1 | P12: 1 | Q12: 0 | R12: 0 | S12: 0 | T12: 1 | U12: 2
C13: Risiko-Management | D13: Plan risk management | E13: 6.3.4 Risiko-Management | F13: Risikomanagement planen | H13: 0 | I13: 1 | J13: 2 | K13: 0 | L13: 3 | M13: 2 | N13: 1 | O13: 1 | P13: 0 | Q13: 0 | R13: 0 | S13: 1 | T13: 0 | U13: 0
C14: Konfigurationsmanagement | D14: Plan configuration management | E14: 6.3.5 Konfigurationsmanagement (Änderungsmanagement) | F14: Konfigurationsmanagement planen | H14: 0 | I14: 1 | J14: 2 | K14: 0 | L14: 3 | M14: 2 | N14: 1 | O14: 0 | P14: 1 | Q14: 0 | R14: 0 | S14: 0 | T14: 0 | U14: 0
C15: Informationsmanagement | D15: Prepare for information management | E15: 6.3.6 Informationsmanagement | F15: Informationsmanagement vorbereiten | H15: 0 | I15: 1 | J15: 2 | K15: 0 | L15: 3 | M15: 1 | N15: 1 | O15: 0 | P15: 1 | Q15: 0 | R15: 0 | S15: 0 | T15: 0 | U15: 0
C16: Messung | D16: Prepare for measurement | E16: 6.3.7 Messung | F16: Vorbereiten der Messung | H16: 0 | I16: 0 | J16: 0 | K16: 0 | L16: 3 | M16: 0 | N16: 1 | O16: 0 | P16: 2 | Q16: 0 | R16: 0 | S16: 0 | T16: 0 | U16: 0
C17: Qualitätssicherungsprozess | D17: Prepare for quality assurance | E17: 6.3.8 Qualitätssicherungsprozess | F17: Vorbereiten der Qualitätssicherung | H17: 0 | I17: 1 | J17: 1 | K17: 0 | L17: 3 | M17: 0 | N17: 0 | O17: 0 | P17: 2 | Q17: 0 | R17: 0 | S17: 2 | T17: 0 | U17: 0
B18: 6.4 Technische Prozesse | C18: Geschäfts- oder Einsatzanalyseprozess: | D18: Prepare for business or mission analysis | E18: 6.4.1 Geschäfts- oder Einsatzanalyseprozess: | F18: Vorbereiten der Geschäfts- oder Einsatzanalyse | H18: 0 | I18: 2 | J18: 0 | K18: 0 | L18: 3 | M18: 0 | N18: 0 | O18: 0 | P18: 0 | Q18: 0 | R18: 0 | S18: 0 | T18: 2 | U18: 1
C19: Prozess der Stakeholder-Bedürfnisse und Anforderungsdefinition: | D19: Prepare the stakeholder needs and requirements definition | E19: 6.4.2 Prozess der Stakeholder-Bedürfnisse und Anforderungsdefinition: | F19: Vorbereiten der Bedarfsanalyse und Anforderungsdefinition der Stakeholder | G19: Es sollen die Anfordernungen der Stakeholderaufgedeckt werden. Dazu sind zunächst alle Stakeholder zu ermitteln und im Nachgang deren Anforderungen an das System. | H19: 0 | I19: 2 | J19: 0 | K19: 0 | L19: 3 | M19: 1 | N19: 0 | O19: 0 | P19: 1 | Q19: 0 | R19: 0 | S19: 0 | T19: 0 | U19: 0
C20: Prozess der Definition von Systemanforderungen: | D20: Prepare for systems requirements definitions | E20: 6.4.3 Prozess der Definition von Systemanforderungen: | F20: Vorbereiten von Systemanforderungsdefinitionen | H20: 0 | I20: 2 | J20: 0 | K20: 0 | L20: 3 | M20: 2 | N20: 1 | O20: 0 | P20: 1 | Q20: 0 | R20: 0 | S20: 0 | T20: 0 | U20: 0
C21: Prozess der Architekturdefinition: | D21: Prepare for architecture definition | E21: 6.4.4 Prozess der Architekturdefinition: | F21: Vorbereiten der Architekturdefinition | H21: 0 | I21: 1 | J21: 0 | K21: 0 | L21: 3 | M21: 2 | N21: 1 | O21: 0 | P21: 0 | Q21: 0 | R21: 0 | S21: 0 | T21: 0 | U21: 0
C22: Prozess der Designdefinition: | D22: Prepare for design definitions | E22: 6.4.5 Prozess der Designdefinition: | F22: Vorbereiten von Entwurfsdefinitionen | H22: 0 | I22: 1 | J22: 0 | K22: 0 | L22: 3 | M22: 2 | N22: 2 | O22: 0 | P22: 0 | Q22: 0 | R22: 0 | S22: 0 | T22: 0 | U22: 0
C23: Prozess der Systemanalyse: | D23: Prepare for systems analysis | E23: 6.4.6 Prozess der Systemanalyse: | F23: Vorbereiten der Systemanalyse | H23: 0 | I23: 0 | J23: 0 | K23: 0 | L23: 3 | M23: 1 | N23: 0 | O23: 0 | P23: 2 | Q23: 0 | R23: 0 | S23: 0 | T23: 0 | U23: 0
C24: Umsetzungsprozess: | D24: Prepare for implementation | E24: 6.4.7 Umsetzungsprozess: | F24: Vorbereiten der Umsetzung | G24: Die Umsetzung wird geplant, indem eine Umsetzungsstrategie erarbeitet wird, d.h. es wird definiert, welches Herstellverfahren verwendet wird, welche Werkzeuge und Fertigungstoleranzen gewählt werden. | H24: 0 | I24: 0 | J24: 0 | K24: 0 | L24: 3 | M24: 0 | N24: 2 | O24: 2 | P24: 0 | Q24: 2 | R24: 0 | S24: 0 | T24: 0 | U24: 0
C25: Integrationsprozess: | D25: Prepare for integration | E25: 6.4.8 Integrationsprozess: | F25: Vorbereiten der Integration | G25: Eine Integrationsstrategie wird erarbeitet. Prüfwerkzeugen und -Einrichtungen für die Integration werden reserviert. | H25: 0 | I25: 1 | J25: 0 | K25: 0 | L25: 3 | M25: 0 | N25: 0 | O25: 1 | P25: 1 | Q25: 2 | R25: 0 | S25: 0 | T25: 0 | U25: 0
C26: Verifikationsprozess: | D26: Prepare for verification | E26: 6.4.9 Verifikationsprozess: | F26: Vorbereiten der Verifikation | G26: Verfikationstätigkeiten und zugehörige Rollen und Verantwortlichkeiten werden geplant. | H26: 0 | I26: 1 | J26: 0 | K26: 0 | L26: 3 | M26: 1 | N26: 1 | O26: 0 | P26: 2 | Q26: 0 | R26: 0 | S26: 1 | T26: 0 | U26: 0
C27: Übergabeprozess: | D27: Prepare for the transition | E27: 6.4.10 Übergabeprozess: | F27: Vorbereiten der Übergabe | G27: Installationsverfahren/ eine Übergabestrategie wird ausgearbeitet. Inhalten zur Schulung des Bedienpersonals, Logistikunterstützung, Auslieferung und Problembehebung bzw. Problemlösung müssen erarbeitet werden. | H27: 2 | I27: 2 | J27: 0 | K27: 0 | L27: 3 | M27: 0 | N27: 0 | O27: 2 | P27: 0 | Q27: 0 | R27: 2 | S27: 0 | T27: 0 | U27: 0
C28: Validierungsprozess: | D28: Prepare for validation | E28: 6.4.11 Validierungsprozess: | F28: Vorbereiten der Validierung | G28: Eine Validierungsstrategie wird entwickelt. | H28: 1 | I28: 1 | J28: 0 | K28: 0 | L28: 3 | M28: 0 | N28: 0 | O28: 0 | P28: 2 | Q28: 0 | R28: 0 | S28: 1 | T28: 0 | U28: 0
C29: Betriebsprozess: | D29: Prepare for operation | E29: 6.4.12 Betriebsprozess: | F29: Vorbereiten auf den Betrieb | G29: Vorbereitung auf den Betrieb. | H29: 2 | I29: 0 | J29: 0 | K29: 0 | L29: 3 | M29: 1 | N29: 0 | O29: 0 | P29: 0 | Q29: 0 | R29: 1 | S29: 0 | T29: 0 | U29: 0
C30: Wartungsprozess: | D30: Prepare for maintenance | E30: 6.4.13 Wartungsprozess: | F30: Vorbereiten der Wartung | G30: Eine Wartungsstrategie wird erarbeitet. Ersatzteilbestände werden überwacht und ausgebildetes Wartungspersonal wird koordiniert. | H30: 2 | I30: 0 | J30: 0 | K30: 0 | L30: 3 | M30: 1 | N30: 0 | O30: 0 | P30: 0 | Q30: 0 | R30: 2 | S30: 0 | T30: 0 | U30: 0
C31: Entsorgungsprozess: | D31: Prepare for disposal | E31: 6.4.14 Entsorgungsprozess: | F31: Vorbereitung der Entsorgung | G31: Die Entsorgungsstrategie wird geplant und das Konzept begutachtet. | H31: 2 | I31: 0 | J31: 0 | K31: 0 | L31: 3 | M31: 0 | N31: 0 | O31: 0 | P31: 0 | Q31: 0 | R31: 1 | S31: 0 | T31: 0 | U31: 0
A32: Support | B32: Weitere | C32: Support | F32: Aufnahme von Support-Anfragen/Problemen/Herausforderungen bzgl. SE-Methoden oder Tools | H32: 0 | I32: 0 | J32: 0 | K32: 2 | L32: 1 | M32: 0 | N32: 0 | O32: 0 | P32: 0 | Q32: 0 | R32: 0 | S32: 0 | T32: 0 | U32: 0
A33: Moderation | C33: Moderation | F33: Festlegen von Teilnehmer, Ziele und Agenda von (SE-) Workshops oder anderen Terminen | H33: 0 | I33: 0 | J33: 2 | K33: 2 | L33: 0 | M33: 2 | N33: 1 | O33: 0 | P33: 1 | Q33: 0 | R33: 0 | S33: 0 | T33: 0 | U33: 0
A34: Qualifikation | C34: Qualifizierung | E34: Schulung | F34: Schulungsbedarf feststellen, Qualifikatonslevel der Abteilungen ableiten | H34: 0 | I34: 0 | J34: 0 | K34: 2 | L34: 0 | M34: 0 | N34: 0 | O34: 0 | P34: 0 | Q34: 0 | R34: 0 | S34: 0 | T34: 0 | U34: 0

Sheet Kompetenz-Prozess-Matrix
B4: 0 = nicht relevant 1 = sinnvoll 2 = notwendig Prozess der ISO 15288 | D4: Kern Kompetenzen | H4: Fachkompetenzen | M4: Sozial- und Selbstkompetenzen | P4: Management- kompetenzen | X4: Kern Kompetenzen | AB4: Fachkompetenzen | AG4: Sozial- und Selbstkompetenzen | AJ4: Management- kompetenzen
D5: Systemisches Denken | E5: Systemmodellierung und -analyse | F5: Berücksichtigung von Systemlebenszyklusphasen | G5: Agiles Denken / Kunden-Nutzenorientierung | H5: Anforderungsmanagement | I5: System-Architekturgestaltung | J5: Integration, Verifikation & Validierung | K5: Betrieb, Service und Instandhaltung | L5: Agile Methodenkompetenz | M5: Selbstorganisation | N5: Kommunikation & Zusammenarbeit | O5: Führen | P5: Projektmanagement | Q5: Entscheidungsmanagement | R5: Informationsmanagement | S5: Konfigurationsmanagement | V5: Indivudual User | X5: Systemisches Denken | Y5: Systemmodellierung und -analyse | Z5: Berücksichtigung von Systemlebenszyklusphasen | AA5: Agiles Denken / Kunden-Nutzenorientierung | AB5: Anforderungsmanagement | AC5: System-Architekturgestaltung | AD5: Integration, Verifikation & Validierung | AE5: Betrieb, Service und Instandhaltung | AF5: Agile Methodenkompetenz | AG5: Selbstorganisation | AH5: Kommunikation & Zusammenarbeit | AI5: Führen | AJ5: Projektmanagement | AK5: Entscheidungsmanagement | AL5: Informationsmanagement | AM5: Konfigurationsmanagement | AN5: Highest
B6: Akquisition | C6: Vorbereiten der Anschaffung | D6: 1 | E6: 0 | F6: 0 | G6: 0 | H6: 1 | I6: 0 | J6: 0 | K6: 0 | L6: 0 | M6: 1 | N6: 2 | O6: 0 | P6: 0 | Q6: 0 | R6: 0 | S6: 0 | V6: 0 | X6: =D6*$V6 -> 0 | Y6: =E6*$V6 -> 0 | Z6: =F6*$V6 -> 0 | AA6: =G6*$V6 -> 0 | AB6: =H6*$V6 -> 0 | AC6: =I6*$V6 -> 0 | AD6: =J6*$V6 -> 0 | AE6: =K6*$V6 -> 0 | ... AM6: =S6*$V6 -> 0 | AN6: =MAX(X6:AM6) -> 0
B7: Lieferung | C7: Vorbereiten der Lieferung | D7: 1 | E7: 0 | F7: 0 | G7: 0 | H7: 1 | I7: 0 | J7: 0 | K7: 0 | L7: 0 | M7: 1 | N7: 2 | O7: 0 | P7: 0 | Q7: 0 | R7: 0 | S7: 0 | V7: 0 | X7: =D7*$V7 -> 0 | Y7: =E7*$V7 -> 0 | Z7: =F7*$V7 -> 0 | AA7: =G7*$V7 -> 0 | AB7: =H7*$V7 -> 0 | AC7: =I7*$V7 -> 0 | AD7: =J7*$V7 -> 0 | AE7: =K7*$V7 -> 0 | ... AM7: =S7*$V7 -> 0 | AN7: =MAX(X7:AM7) -> 0
B8: Lebenszyklus-Modell-Management | C8: Definition eines Prozess | D8: 2 | E8: 2 | F8: 2 | G8: 1 | H8: 2 | I8: 2 | J8: 2 | K8: 2 | L8: 2 | M8: 1 | N8: 0 | O8: 0 | P8: 2 | Q8: 2 | R8: 2 | S8: 2 | V8: 0 | X8: =D8*$V8 -> 0 | Y8: =E8*$V8 -> 0 | Z8: =F8*$V8 -> 0 | AA8: =G8*$V8 -> 0 | AB8: =H8*$V8 -> 0 | AC8: =I8*$V8 -> 0 | AD8: =J8*$V8 -> 0 | AE8: =K8*$V8 -> 0 | ... AM8: =S8*$V8 -> 0 | AN8: =MAX(X8:AM8) -> 0
B9: Verwaltung der Infrastruktur | C9: Einrichten der Infrastruktur | D9: 1 | E9: 1 | F9: 0 | G9: 0 | H9: 1 | I9: 1 | J9: 0 | K9: 0 | L9: 0 | M9: 1 | N9: 1 | O9: 1 | P9: 0 | Q9: 1 | R9: 1 | S9: 1 | V9: 0 | X9: =D9*$V9 -> 0 | Y9: =E9*$V9 -> 0 | Z9: =F9*$V9 -> 0 | AA9: =G9*$V9 -> 0 | AB9: =H9*$V9 -> 0 | AC9: =I9*$V9 -> 0 | AD9: =J9*$V9 -> 0 | AE9: =K9*$V9 -> 0 | ... AM9: =S9*$V9 -> 0 | AN9: =MAX(X9:AM9) -> 0
B10: Portfoliomanagement | C10: Definition und Genehmigung von Projekten | D10: 1 | E10: 0 | F10: 0 | G10: 0 | H10: 0 | I10: 0 | J10: 0 | K10: 0 | L10: 0 | M10: 1 | N10: 1 | O10: 2 | P10: 1 | Q10: 2 | R10: 0 | S10: 0 | V10: 2 | X10: =D10*$V10 -> 2 | Y10: =E10*$V10 -> 0 | Z10: =F10*$V10 -> 0 | AA10: =G10*$V10 -> 0 | AB10: =H10*$V10 -> 0 | AC10: =I10*$V10 -> 0 | AD10: =J10*$V10 -> 0 | AE10: =K10*$V10 -> 0 | ... AM10: =S10*$V10 -> 0 | AN10: =MAX(X10:AM10) -> 4
B11: Personalwesen-Management | C11: Idenfizierung von Fähigkeiten | D11: 1 | E11: 1 | F11: 1 | G11: 0 | H11: 0 | I11: 0 | J11: 0 | K11: 0 | L11: 0 | M11: 1 | N11: 1 | O11: 1 | P11: 0 | Q11: 0 | R11: 0 | S11: 0 | V11: 0 | X11: =D11*$V11 -> 0 | Y11: =E11*$V11 -> 0 | Z11: =F11*$V11 -> 0 | AA11: =G11*$V11 -> 0 | AB11: =H11*$V11 -> 0 | AC11: =I11*$V11 -> 0 | AD11: =J11*$V11 -> 0 | AE11: =K11*$V11 -> 0 | ... AM11: =S11*$V11 -> 0 | AN11: =MAX(X11:AM11) -> 0
B12: Qualitätsmanagement | C12: Planung des Qualitätsmanagement | D12: 1 | E12: 1 | F12: 1 | G12: 0 | H12: 2 | I12: 2 | J12: 0 | K12: 0 | L12: 0 | M12: 1 | N12: 1 | O12: 1 | P12: 2 | Q12: 0 | R12: 0 | S12: 0 | V12: 0 | X12: =D12*$V12 -> 0 | Y12: =E12*$V12 -> 0 | Z12: =F12*$V12 -> 0 | AA12: =G12*$V12 -> 0 | AB12: =H12*$V12 -> 0 | AC12: =I12*$V12 -> 0 | AD12: =J12*$V12 -> 0 | AE12: =K12*$V12 -> 0 | ... AM12: =S12*$V12 -> 0 | AN12: =MAX(X12:AM12) -> 0
B13: Wissensmanagement | C13: Planung des Wissensmanagement | D13: 1 | E13: 1 | F13: 0 | G13: 0 | H13: 0 | I13: 1 | J13: 0 | K13: 0 | L13: 0 | M13: 1 | N13: 1 | O13: 1 | P13: 0 | Q13: 0 | R13: 2 | S13: 0 | V13: 0 | X13: =D13*$V13 -> 0 | Y13: =E13*$V13 -> 0 | Z13: =F13*$V13 -> 0 | AA13: =G13*$V13 -> 0 | AB13: =H13*$V13 -> 0 | AC13: =I13*$V13 -> 0 | AD13: =J13*$V13 -> 0 | AE13: =K13*$V13 -> 0 | ... AM13: =S13*$V13 -> 0 | AN13: =MAX(X13:AM13) -> 0
B14: Projektierung/Projektplanung | C14: Definieren des Projekts | D14: 2 | E14: 0 | F14: 1 | G14: 2 | H14: 1 | I14: 1 | J14: 1 | K14: 1 | L14: 2 | M14: 2 | N14: 2 | O14: 2 | P14: 2 | Q14: 1 | R14: 1 | S14: 0 | V14: 0 | X14: =D14*$V14 -> 0 | Y14: =E14*$V14 -> 0 | Z14: =F14*$V14 -> 0 | AA14: =G14*$V14 -> 0 | AB14: =H14*$V14 -> 0 | AC14: =I14*$V14 -> 0 | AD14: =J14*$V14 -> 0 | AE14: =K14*$V14 -> 0 | ... AM14: =S14*$V14 -> 0 | AN14: =MAX(X14:AM14) -> 0
B15: Projektbewertung und Steuerung | C15: Planung zur Projektbewertung und -steuerung | D15: 1 | E15: 0 | F15: 1 | G15: 2 | H15: 1 | I15: 1 | J15: 1 | K15: 1 | L15: 2 | M15: 2 | N15: 2 | O15: 2 | P15: 2 | Q15: 1 | R15: 1 | S15: 0 | V15: 2 | X15: =D15*$V15 -> 2 | Y15: =E15*$V15 -> 0 | Z15: =F15*$V15 -> 2 | AA15: =G15*$V15 -> 4 | AB15: =H15*$V15 -> 2 | AC15: =I15*$V15 -> 2 | AD15: =J15*$V15 -> 2 | AE15: =K15*$V15 -> 2 | ... AM15: =S15*$V15 -> 0 | AN15: =MAX(X15:AM15) -> 4
B16: Entscheidungsmanagement | C16: Vorbereiten der Entscheidungen | D16: 1 | E16: 1 | F16: 2 | G16: 1 | H16: 0 | I16: 0 | J16: 0 | K16: 0 | L16: 0 | M16: 1 | N16: 1 | O16: 1 | P16: 1 | Q16: 2 | R16: 0 | S16: 0 | V16: 0 | X16: =D16*$V16 -> 0 | Y16: =E16*$V16 -> 0 | Z16: =F16*$V16 -> 0 | AA16: =G16*$V16 -> 0 | AB16: =H16*$V16 -> 0 | AC16: =I16*$V16 -> 0 | AD16: =J16*$V16 -> 0 | AE16: =K16*$V16 -> 0 | ... AM16: =S16*$V16 -> 0 | AN16: =MAX(X16:AM16) -> 0
B17: Risiko-Management | C17: Risikomanagement planen | D17: 1 | E17: 2 | F17: 2 | G17: 1 | H17: 1 | I17: 0 | J17: 0 | K17: 0 | L17: 0 | M17: 1 | N17: 1 | O17: 1 | P17: 1 | Q17: 2 | R17: 1 | S17: 0 | V17: 0 | X17: =D17*$V17 -> 0 | Y17: =E17*$V17 -> 0 | Z17: =F17*$V17 -> 0 | AA17: =G17*$V17 -> 0 | AB17: =H17*$V17 -> 0 | AC17: =I17*$V17 -> 0 | AD17: =J17*$V17 -> 0 | AE17: =K17*$V17 -> 0 | ... AM17: =S17*$V17 -> 0 | AN17: =MAX(X17:AM17) -> 0
... B38: Qualifizierung | C38: Schulungsbedarf feststellen, Qualifikatonslevel der Abteilungen ableiten | D38: 2 | E38: 2 | F38: 1 | G38: 2 | H38: 2 | I38: 2 | J38: 2 | K38: 2 | L38: 2 | M38: 2 | N38: 2 | O38: 2 | P38: 2 | Q38: 2 | R38: 2 | S38: 2 | V38: 0 | X38: =D38*$V38 -> 0 | Y38: =E38*$V38 -> 0 | Z38: =F38*$V38 -> 0 | AA38: =G38*$V38 -> 0 | AB38: =H38*$V38 -> 0 | AC38: =I38*$V38 -> 0 | AD38: =J38*$V38 -> 0 | AE38: =K38*$V38 -> 0 | ... AM38: =S38*$V38 -> 0 | AN38: =MAX(X38:AM38) -> 0

Sheet Rollen-Kompetenzen-Matrix
B2: 0 = nicht relevant 1 = anwenden 2 = verstehen 3/4 = anwenden 6 = beherrschen | D2: Kunde | E2: Kundenvertreter | F2: Projektleiter | G2: Interner Support (IT, Qualifikation, SE) | H2: Prozess- & Richtlinien-verantwortlicher​ | I2: System-Ingenieur | J2: Entwickler | K2: Produktionskoordinator/ -planer | L2: V&V-Mitarbeiter | M2: Produktionsmitarbeiter | N2: Servicetechniker | O2: Qualitätsmanager | P2: Innovations- und (Strategie)management | Q2: Management | S2: Anmerkung Leaderschulung
A3: Kern Kompetenzen | B3: Systemisches Denken | D3: =MAX(D4:D36) -> 2 | E3: =MAX(E4:E36) -> 4 | F3: =MAX(F4:F36) -> 4 | G3: =MAX(G4:G36) -> 4 | H3: =MAX(H4:H36) -> 6 | I3: =MAX(I4:I36) -> 4 | J3: =MAX(J4:J36) -> 2 | K3: =MAX(K4:K36) -> 2 | ... Q3: =MAX(Q4:Q36) -> 2 | S3: 2
C4: 6.1.1 Akquisition | D4: =PRODUCT('Rollen-Prozess-Matrix'!H2,'Kompetenz-Prozess-Matrix'!D6) -> 0 | E4: =PRODUCT('Rollen-Prozess-Matrix'!I2,'Kompetenz-Prozess-Matrix'!D6) -> 0 | F4: =PRODUCT('Rollen-Prozess-Matrix'!J2,'Kompetenz-Prozess-Matrix'!D6) -> 0 | G4: =PRODUCT('Rollen-Prozess-Matrix'!K2,'Kompetenz-Prozess-Matrix'!D6) -> 0 | H4: =PRODUCT('Rollen-Prozess-Matrix'!L2,'Kompetenz-Prozess-Matrix'!D6) -> 3 | I4: =PRODUCT('Rollen-Prozess-Matrix'!M2,'Kompetenz-Prozess-Matrix'!D6) -> 1 | J4: =PRODUCT('Rollen-Prozess-Matrix'!N2,'Kompetenz-Prozess-Matrix'!D6) -> 1 | K4: =PRODUCT('Rollen-Prozess-Matrix'!O2,'Kompetenz-Prozess-Matrix'!D6) -> 2 | L4: =PRODUCT('Rollen-Prozess-Matrix'!P2,'Kompetenz-Prozess-Matrix'!D6) -> 1 | M4: =PRODUCT('Rollen-Prozess-Matrix'!Q2,'Kompetenz-Prozess-Matrix'!D6) -> 0 | N4: =PRODUCT('Rollen-Prozess-Matrix'!R2,'Kompetenz-Prozess-Matrix'!D6) -> 0 | O4: =PRODUCT('Rollen-Prozess-Matrix'!S2,'Kompetenz-Prozess-Matrix'!D6) -> 0 | P4: =PRODUCT('Rollen-Prozess-Matrix'!T2,'Kompetenz-Prozess-Matrix'!D6) -> 0 | Q4: =PRODUCT('Rollen-Prozess-Matrix'!U2,'Kompetenz-Prozess-Matrix'!D6) -> 0
C5: 6.1.2 Lieferung | D5: =PRODUCT('Rollen-Prozess-Matrix'!H3,'Kompetenz-Prozess-Matrix'!D7) -> 0 | E5: =PRODUCT('Rollen-Prozess-Matrix'!I3,'Kompetenz-Prozess-Matrix'!D7) -> 2 | F5: =PRODUCT('Rollen-Prozess-Matrix'!J3,'Kompetenz-Prozess-Matrix'!D7) -> 1 | G5: =PRODUCT('Rollen-Prozess-Matrix'!K3,'Kompetenz-Prozess-Matrix'!D7) -> 0 | H5: =PRODUCT('Rollen-Prozess-Matrix'!L3,'Kompetenz-Prozess-Matrix'!D7) -> 3 | I5: =PRODUCT('Rollen-Prozess-Matrix'!M3,'Kompetenz-Prozess-Matrix'!D7) -> 1 | J5: =PRODUCT('Rollen-Prozess-Matrix'!N3,'Kompetenz-Prozess-Matrix'!D7) -> 0 | K5: =PRODUCT('Rollen-Prozess-Matrix'!O3,'Kompetenz-Prozess-Matrix'!D7) -> 1 | L5: =PRODUCT('Rollen-Prozess-Matrix'!P3,'Kompetenz-Prozess-Matrix'!D7) -> 0 | M5: =PRODUCT('Rollen-Prozess-Matrix'!Q3,'Kompetenz-Prozess-Matrix'!D7) -> 0 | N5: =PRODUCT('Rollen-Prozess-Matrix'!R3,'Kompetenz-Prozess-Matrix'!D7) -> 1 | O5: =PRODUCT('Rollen-Prozess-Matrix'!S3,'Kompetenz-Prozess-Matrix'!D7) -> 0 | P5: =PRODUCT('Rollen-Prozess-Matrix'!T3,'Kompetenz-Prozess-Matrix'!D7) -> 0 | Q5: =PRODUCT('Rollen-Prozess-Matrix'!U3,'Kompetenz-Prozess-Matrix'!D7) -> 0
C6: 6.2.1 Lebenszyklus-Modell-Management | D6: =PRODUCT('Rollen-Prozess-Matrix'!H4,'Kompetenz-Prozess-Matrix'!D8) -> 0 | E6: =PRODUCT('Rollen-Prozess-Matrix'!I4,'Kompetenz-Prozess-Matrix'!D8) -> 0 | F6: =PRODUCT('Rollen-Prozess-Matrix'!J4,'Kompetenz-Prozess-Matrix'!D8) -> 0 | G6: =PRODUCT('Rollen-Prozess-Matrix'!K4,'Kompetenz-Prozess-Matrix'!D8) -> 2 | H6: =PRODUCT('Rollen-Prozess-Matrix'!L4,'Kompetenz-Prozess-Matrix'!D8) -> 6 | I6: =PRODUCT('Rollen-Prozess-Matrix'!M4,'Kompetenz-Prozess-Matrix'!D8) -> 0 | J6: =PRODUCT('Rollen-Prozess-Matrix'!N4,'Kompetenz-Prozess-Matrix'!D8) -> 0 | K6: =PRODUCT('Rollen-Prozess-Matrix'!O4,'Kompetenz-Prozess-Matrix'!D8) -> 0 | L6: =PRODUCT('Rollen-Prozess-Matrix'!P4,'Kompetenz-Prozess-Matrix'!D8) -> 0 | M6: =PRODUCT('Rollen-Prozess-Matrix'!Q4,'Kompetenz-Prozess-Matrix'!D8) -> 0 | N6: =PRODUCT('Rollen-Prozess-Matrix'!R4,'Kompetenz-Prozess-Matrix'!D8) -> 0 | O6: =PRODUCT('Rollen-Prozess-Matrix'!S4,'Kompetenz-Prozess-Matrix'!D8) -> 0 | P6: =PRODUCT('Rollen-Prozess-Matrix'!T4,'Kompetenz-Prozess-Matrix'!D8) -> 0 | Q6: =PRODUCT('Rollen-Prozess-Matrix'!U4,'Kompetenz-Prozess-Matrix'!D8) -> 0
C7: 6.2.2 Verwaltung der Infrastruktur | D7: =PRODUCT('Rollen-Prozess-Matrix'!H5,'Kompetenz-Prozess-Matrix'!D9) -> 0 | E7: =PRODUCT('Rollen-Prozess-Matrix'!I5,'Kompetenz-Prozess-Matrix'!D9) -> 0 | F7: =PRODUCT('Rollen-Prozess-Matrix'!J5,'Kompetenz-Prozess-Matrix'!D9) -> 0 | G7: =PRODUCT('Rollen-Prozess-Matrix'!K5,'Kompetenz-Prozess-Matrix'!D9) -> 2 | H7: =PRODUCT('Rollen-Prozess-Matrix'!L5,'Kompetenz-Prozess-Matrix'!D9) -> 3 | I7: =PRODUCT('Rollen-Prozess-Matrix'!M5,'Kompetenz-Prozess-Matrix'!D9) -> 0 | J7: =PRODUCT('Rollen-Prozess-Matrix'!N5,'Kompetenz-Prozess-Matrix'!D9) -> 0 | K7: =PRODUCT('Rollen-Prozess-Matrix'!O5,'Kompetenz-Prozess-Matrix'!D9) -> 0 | L7: =PRODUCT('Rollen-Prozess-Matrix'!P5,'Kompetenz-Prozess-Matrix'!D9) -> 0 | M7: =PRODUCT('Rollen-Prozess-Matrix'!Q5,'Kompetenz-Prozess-Matrix'!D9) -> 0 | N7: =PRODUCT('Rollen-Prozess-Matrix'!R5,'Kompetenz-Prozess-Matrix'!D9) -> 0 | O7: =PRODUCT('Rollen-Prozess-Matrix'!S5,'Kompetenz-Prozess-Matrix'!D9) -> 0 | P7: =PRODUCT('Rollen-Prozess-Matrix'!T5,'Kompetenz-Prozess-Matrix'!D9) -> 0 | Q7: =PRODUCT('Rollen-Prozess-Matrix'!U5,'Kompetenz-Prozess-Matrix'!D9) -> 0
C8: 6.2.3 Portfoliomanagement | D8: =PRODUCT('Rollen-Prozess-Matrix'!H6,'Kompetenz-Prozess-Matrix'!D10) -> 0 | E8: =PRODUCT('Rollen-Prozess-Matrix'!I6,'Kompetenz-Prozess-Matrix'!D10) -> 1 | F8: =PRODUCT('Rollen-Prozess-Matrix'!J6,'Kompetenz-Prozess-Matrix'!D10) -> 1 | G8: =PRODUCT('Rollen-Prozess-Matrix'!K6,'Kompetenz-Prozess-Matrix'!D10) -> 0 | H8: =PRODUCT('Rollen-Prozess-Matrix'!L6,'Kompetenz-Prozess-Matrix'!D10) -> 3 | I8: =PRODUCT('Rollen-Prozess-Matrix'!M6,'Kompetenz-Prozess-Matrix'!D10) -> 0 | J8: =PRODUCT('Rollen-Prozess-Matrix'!N6,'Kompetenz-Prozess-Matrix'!D10) -> 0 | K8: =PRODUCT('Rollen-Prozess-Matrix'!O6,'Kompetenz-Prozess-Matrix'!D10) -> 0 | L8: =PRODUCT('Rollen-Prozess-Matrix'!P6,'Kompetenz-Prozess-Matrix'!D10) -> 0 | M8: =PRODUCT('Rollen-Prozess-Matrix'!Q6,'Kompetenz-Prozess-Matrix'!D10) -> 0 | N8: =PRODUCT('Rollen-Prozess-Matrix'!R6,'Kompetenz-Prozess-Matrix'!D10) -> 0 | O8: =PRODUCT('Rollen-Prozess-Matrix'!S6,'Kompetenz-Prozess-Matrix'!D10) -> 0 | P8: =PRODUCT('Rollen-Prozess-Matrix'!T6,'Kompetenz-Prozess-Matrix'!D10) -> 2 | Q8: =PRODUCT('Rollen-Prozess-Matrix'!U6,'Kompetenz-Prozess-Matrix'!D10) -> 1
C9: 6.2.4 Personalwesen-Management | D9: =PRODUCT('Rollen-Prozess-Matrix'!H7,'Kompetenz-Prozess-Matrix'!D11) -> 0 | E9: =PRODUCT('Rollen-Prozess-Matrix'!I7,'Kompetenz-Prozess-Matrix'!D11) -> 0 | F9: =PRODUCT('Rollen-Prozess-Matrix'!J7,'Kompetenz-Prozess-Matrix'!D11) -> 0 | G9: =PRODUCT('Rollen-Prozess-Matrix'!K7,'Kompetenz-Prozess-Matrix'!D11) -> 2 | H9: =PRODUCT('Rollen-Prozess-Matrix'!L7,'Kompetenz-Prozess-Matrix'!D11) -> 3 | I9: =PRODUCT('Rollen-Prozess-Matrix'!M7,'Kompetenz-Prozess-Matrix'!D11) -> 0 | J9: =PRODUCT('Rollen-Prozess-Matrix'!N7,'Kompetenz-Prozess-Matrix'!D11) -> 0 | K9: =PRODUCT('Rollen-Prozess-Matrix'!O7,'Kompetenz-Prozess-Matrix'!D11) -> 0 | L9: =PRODUCT('Rollen-Prozess-Matrix'!P7,'Kompetenz-Prozess-Matrix'!D11) -> 0 | M9: =PRODUCT('Rollen-Prozess-Matrix'!Q7,'Kompetenz-Prozess-Matrix'!D11) -> 0 | N9: =PRODUCT('Rollen-Prozess-Matrix'!R7,'Kompetenz-Prozess-Matrix'!D11) -> 0 | O9: =PRODUCT('Rollen-Prozess-Matrix'!S7,'Kompetenz-Prozess-Matrix'!D11) -> 0 | P9: =PRODUCT('Rollen-Prozess-Matrix'!T7,'Kompetenz-Prozess-Matrix'!D11) -> 0 | Q9: =PRODUCT('Rollen-Prozess-Matrix'!U7,'Kompetenz-Prozess-Matrix'!D11) -> 1
C10: 6.2.5 Qualitätsmanagement | D10: =PRODUCT('Rollen-Prozess-Matrix'!H8,'Kompetenz-Prozess-Matrix'!D12) -> 0 | E10: =PRODUCT('Rollen-Prozess-Matrix'!I8,'Kompetenz-Prozess-Matrix'!D12) -> 0 | F10: =PRODUCT('Rollen-Prozess-Matrix'!J8,'Kompetenz-Prozess-Matrix'!D12) -> 0 | G10: =PRODUCT('Rollen-Prozess-Matrix'!K8,'Kompetenz-Prozess-Matrix'!D12) -> 0 | H10: =PRODUCT('Rollen-Prozess-Matrix'!L8,'Kompetenz-Prozess-Matrix'!D12) -> 3 | I10: =PRODUCT('Rollen-Prozess-Matrix'!M8,'Kompetenz-Prozess-Matrix'!D12) -> 0 | J10: =PRODUCT('Rollen-Prozess-Matrix'!N8,'Kompetenz-Prozess-Matrix'!D12) -> 0 | K10: =PRODUCT('Rollen-Prozess-Matrix'!O8,'Kompetenz-Prozess-Matrix'!D12) -> 0 | L10: =PRODUCT('Rollen-Prozess-Matrix'!P8,'Kompetenz-Prozess-Matrix'!D12) -> 1 | M10: =PRODUCT('Rollen-Prozess-Matrix'!Q8,'Kompetenz-Prozess-Matrix'!D12) -> 0 | N10: =PRODUCT('Rollen-Prozess-Matrix'!R8,'Kompetenz-Prozess-Matrix'!D12) -> 0 | O10: =PRODUCT('Rollen-Prozess-Matrix'!S8,'Kompetenz-Prozess-Matrix'!D12) -> 2 | P10: =PRODUCT('Rollen-Prozess-Matrix'!T8,'Kompetenz-Prozess-Matrix'!D12) -> 0 | Q10: =PRODUCT('Rollen-Prozess-Matrix'!U8,'Kompetenz-Prozess-Matrix'!D12) -> 0
C11: 6.2.6 Wissensmanagement | D11: =PRODUCT('Rollen-Prozess-Matrix'!H9,'Kompetenz-Prozess-Matrix'!D13) -> 0 | E11: =PRODUCT('Rollen-Prozess-Matrix'!I9,'Kompetenz-Prozess-Matrix'!D13) -> 0 | F11: =PRODUCT('Rollen-Prozess-Matrix'!J9,'Kompetenz-Prozess-Matrix'!D13) -> 0 | G11: =PRODUCT('Rollen-Prozess-Matrix'!K9,'Kompetenz-Prozess-Matrix'!D13) -> 2 | H11: =PRODUCT('Rollen-Prozess-Matrix'!L9,'Kompetenz-Prozess-Matrix'!D13) -> 3 | I11: =PRODUCT('Rollen-Prozess-Matrix'!M9,'Kompetenz-Prozess-Matrix'!D13) -> 0 | J11: =PRODUCT('Rollen-Prozess-Matrix'!N9,'Kompetenz-Prozess-Matrix'!D13) -> 0 | K11: =PRODUCT('Rollen-Prozess-Matrix'!O9,'Kompetenz-Prozess-Matrix'!D13) -> 0 | L11: =PRODUCT('Rollen-Prozess-Matrix'!P9,'Kompetenz-Prozess-Matrix'!D13) -> 0 | M11: =PRODUCT('Rollen-Prozess-Matrix'!Q9,'Kompetenz-Prozess-Matrix'!D13) -> 0 | N11: =PRODUCT('Rollen-Prozess-Matrix'!R9,'Kompetenz-Prozess-Matrix'!D13) -> 0 | O11: =PRODUCT('Rollen-Prozess-Matrix'!S9,'Kompetenz-Prozess-Matrix'!D13) -> 0 | P11: =PRODUCT('Rollen-Prozess-Matrix'!T9,'Kompetenz-Prozess-Matrix'!D13) -> 0 | Q11: =PRODUCT('Rollen-Prozess-Matrix'!U9,'Kompetenz-Prozess-Matrix'!D13) -> 0
C12: 6.3.1 Projektierung/Projektplanung | D12: =PRODUCT('Rollen-Prozess-Matrix'!H10,'Kompetenz-Prozess-Matrix'!D14) -> 0 | E12: =PRODUCT('Rollen-Prozess-Matrix'!I10,'Kompetenz-Prozess-Matrix'!D14) -> 0 | F12: =PRODUCT('Rollen-Prozess-Matrix'!J10,'Kompetenz-Prozess-Matrix'!D14) -> 4 | G12: =PRODUCT('Rollen-Prozess-Matrix'!K10,'Kompetenz-Prozess-Matrix'!D14) -> 0 | H12: =PRODUCT('Rollen-Prozess-Matrix'!L10,'Kompetenz-Prozess-Matrix'!D14) -> 6 | I12: =PRODUCT('Rollen-Prozess-Matrix'!M10,'Kompetenz-Prozess-Matrix'!D14) -> 0 | J12: =PRODUCT('Rollen-Prozess-Matrix'!N10,'Kompetenz-Prozess-Matrix'!D14) -> 0 | K12: =PRODUCT('Rollen-Prozess-Matrix'!O10,'Kompetenz-Prozess-Matrix'!D14) -> 0 | L12: =PRODUCT('Rollen-Prozess-Matrix'!P10,'Kompetenz-Prozess-Matrix'!D14) -> 0 | M12: =PRODUCT('Rollen-Prozess-Matrix'!Q10,'Kompetenz-Prozess-Matrix'!D14) -> 0 | N12: =PRODUCT('Rollen-Prozess-Matrix'!R10,'Kompetenz-Prozess-Matrix'!D14) -> 0 | O12: =PRODUCT('Rollen-Prozess-Matrix'!S10,'Kompetenz-Prozess-Matrix'!D14) -> 0 | P12: =PRODUCT('Rollen-Prozess-Matrix'!T10,'Kompetenz-Prozess-Matrix'!D14) -> 0 | Q12: =PRODUCT('Rollen-Prozess-Matrix'!U10,'Kompetenz-Prozess-Matrix'!D14) -> 0
C13: 6.3.2 Projektbewertung und Steuerung | D13: =PRODUCT('Rollen-Prozess-Matrix'!H11,'Kompetenz-Prozess-Matrix'!D15) -> 0 | E13: =PRODUCT('Rollen-Prozess-Matrix'!I11,'Kompetenz-Prozess-Matrix'!D15) -> 0 | F13: =PRODUCT('Rollen-Prozess-Matrix'!J11,'Kompetenz-Prozess-Matrix'!D15) -> 2 | G13: =PRODUCT('Rollen-Prozess-Matrix'!K11,'Kompetenz-Prozess-Matrix'!D15) -> 0 | H13: =PRODUCT('Rollen-Prozess-Matrix'!L11,'Kompetenz-Prozess-Matrix'!D15) -> 3 | I13: =PRODUCT('Rollen-Prozess-Matrix'!M11,'Kompetenz-Prozess-Matrix'!D15) -> 0 | J13: =PRODUCT('Rollen-Prozess-Matrix'!N11,'Kompetenz-Prozess-Matrix'!D15) -> 0 | K13: =PRODUCT('Rollen-Prozess-Matrix'!O11,'Kompetenz-Prozess-Matrix'!D15) -> 0 | L13: =PRODUCT('Rollen-Prozess-Matrix'!P11,'Kompetenz-Prozess-Matrix'!D15) -> 0 | M13: =PRODUCT('Rollen-Prozess-Matrix'!Q11,'Kompetenz-Prozess-Matrix'!D15) -> 0 | N13: =PRODUCT('Rollen-Prozess-Matrix'!R11,'Kompetenz-Prozess-Matrix'!D15) -> 0 | O13: =PRODUCT('Rollen-Prozess-Matrix'!S11,'Kompetenz-Prozess-Matrix'!D15) -> 0 | P13: =PRODUCT('Rollen-Prozess-Matrix'!T11,'Kompetenz-Prozess-Matrix'!D15) -> 0 | Q13: =PRODUCT('Rollen-Prozess-Matrix'!U11,'Kompetenz-Prozess-Matrix'!D15) -> 1
C14: 6.3.3 Entscheidungsmanagement | D14: =PRODUCT('Rollen-Prozess-Matrix'!H12,'Kompetenz-Prozess-Matrix'!D16) -> 0 | E14: =PRODUCT('Rollen-Prozess-Matrix'!I12,'Kompetenz-Prozess-Matrix'!D16) -> 2 | F14: =PRODUCT('Rollen-Prozess-Matrix'!J12,'Kompetenz-Prozess-Matrix'!D16) -> 2 | G14: =PRODUCT('Rollen-Prozess-Matrix'!K12,'Kompetenz-Prozess-Matrix'!D16) -> 0 | H14: =PRODUCT('Rollen-Prozess-Matrix'!L12,'Kompetenz-Prozess-Matrix'!D16) -> 3 | I14: =PRODUCT('Rollen-Prozess-Matrix'!M12,'Kompetenz-Prozess-Matrix'!D16) -> 2 | J14: =PRODUCT('Rollen-Prozess-Matrix'!N12,'Kompetenz-Prozess-Matrix'!D16) -> 1 | K14: =PRODUCT('Rollen-Prozess-Matrix'!O12,'Kompetenz-Prozess-Matrix'!D16) -> 1 | L14: =PRODUCT('Rollen-Prozess-Matrix'!P12,'Kompetenz-Prozess-Matrix'!D16) -> 1 | M14: =PRODUCT('Rollen-Prozess-Matrix'!Q12,'Kompetenz-Prozess-Matrix'!D16) -> 0 | N14: =PRODUCT('Rollen-Prozess-Matrix'!R12,'Kompetenz-Prozess-Matrix'!D16) -> 0 | O14: =PRODUCT('Rollen-Prozess-Matrix'!S12,'Kompetenz-Prozess-Matrix'!D16) -> 0 | P14: =PRODUCT('Rollen-Prozess-Matrix'!T12,'Kompetenz-Prozess-Matrix'!D16) -> 1 | Q14: =PRODUCT('Rollen-Prozess-Matrix'!U12,'Kompetenz-Prozess-Matrix'!D16) -> 2
C15: 6.3.4 Risiko-Management | D15: =PRODUCT('Rollen-Prozess-Matrix'!H13,'Kompetenz-Prozess-Matrix'!D17) -> 0 | E15: =PRODUCT('Rollen-Prozess-Matrix'!I13,'Kompetenz-Prozess-Matrix'!D17) -> 1 | F15: =PRODUCT('Rollen-Prozess-Matrix'!J13,'Kompetenz-Prozess-Matrix'!D17) -> 2 | G15: =PRODUCT('Rollen-Prozess-Matrix'!K13,'Kompetenz-Prozess-Matrix'!D17) -> 0 | H15: =PRODUCT('Rollen-Prozess-Matrix'!L13,'Kompetenz-Prozess-Matrix'!D17) -> 3 | I15: =PRODUCT('Rollen-Prozess-Matrix'!M13,'Kompetenz-Prozess-Matrix'!D17) -> 2 | J15: =PRODUCT('Rollen-Prozess-Matrix'!N13,'Kompetenz-Prozess-Matrix'!D17) -> 1 | K15: =PRODUCT('Rollen-Prozess-Matrix'!O13,'Kompetenz-Prozess-Matrix'!D17) -> 1 | L15: =PRODUCT('Rollen-Prozess-Matrix'!P13,'Kompetenz-Prozess-Matrix'!D17) -> 0 | M15: =PRODUCT('Rollen-Prozess-Matrix'!Q13,'Kompetenz-Prozess-Matrix'!D17) -> 0 | N15: =PRODUCT('Rollen-Prozess-Matrix'!R13,'Kompetenz-Prozess-Matrix'!D17) -> 0 | O15: =PRODUCT('Rollen-Prozess-Matrix'!S13,'Kompetenz-Prozess-Matrix'!D17) -> 1 | P15: =PRODUCT('Rollen-Prozess-Matrix'!T13,'Kompetenz-Prozess-Matrix'!D17) -> 0 | Q15: =PRODUCT('Rollen-Prozess-Matrix'!U13,'Kompetenz-Prozess-Matrix'!D17) -> 0
... C36: Qualifizierung | D36: =PRODUCT('Rollen-Prozess-Matrix'!H34,'Kompetenz-Prozess-Matrix'!D38) -> 0 | E36: =PRODUCT('Rollen-Prozess-Matrix'!I34,'Kompetenz-Prozess-Matrix'!D38) -> 0 | F36: =PRODUCT('Rollen-Prozess-Matrix'!J34,'Kompetenz-Prozess-Matrix'!D38) -> 0 | G36: =PRODUCT('Rollen-Prozess-Matrix'!K34,'Kompetenz-Prozess-Matrix'!D38) -> 4 | H36: =PRODUCT('Rollen-Prozess-Matrix'!L34,'Kompetenz-Prozess-Matrix'!D38) -> 0 | I36: =PRODUCT('Rollen-Prozess-Matrix'!M34,'Kompetenz-Prozess-Matrix'!D38) -> 0 | J36: =PRODUCT('Rollen-Prozess-Matrix'!N34,'Kompetenz-Prozess-Matrix'!D38) -> 0 | K36: =PRODUCT('Rollen-Prozess-Matrix'!O34,'Kompetenz-Prozess-Matrix'!D38) -> 0 | L36: =PRODUCT('Rollen-Prozess-Matrix'!P34,'Kompetenz-Prozess-Matrix'!D38) -> 0 | M36: =PRODUCT('Rollen-Prozess-Matrix'!Q34,'Kompetenz-Prozess-Matrix'!D38) -> 0 | N36: =PRODUCT('Rollen-Prozess-Matrix'!R34,'Kompetenz-Prozess-Matrix'!D38) -> 0 | O36: =PRODUCT('Rollen-Prozess-Matrix'!S34,'Kompetenz-Prozess-Matrix'!D38) -> 0 | P36: =PRODUCT('Rollen-Prozess-Matrix'!T34,'Kompetenz-Prozess-Matrix'!D38) -> 0 | Q36: =PRODUCT('Rollen-Prozess-Matrix'!U34,'Kompetenz-Prozess-Matrix'!D38) -> 0
B37: Systemmodellierung und -analyse | D37: =MAX(D38:D70) -> 2 | E37: =MAX(E38:E70) -> 4 | F37: =MAX(F38:F70) -> 4 | G37: =MAX(G38:G70) -> 4 | H37: =MAX(H38:H70) -> 6 | I37: =MAX(I38:I70) -> 4 | J37: =MAX(J38:J70) -> 4 | K37: =MAX(K38:K70) -> 2 | ... Q37: =MAX(Q38:Q70) -> 2 | S37: 1
C38: 6.1.1 Akquisition | D38: =PRODUCT('Rollen-Prozess-Matrix'!H2,'Kompetenz-Prozess-Matrix'!E6) -> 0 | E38: =PRODUCT('Rollen-Prozess-Matrix'!I2,'Kompetenz-Prozess-Matrix'!E6) -> 0 | F38: =PRODUCT('Rollen-Prozess-Matrix'!J2,'Kompetenz-Prozess-Matrix'!E6) -> 0 | G38: =PRODUCT('Rollen-Prozess-Matrix'!K2,'Kompetenz-Prozess-Matrix'!E6) -> 0 | H38: =PRODUCT('Rollen-Prozess-Matrix'!L2,'Kompetenz-Prozess-Matrix'!E6) -> 0 | I38: =PRODUCT('Rollen-Prozess-Matrix'!M2,'Kompetenz-Prozess-Matrix'!E6) -> 0 | J38: =PRODUCT('Rollen-Prozess-Matrix'!N2,'Kompetenz-Prozess-Matrix'!E6) -> 0 | K38: =PRODUCT('Rollen-Prozess-Matrix'!O2,'Kompetenz-Prozess-Matrix'!E6) -> 0 | L38: =PRODUCT('Rollen-Prozess-Matrix'!P2,'Kompetenz-Prozess-Matrix'!E6) -> 0 | M38: =PRODUCT('Rollen-Prozess-Matrix'!Q2,'Kompetenz-Prozess-Matrix'!E6) -> 0 | N38: =PRODUCT('Rollen-Prozess-Matrix'!R2,'Kompetenz-Prozess-Matrix'!E6) -> 0 | O38: =PRODUCT('Rollen-Prozess-Matrix'!S2,'Kompetenz-Prozess-Matrix'!E6) -> 0 | P38: =PRODUCT('Rollen-Prozess-Matrix'!T2,'Kompetenz-Prozess-Matrix'!E6) -> 0 | Q38: =PRODUCT('Rollen-Prozess-Matrix'!U2,'Kompetenz-Prozess-Matrix'!E6) -> 0
C39: 6.1.2 Lieferung | D39: =PRODUCT('Rollen-Prozess-Matrix'!H3,'Kompetenz-Prozess-Matrix'!E7) -> 0 | E39: =PRODUCT('Rollen-Prozess-Matrix'!I3,'Kompetenz-Prozess-Matrix'!E7) -> 0 | F39: =PRODUCT('Rollen-Prozess-Matrix'!J3,'Kompetenz-Prozess-Matrix'!E7) -> 0 | G39: =PRODUCT('Rollen-Prozess-Matrix'!K3,'Kompetenz-Prozess-Matrix'!E7) -> 0 | H39: =PRODUCT('Rollen-Prozess-Matrix'!L3,'Kompetenz-Prozess-Matrix'!E7) -> 0 | I39: =PRODUCT('Rollen-Prozess-Matrix'!M3,'Kompetenz-Prozess-Matrix'!E7) -> 0 | J39: =PRODUCT('Rollen-Prozess-Matrix'!N3,'Kompetenz-Prozess-Matrix'!E7) -> 0 | K39: =PRODUCT('Rollen-Prozess-Matrix'!O3,'Kompetenz-Prozess-Matrix'!E7) -> 0 | L39: =PRODUCT('Rollen-Prozess-Matrix'!P3,'Kompetenz-Prozess-Matrix'!E7) -> 0 | M39: =PRODUCT('Rollen-Prozess-Matrix'!Q3,'Kompetenz-Prozess-Matrix'!E7) -> 0 | N39: =PRODUCT('Rollen-Prozess-Matrix'!R3,'Kompetenz-Prozess-Matrix'!E7) -> 0 | O39: =PRODUCT('Rollen-Prozess-Matrix'!S3,'Kompetenz-Prozess-Matrix'!E7) -> 0 | P39: =PRODUCT('Rollen-Prozess-Matrix'!T3,'Kompetenz-Prozess-Matrix'!E7) -> 0 | Q39: =PRODUCT('Rollen-Prozess-Matrix'!U3,'Kompetenz-Prozess-Matrix'!E7) -> 0
C40: 6.2.1 Lebenszyklus-Modell-Management | D40: =PRODUCT('Rollen-Prozess-Matrix'!H4,'Kompetenz-Prozess-Matrix'!E8) -> 0 | E40: =PRODUCT('Rollen-Prozess-Matrix'!I4,'Kompetenz-Prozess-Matrix'!E8) -> 0 | F40: =PRODUCT('Rollen-Prozess-Matrix'!J4,'Kompetenz-Prozess-Matrix'!E8) -> 0 | G40: =PRODUCT('Rollen-Prozess-Matrix'!K4,'Kompetenz-Prozess-Matrix'!E8) -> 2 | H40: =PRODUCT('Rollen-Prozess-Matrix'!L4,'Kompetenz-Prozess-Matrix'!E8) -> 6 | I40: =PRODUCT('Rollen-Prozess-Matrix'!M4,'Kompetenz-Prozess-Matrix'!E8) -> 0 | J40: =PRODUCT('Rollen-Prozess-Matrix'!N4,'Kompetenz-Prozess-Matrix'!E8) -> 0 | K40: =PRODUCT('Rollen-Prozess-Matrix'!O4,'Kompetenz-Prozess-Matrix'!E8) -> 0 | L40: =PRODUCT('Rollen-Prozess-Matrix'!P4,'Kompetenz-Prozess-Matrix'!E8) -> 0 | M40: =PRODUCT('Rollen-Prozess-Matrix'!Q4,'Kompetenz-Prozess-Matrix'!E8) -> 0 | N40: =PRODUCT('Rollen-Prozess-Matrix'!R4,'Kompetenz-Prozess-Matrix'!E8) -> 0 | O40: =PRODUCT('Rollen-Prozess-Matrix'!S4,'Kompetenz-Prozess-Matrix'!E8) -> 0 | P40: =PRODUCT('Rollen-Prozess-Matrix'!T4,'Kompetenz-Prozess-Matrix'!E8) -> 0 | Q40: =PRODUCT('Rollen-Prozess-Matrix'!U4,'Kompetenz-Prozess-Matrix'!E8) -> 0
C41: 6.2.2 Verwaltung der Infrastruktur | D41: =PRODUCT('Rollen-Prozess-Matrix'!H5,'Kompetenz-Prozess-Matrix'!E9) -> 0 | E41: =PRODUCT('Rollen-Prozess-Matrix'!I5,'Kompetenz-Prozess-Matrix'!E9) -> 0 | F41: =PRODUCT('Rollen-Prozess-Matrix'!J5,'Kompetenz-Prozess-Matrix'!E9) -> 0 | G41: =PRODUCT('Rollen-Prozess-Matrix'!K5,'Kompetenz-Prozess-Matrix'!E9) -> 2 | H41: =PRODUCT('Rollen-Prozess-Matrix'!L5,'Kompetenz-Prozess-Matrix'!E9) -> 3 | I41: =PRODUCT('Rollen-Prozess-Matrix'!M5,'Kompetenz-Prozess-Matrix'!E9) -> 0 | J41: =PRODUCT('Rollen-Prozess-Matrix'!N5,'Kompetenz-Prozess-Matrix'!E9) -> 0 | K41: =PRODUCT('Rollen-Prozess-Matrix'!O5,'Kompetenz-Prozess-Matrix'!E9) -> 0 | L41: =PRODUCT('Rollen-Prozess-Matrix'!P5,'Kompetenz-Prozess-Matrix'!E9) -> 0 | M41: =PRODUCT('Rollen-Prozess-Matrix'!Q5,'Kompetenz-Prozess-Matrix'!E9) -> 0 | N41: =PRODUCT('Rollen-Prozess-Matrix'!R5,'Kompetenz-Prozess-Matrix'!E9) -> 0 | O41: =PRODUCT('Rollen-Prozess-Matrix'!S5,'Kompetenz-Prozess-Matrix'!E9) -> 0 | P41: =PRODUCT('Rollen-Prozess-Matrix'!T5,'Kompetenz-Prozess-Matrix'!E9) -> 0 | Q41: =PRODUCT('Rollen-Prozess-Matrix'!U5,'Kompetenz-Prozess-Matrix'!E9) -> 0
C42: 6.2.3 Portfoliomanagement | D42: =PRODUCT('Rollen-Prozess-Matrix'!H6,'Kompetenz-Prozess-Matrix'!E10) -> 0 | E42: =PRODUCT('Rollen-Prozess-Matrix'!I6,'Kompetenz-Prozess-Matrix'!E10) -> 0 | F42: =PRODUCT('Rollen-Prozess-Matrix'!J6,'Kompetenz-Prozess-Matrix'!E10) -> 0 | G42: =PRODUCT('Rollen-Prozess-Matrix'!K6,'Kompetenz-Prozess-Matrix'!E10) -> 0 | H42: =PRODUCT('Rollen-Prozess-Matrix'!L6,'Kompetenz-Prozess-Matrix'!E10) -> 0 | I42: =PRODUCT('Rollen-Prozess-Matrix'!M6,'Kompetenz-Prozess-Matrix'!E10) -> 0 | J42: =PRODUCT('Rollen-Prozess-Matrix'!N6,'Kompetenz-Prozess-Matrix'!E10) -> 0 | K42: =PRODUCT('Rollen-Prozess-Matrix'!O6,'Kompetenz-Prozess-Matrix'!E10) -> 0 | L42: =PRODUCT('Rollen-Prozess-Matrix'!P6,'Kompetenz-Prozess-Matrix'!E10) -> 0 | M42: =PRODUCT('Rollen-Prozess-Matrix'!Q6,'Kompetenz-Prozess-Matrix'!E10) -> 0 | N42: =PRODUCT('Rollen-Prozess-Matrix'!R6,'Kompetenz-Prozess-Matrix'!E10) -> 0 | O42: =PRODUCT('Rollen-Prozess-Matrix'!S6,'Kompetenz-Prozess-Matrix'!E10) -> 0 | P42: =PRODUCT('Rollen-Prozess-Matrix'!T6,'Kompetenz-Prozess-Matrix'!E10) -> 0 | Q42: =PRODUCT('Rollen-Prozess-Matrix'!U6,'Kompetenz-Prozess-Matrix'!E10) -> 0
C43: 6.2.4 Personalwesen-Management | D43: =PRODUCT('Rollen-Prozess-Matrix'!H7,'Kompetenz-Prozess-Matrix'!E11) -> 0 | E43: =PRODUCT('Rollen-Prozess-Matrix'!I7,'Kompetenz-Prozess-Matrix'!E11) -> 0 | F43: =PRODUCT('Rollen-Prozess-Matrix'!J7,'Kompetenz-Prozess-Matrix'!E11) -> 0 | G43: =PRODUCT('Rollen-Prozess-Matrix'!K7,'Kompetenz-Prozess-Matrix'!E11) -> 2 | H43: =PRODUCT('Rollen-Prozess-Matrix'!L7,'Kompetenz-Prozess-Matrix'!E11) -> 3 | I43: =PRODUCT('Rollen-Prozess-Matrix'!M7,'Kompetenz-Prozess-Matrix'!E11) -> 0 | J43: =PRODUCT('Rollen-Prozess-Matrix'!N7,'Kompetenz-Prozess-Matrix'!E11) -> 0 | K43: =PRODUCT('Rollen-Prozess-Matrix'!O7,'Kompetenz-Prozess-Matrix'!E11) -> 0 | L43: =PRODUCT('Rollen-Prozess-Matrix'!P7,'Kompetenz-Prozess-Matrix'!E11) -> 0 | M43: =PRODUCT('Rollen-Prozess-Matrix'!Q7,'Kompetenz-Prozess-Matrix'!E11) -> 0 | N43: =PRODUCT('Rollen-Prozess-Matrix'!R7,'Kompetenz-Prozess-Matrix'!E11) -> 0 | O43: =PRODUCT('Rollen-Prozess-Matrix'!S7,'Kompetenz-Prozess-Matrix'!E11) -> 0 | P43: =PRODUCT('Rollen-Prozess-Matrix'!T7,'Kompetenz-Prozess-Matrix'!E11) -> 0 | Q43: =PRODUCT('Rollen-Prozess-Matrix'!U7,'Kompetenz-Prozess-Matrix'!E11) -> 1
C44: 6.2.5 Qualitätsmanagement | D44: =PRODUCT('Rollen-Prozess-Matrix'!H8,'Kompetenz-Prozess-Matrix'!E12) -> 0 | E44: =PRODUCT('Rollen-Prozess-Matrix'!I8,'Kompetenz-Prozess-Matrix'!E12) -> 0 | F44: =PRODUCT('Rollen-Prozess-Matrix'!J8,'Kompetenz-Prozess-Matrix'!E12) -> 0 | G44: =PRODUCT('Rollen-Prozess-Matrix'!K8,'Kompetenz-Prozess-Matrix'!E12) -> 0 | H44: =PRODUCT('Rollen-Prozess-Matrix'!L8,'Kompetenz-Prozess-Matrix'!E12) -> 3 | I44: =PRODUCT('Rollen-Prozess-Matrix'!M8,'Kompetenz-Prozess-Matrix'!E12) -> 0 | J44: =PRODUCT('Rollen-Prozess-Matrix'!N8,'Kompetenz-Prozess-Matrix'!E12) -> 0 | K44: =PRODUCT('Rollen-Prozess-Matrix'!O8,'Kompetenz-Prozess-Matrix'!E12) -> 0 | L44: =PRODUCT('Rollen-Prozess-Matrix'!P8,'Kompetenz-Prozess-Matrix'!E12) -> 1 | M44: =PRODUCT('Rollen-Prozess-Matrix'!Q8,'Kompetenz-Prozess-Matrix'!E12) -> 0 | N44: =PRODUCT('Rollen-Prozess-Matrix'!R8,'Kompetenz-Prozess-Matrix'!E12) -> 0 | O44: =PRODUCT('Rollen-Prozess-Matrix'!S8,'Kompetenz-Prozess-Matrix'!E12) -> 2 | P44: =PRODUCT('Rollen-Prozess-Matrix'!T8,'Kompetenz-Prozess-Matrix'!E12) -> 0 | Q44: =PRODUCT('Rollen-Prozess-Matrix'!U8,'Kompetenz-Prozess-Matrix'!E12) -> 0
C45: 6.2.6 Wissensmanagement | D45: =PRODUCT('Rollen-Prozess-Matrix'!H9,'Kompetenz-Prozess-Matrix'!E13) -> 0 | E45: =PRODUCT('Rollen-Prozess-Matrix'!I9,'Kompetenz-Prozess-Matrix'!E13) -> 0 | F45: =PRODUCT('Rollen-Prozess-Matrix'!J9,'Kompetenz-Prozess-Matrix'!E13) -> 0 | G45: =PRODUCT('Rollen-Prozess-Matrix'!K9,'Kompetenz-Prozess-Matrix'!E13) -> 2 | H45: =PRODUCT('Rollen-Prozess-Matrix'!L9,'Kompetenz-Prozess-Matrix'!E13) -> 3 | I45: =PRODUCT('Rollen-Prozess-Matrix'!M9,'Kompetenz-Prozess-Matrix'!E13) -> 0 | J45: =PRODUCT('Rollen-Prozess-Matrix'!N9,'Kompetenz-Prozess-Matrix'!E13) -> 0 | K45: =PRODUCT('Rollen-Prozess-Matrix'!O9,'Kompetenz-Prozess-Matrix'!E13) -> 0 | L45: =PRODUCT('Rollen-Prozess-Matrix'!P9,'Kompetenz-Prozess-Matrix'!E13) -> 0 | M45: =PRODUCT('Rollen-Prozess-Matrix'!Q9,'Kompetenz-Prozess-Matrix'!E13) -> 0 | N45: =PRODUCT('Rollen-Prozess-Matrix'!R9,'Kompetenz-Prozess-Matrix'!E13) -> 0 | O45: =PRODUCT('Rollen-Prozess-Matrix'!S9,'Kompetenz-Prozess-Matrix'!E13) -> 0 | P45: =PRODUCT('Rollen-Prozess-Matrix'!T9,'Kompetenz-Prozess-Matrix'!E13) -> 0 | Q45: =PRODUCT('Rollen-Prozess-Matrix'!U9,'Kompetenz-Prozess-Matrix'!E13) -> 0
C46: 6.3.1 Projektierung/Projektplanung | D46: =PRODUCT('Rollen-Prozess-Matrix'!H10,'Kompetenz-Prozess-Matrix'!E14) -> 0 | E46: =PRODUCT('Rollen-Prozess-Matrix'!I10,'Kompetenz-Prozess-Matrix'!E14) -> 0 | F46: =PRODUCT('Rollen-Prozess-Matrix'!J10,'Kompetenz-Prozess-Matrix'!E14) -> 0 | G46: =PRODUCT('Rollen-Prozess-Matrix'!K10,'Kompetenz-Prozess-Matrix'!E14) -> 0 | H46: =PRODUCT('Rollen-Prozess-Matrix'!L10,'Kompetenz-Prozess-Matrix'!E14) -> 0 | I46: =PRODUCT('Rollen-Prozess-Matrix'!M10,'Kompetenz-Prozess-Matrix'!E14) -> 0 | J46: =PRODUCT('Rollen-Prozess-Matrix'!N10,'Kompetenz-Prozess-Matrix'!E14) -> 0 | K46: =PRODUCT('Rollen-Prozess-Matrix'!O10,'Kompetenz-Prozess-Matrix'!E14) -> 0 | L46: =PRODUCT('Rollen-Prozess-Matrix'!P10,'Kompetenz-Prozess-Matrix'!E14) -> 0 | M46: =PRODUCT('Rollen-Prozess-Matrix'!Q10,'Kompetenz-Prozess-Matrix'!E14) -> 0 | N46: =PRODUCT('Rollen-Prozess-Matrix'!R10,'Kompetenz-Prozess-Matrix'!E14) -> 0 | O46: =PRODUCT('Rollen-Prozess-Matrix'!S10,'Kompetenz-Prozess-Matrix'!E14) -> 0 | P46: =PRODUCT('Rollen-Prozess-Matrix'!T10,'Kompetenz-Prozess-Matrix'!E14) -> 0 | Q46: =PRODUCT('Rollen-Prozess-Matrix'!U10,'Kompetenz-Prozess-Matrix'!E14) -> 0
C47: 6.3.2 Projektbewertung und Steuerung | D47: =PRODUCT('Rollen-Prozess-Matrix'!H11,'Kompetenz-Prozess-Matrix'!E15) -> 0 | E47: =PRODUCT('Rollen-Prozess-Matrix'!I11,'Kompetenz-Prozess-Matrix'!E15) -> 0 | F47: =PRODUCT('Rollen-Prozess-Matrix'!J11,'Kompetenz-Prozess-Matrix'!E15) -> 0 | G47: =PRODUCT('Rollen-Prozess-Matrix'!K11,'Kompetenz-Prozess-Matrix'!E15) -> 0 | H47: =PRODUCT('Rollen-Prozess-Matrix'!L11,'Kompetenz-Prozess-Matrix'!E15) -> 0 | I47: =PRODUCT('Rollen-Prozess-Matrix'!M11,'Kompetenz-Prozess-Matrix'!E15) -> 0 | J47: =PRODUCT('Rollen-Prozess-Matrix'!N11,'Kompetenz-Prozess-Matrix'!E15) -> 0 | K47: =PRODUCT('Rollen-Prozess-Matrix'!O11,'Kompetenz-Prozess-Matrix'!E15) -> 0 | L47: =PRODUCT('Rollen-Prozess-Matrix'!P11,'Kompetenz-Prozess-Matrix'!E15) -> 0 | M47: =PRODUCT('Rollen-Prozess-Matrix'!Q11,'Kompetenz-Prozess-Matrix'!E15) -> 0 | N47: =PRODUCT('Rollen-Prozess-Matrix'!R11,'Kompetenz-Prozess-Matrix'!E15) -> 0 | O47: =PRODUCT('Rollen-Prozess-Matrix'!S11,'Kompetenz-Prozess-Matrix'!E15) -> 0 | P47: =PRODUCT('Rollen-Prozess-Matrix'!T11,'Kompetenz-Prozess-Matrix'!E15) -> 0 | Q47: =PRODUCT('Rollen-Prozess-Matrix'!U11,'Kompetenz-Prozess-Matrix'!E15) -> 0
C48: 6.3.3 Entscheidungsmanagement | D48: =PRODUCT('Rollen-Prozess-Matrix'!H12,'Kompetenz-Prozess-Matrix'!E16) -> 0 | E48: =PRODUCT('Rollen-Prozess-Matrix'!I12,'Kompetenz-Prozess-Matrix'!E16) -> 2 | F48: =PRODUCT('Rollen-Prozess-Matrix'!J12,'Kompetenz-Prozess-Matrix'!E16) -> 2 | G48: =PRODUCT('Rollen-Prozess-Matrix'!K12,'Kompetenz-Prozess-Matrix'!E16) -> 0 | H48: =PRODUCT('Rollen-Prozess-Matrix'!L12,'Kompetenz-Prozess-Matrix'!E16) -> 3 | I48: =PRODUCT('Rollen-Prozess-Matrix'!M12,'Kompetenz-Prozess-Matrix'!E16) -> 2 | J48: =PRODUCT('Rollen-Prozess-Matrix'!N12,'Kompetenz-Prozess-Matrix'!E16) -> 1 | K48: =PRODUCT('Rollen-Prozess-Matrix'!O12,'Kompetenz-Prozess-Matrix'!E16) -> 1 | L48: =PRODUCT('Rollen-Prozess-Matrix'!P12,'Kompetenz-Prozess-Matrix'!E16) -> 1 | M48: =PRODUCT('Rollen-Prozess-Matrix'!Q12,'Kompetenz-Prozess-Matrix'!E16) -> 0 | N48: =PRODUCT('Rollen-Prozess-Matrix'!R12,'Kompetenz-Prozess-Matrix'!E16) -> 0 | O48: =PRODUCT('Rollen-Prozess-Matrix'!S12,'Kompetenz-Prozess-Matrix'!E16) -> 0 | P48: =PRODUCT('Rollen-Prozess-Matrix'!T12,'Kompetenz-Prozess-Matrix'!E16) -> 1 | Q48: =PRODUCT('Rollen-Prozess-Matrix'!U12,'Kompetenz-Prozess-Matrix'!E16) -> 2
C49: 6.3.4 Risiko-Management | D49: =PRODUCT('Rollen-Prozess-Matrix'!H13,'Kompetenz-Prozess-Matrix'!E17) -> 0 | E49: =PRODUCT('Rollen-Prozess-Matrix'!I13,'Kompetenz-Prozess-Matrix'!E17) -> 2 | F49: =PRODUCT('Rollen-Prozess-Matrix'!J13,'Kompetenz-Prozess-Matrix'!E17) -> 4 | G49: =PRODUCT('Rollen-Prozess-Matrix'!K13,'Kompetenz-Prozess-Matrix'!E17) -> 0 | H49: =PRODUCT('Rollen-Prozess-Matrix'!L13,'Kompetenz-Prozess-Matrix'!E17) -> 6 | I49: =PRODUCT('Rollen-Prozess-Matrix'!M13,'Kompetenz-Prozess-Matrix'!E17) -> 4 | J49: =PRODUCT('Rollen-Prozess-Matrix'!N13,'Kompetenz-Prozess-Matrix'!E17) -> 2 | K49: =PRODUCT('Rollen-Prozess-Matrix'!O13,'Kompetenz-Prozess-Matrix'!E17) -> 2 | L49: =PRODUCT('Rollen-Prozess-Matrix'!P13,'Kompetenz-Prozess-Matrix'!E17) -> 0 | M49: =PRODUCT('Rollen-Prozess-Matrix'!Q13,'Kompetenz-Prozess-Matrix'!E17) -> 0 | N49: =PRODUCT('Rollen-Prozess-Matrix'!R13,'Kompetenz-Prozess-Matrix'!E17) -> 0 | O49: =PRODUCT('Rollen-Prozess-Matrix'!S13,'Kompetenz-Prozess-Matrix'!E17) -> 2 | P49: =PRODUCT('Rollen-Prozess-Matrix'!T13,'Kompetenz-Prozess-Matrix'!E17) -> 0 | Q49: =PRODUCT('Rollen-Prozess-Matrix'!U13,'Kompetenz-Prozess-Matrix'!E17) -> 0
... C70: Qualifizierung | D70: =PRODUCT('Rollen-Prozess-Matrix'!H34,'Kompetenz-Prozess-Matrix'!E38) -> 0 | E70: =PRODUCT('Rollen-Prozess-Matrix'!I34,'Kompetenz-Prozess-Matrix'!E38) -> 0 | F70: =PRODUCT('Rollen-Prozess-Matrix'!J34,'Kompetenz-Prozess-Matrix'!E38) -> 0 | G70: =PRODUCT('Rollen-Prozess-Matrix'!K34,'Kompetenz-Prozess-Matrix'!E38) -> 4 | H70: =PRODUCT('Rollen-Prozess-Matrix'!L34,'Kompetenz-Prozess-Matrix'!E38) -> 0 | I70: =PRODUCT('Rollen-Prozess-Matrix'!M34,'Kompetenz-Prozess-Matrix'!E38) -> 0 | J70: =PRODUCT('Rollen-Prozess-Matrix'!N34,'Kompetenz-Prozess-Matrix'!E38) -> 0 | K70: =PRODUCT('Rollen-Prozess-Matrix'!O34,'Kompetenz-Prozess-Matrix'!E38) -> 0 | L70: =PRODUCT('Rollen-Prozess-Matrix'!P34,'Kompetenz-Prozess-Matrix'!E38) -> 0 | M70: =PRODUCT('Rollen-Prozess-Matrix'!Q34,'Kompetenz-Prozess-Matrix'!E38) -> 0 | N70: =PRODUCT('Rollen-Prozess-Matrix'!R34,'Kompetenz-Prozess-Matrix'!E38) -> 0 | O70: =PRODUCT('Rollen-Prozess-Matrix'!S34,'Kompetenz-Prozess-Matrix'!E38) -> 0 | P70: =PRODUCT('Rollen-Prozess-Matrix'!T34,'Kompetenz-Prozess-Matrix'!E38) -> 0 | Q70: =PRODUCT('Rollen-Prozess-Matrix'!U34,'Kompetenz-Prozess-Matrix'!E38) -> 0
B71: Berücksichtigung von Systemlebenszyklusphasen | D71: =MAX(D72:D104) -> 2 | E71: =MAX(E72:E104) -> 4 | F71: =MAX(F72:F104) -> 4 | G71: =MAX(G72:G104) -> 4 | H71: =MAX(H72:H104) -> 6 | I71: =MAX(I72:I104) -> 4 | J71: =MAX(J72:J104) -> 4 | K71: =MAX(K72:K104) -> 2 | ... Q71: =MAX(Q72:Q104) -> 4 | S71: 1
C72: 6.1.1 Akquisition | D72: =PRODUCT('Rollen-Prozess-Matrix'!H2,'Kompetenz-Prozess-Matrix'!F6) -> 0 | E72: =PRODUCT('Rollen-Prozess-Matrix'!I2,'Kompetenz-Prozess-Matrix'!F6) -> 0 | F72: =PRODUCT('Rollen-Prozess-Matrix'!J2,'Kompetenz-Prozess-Matrix'!F6) -> 0 | G72: =PRODUCT('Rollen-Prozess-Matrix'!K2,'Kompetenz-Prozess-Matrix'!F6) -> 0 | H72: =PRODUCT('Rollen-Prozess-Matrix'!L2,'Kompetenz-Prozess-Matrix'!F6) -> 0 | I72: =PRODUCT('Rollen-Prozess-Matrix'!M2,'Kompetenz-Prozess-Matrix'!F6) -> 0 | J72: =PRODUCT('Rollen-Prozess-Matrix'!N2,'Kompetenz-Prozess-Matrix'!F6) -> 0 | K72: =PRODUCT('Rollen-Prozess-Matrix'!O2,'Kompetenz-Prozess-Matrix'!F6) -> 0 | L72: =PRODUCT('Rollen-Prozess-Matrix'!P2,'Kompetenz-Prozess-Matrix'!F6) -> 0 | M72: =PRODUCT('Rollen-Prozess-Matrix'!Q2,'Kompetenz-Prozess-Matrix'!F6) -> 0 | N72: =PRODUCT('Rollen-Prozess-Matrix'!R2,'Kompetenz-Prozess-Matrix'!F6) -> 0 | O72: =PRODUCT('Rollen-Prozess-Matrix'!S2,'Kompetenz-Prozess-Matrix'!F6) -> 0 | P72: =PRODUCT('Rollen-Prozess-Matrix'!T2,'Kompetenz-Prozess-Matrix'!F6) -> 0 | Q72: =PRODUCT('Rollen-Prozess-Matrix'!U2,'Kompetenz-Prozess-Matrix'!F6) -> 0
C73: 6.1.2 Lieferung | D73: =PRODUCT('Rollen-Prozess-Matrix'!H3,'Kompetenz-Prozess-Matrix'!F7) -> 0 | E73: =PRODUCT('Rollen-Prozess-Matrix'!I3,'Kompetenz-Prozess-Matrix'!F7) -> 0 | F73: =PRODUCT('Rollen-Prozess-Matrix'!J3,'Kompetenz-Prozess-Matrix'!F7) -> 0 | G73: =PRODUCT('Rollen-Prozess-Matrix'!K3,'Kompetenz-Prozess-Matrix'!F7) -> 0 | H73: =PRODUCT('Rollen-Prozess-Matrix'!L3,'Kompetenz-Prozess-Matrix'!F7) -> 0 | I73: =PRODUCT('Rollen-Prozess-Matrix'!M3,'Kompetenz-Prozess-Matrix'!F7) -> 0 | J73: =PRODUCT('Rollen-Prozess-Matrix'!N3,'Kompetenz-Prozess-Matrix'!F7) -> 0 | K73: =PRODUCT('Rollen-Prozess-Matrix'!O3,'Kompetenz-Prozess-Matrix'!F7) -> 0 | L73: =PRODUCT('Rollen-Prozess-Matrix'!P3,'Kompetenz-Prozess-Matrix'!F7) -> 0 | M73: =PRODUCT('Rollen-Prozess-Matrix'!Q3,'Kompetenz-Prozess-Matrix'!F7) -> 0 | N73: =PRODUCT('Rollen-Prozess-Matrix'!R3,'Kompetenz-Prozess-Matrix'!F7) -> 0 | O73: =PRODUCT('Rollen-Prozess-Matrix'!S3,'Kompetenz-Prozess-Matrix'!F7) -> 0 | P73: =PRODUCT('Rollen-Prozess-Matrix'!T3,'Kompetenz-Prozess-Matrix'!F7) -> 0 | Q73: =PRODUCT('Rollen-Prozess-Matrix'!U3,'Kompetenz-Prozess-Matrix'!F7) -> 0
C74: 6.2.1 Lebenszyklus-Modell-Management | D74: =PRODUCT('Rollen-Prozess-Matrix'!H4,'Kompetenz-Prozess-Matrix'!F8) -> 0 | E74: =PRODUCT('Rollen-Prozess-Matrix'!I4,'Kompetenz-Prozess-Matrix'!F8) -> 0 | F74: =PRODUCT('Rollen-Prozess-Matrix'!J4,'Kompetenz-Prozess-Matrix'!F8) -> 0 | G74: =PRODUCT('Rollen-Prozess-Matrix'!K4,'Kompetenz-Prozess-Matrix'!F8) -> 2 | H74: =PRODUCT('Rollen-Prozess-Matrix'!L4,'Kompetenz-Prozess-Matrix'!F8) -> 6 | I74: =PRODUCT('Rollen-Prozess-Matrix'!M4,'Kompetenz-Prozess-Matrix'!F8) -> 0 | J74: =PRODUCT('Rollen-Prozess-Matrix'!N4,'Kompetenz-Prozess-Matrix'!F8) -> 0 | K74: =PRODUCT('Rollen-Prozess-Matrix'!O4,'Kompetenz-Prozess-Matrix'!F8) -> 0 | L74: =PRODUCT('Rollen-Prozess-Matrix'!P4,'Kompetenz-Prozess-Matrix'!F8) -> 0 | M74: =PRODUCT('Rollen-Prozess-Matrix'!Q4,'Kompetenz-Prozess-Matrix'!F8) -> 0 | N74: =PRODUCT('Rollen-Prozess-Matrix'!R4,'Kompetenz-Prozess-Matrix'!F8) -> 0 | O74: =PRODUCT('Rollen-Prozess-Matrix'!S4,'Kompetenz-Prozess-Matrix'!F8) -> 0 | P74: =PRODUCT('Rollen-Prozess-Matrix'!T4,'Kompetenz-Prozess-Matrix'!F8) -> 0 | Q74: =PRODUCT('Rollen-Prozess-Matrix'!U4,'Kompetenz-Prozess-Matrix'!F8) -> 0
C75: 6.2.2 Verwaltung der Infrastruktur | D75: =PRODUCT('Rollen-Prozess-Matrix'!H5,'Kompetenz-Prozess-Matrix'!F9) -> 0 | E75: =PRODUCT('Rollen-Prozess-Matrix'!I5,'Kompetenz-Prozess-Matrix'!F9) -> 0 | F75: =PRODUCT('Rollen-Prozess-Matrix'!J5,'Kompetenz-Prozess-Matrix'!F9) -> 0 | G75: =PRODUCT('Rollen-Prozess-Matrix'!K5,'Kompetenz-Prozess-Matrix'!F9) -> 0 | H75: =PRODUCT('Rollen-Prozess-Matrix'!L5,'Kompetenz-Prozess-Matrix'!F9) -> 0 | I75: =PRODUCT('Rollen-Prozess-Matrix'!M5,'Kompetenz-Prozess-Matrix'!F9) -> 0 | J75: =PRODUCT('Rollen-Prozess-Matrix'!N5,'Kompetenz-Prozess-Matrix'!F9) -> 0 | K75: =PRODUCT('Rollen-Prozess-Matrix'!O5,'Kompetenz-Prozess-Matrix'!F9) -> 0 | L75: =PRODUCT('Rollen-Prozess-Matrix'!P5,'Kompetenz-Prozess-Matrix'!F9) -> 0 | M75: =PRODUCT('Rollen-Prozess-Matrix'!Q5,'Kompetenz-Prozess-Matrix'!F9) -> 0 | N75: =PRODUCT('Rollen-Prozess-Matrix'!R5,'Kompetenz-Prozess-Matrix'!F9) -> 0 | O75: =PRODUCT('Rollen-Prozess-Matrix'!S5,'Kompetenz-Prozess-Matrix'!F9) -> 0 | P75: =PRODUCT('Rollen-Prozess-Matrix'!T5,'Kompetenz-Prozess-Matrix'!F9) -> 0 | Q75: =PRODUCT('Rollen-Prozess-Matrix'!U5,'Kompetenz-Prozess-Matrix'!F9) -> 0
C76: 6.2.3 Portfoliomanagement | D76: =PRODUCT('Rollen-Prozess-Matrix'!H6,'Kompetenz-Prozess-Matrix'!F10) -> 0 | E76: =PRODUCT('Rollen-Prozess-Matrix'!I6,'Kompetenz-Prozess-Matrix'!F10) -> 0 | F76: =PRODUCT('Rollen-Prozess-Matrix'!J6,'Kompetenz-Prozess-Matrix'!F10) -> 0 | G76: =PRODUCT('Rollen-Prozess-Matrix'!K6,'Kompetenz-Prozess-Matrix'!F10) -> 0 | H76: =PRODUCT('Rollen-Prozess-Matrix'!L6,'Kompetenz-Prozess-Matrix'!F10) -> 0 | I76: =PRODUCT('Rollen-Prozess-Matrix'!M6,'Kompetenz-Prozess-Matrix'!F10) -> 0 | J76: =PRODUCT('Rollen-Prozess-Matrix'!N6,'Kompetenz-Prozess-Matrix'!F10) -> 0 | K76: =PRODUCT('Rollen-Prozess-Matrix'!O6,'Kompetenz-Prozess-Matrix'!F10) -> 0 | L76: =PRODUCT('Rollen-Prozess-Matrix'!P6,'Kompetenz-Prozess-Matrix'!F10) -> 0 | M76: =PRODUCT('Rollen-Prozess-Matrix'!Q6,'Kompetenz-Prozess-Matrix'!F10) -> 0 | N76: =PRODUCT('Rollen-Prozess-Matrix'!R6,'Kompetenz-Prozess-Matrix'!F10) -> 0 | O76: =PRODUCT('Rollen-Prozess-Matrix'!S6,'Kompetenz-Prozess-Matrix'!F10) -> 0 | P76: =PRODUCT('Rollen-Prozess-Matrix'!T6,'Kompetenz-Prozess-Matrix'!F10) -> 0 | Q76: =PRODUCT('Rollen-Prozess-Matrix'!U6,'Kompetenz-Prozess-Matrix'!F10) -> 0
C77: 6.2.4 Personalwesen-Management | D77: =PRODUCT('Rollen-Prozess-Matrix'!H7,'Kompetenz-Prozess-Matrix'!F11) -> 0 | E77: =PRODUCT('Rollen-Prozess-Matrix'!I7,'Kompetenz-Prozess-Matrix'!F11) -> 0 | F77: =PRODUCT('Rollen-Prozess-Matrix'!J7,'Kompetenz-Prozess-Matrix'!F11) -> 0 | G77: =PRODUCT('Rollen-Prozess-Matrix'!K7,'Kompetenz-Prozess-Matrix'!F11) -> 2 | H77: =PRODUCT('Rollen-Prozess-Matrix'!L7,'Kompetenz-Prozess-Matrix'!F11) -> 3 | I77: =PRODUCT('Rollen-Prozess-Matrix'!M7,'Kompetenz-Prozess-Matrix'!F11) -> 0 | J77: =PRODUCT('Rollen-Prozess-Matrix'!N7,'Kompetenz-Prozess-Matrix'!F11) -> 0 | K77: =PRODUCT('Rollen-Prozess-Matrix'!O7,'Kompetenz-Prozess-Matrix'!F11) -> 0 | L77: =PRODUCT('Rollen-Prozess-Matrix'!P7,'Kompetenz-Prozess-Matrix'!F11) -> 0 | M77: =PRODUCT('Rollen-Prozess-Matrix'!Q7,'Kompetenz-Prozess-Matrix'!F11) -> 0 | N77: =PRODUCT('Rollen-Prozess-Matrix'!R7,'Kompetenz-Prozess-Matrix'!F11) -> 0 | O77: =PRODUCT('Rollen-Prozess-Matrix'!S7,'Kompetenz-Prozess-Matrix'!F11) -> 0 | P77: =PRODUCT('Rollen-Prozess-Matrix'!T7,'Kompetenz-Prozess-Matrix'!F11) -> 0 | Q77: =PRODUCT('Rollen-Prozess-Matrix'!U7,'Kompetenz-Prozess-Matrix'!F11) -> 1
C78: 6.2.5 Qualitätsmanagement | D78: =PRODUCT('Rollen-Prozess-Matrix'!H8,'Kompetenz-Prozess-Matrix'!F12) -> 0 | E78: =PRODUCT('Rollen-Prozess-Matrix'!I8,'Kompetenz-Prozess-Matrix'!F12) -> 0 | F78: =PRODUCT('Rollen-Prozess-Matrix'!J8,'Kompetenz-Prozess-Matrix'!F12) -> 0 | G78: =PRODUCT('Rollen-Prozess-Matrix'!K8,'Kompetenz-Prozess-Matrix'!F12) -> 0 | H78: =PRODUCT('Rollen-Prozess-Matrix'!L8,'Kompetenz-Prozess-Matrix'!F12) -> 3 | I78: =PRODUCT('Rollen-Prozess-Matrix'!M8,'Kompetenz-Prozess-Matrix'!F12) -> 0 | J78: =PRODUCT('Rollen-Prozess-Matrix'!N8,'Kompetenz-Prozess-Matrix'!F12) -> 0 | K78: =PRODUCT('Rollen-Prozess-Matrix'!O8,'Kompetenz-Prozess-Matrix'!F12) -> 0 | L78: =PRODUCT('Rollen-Prozess-Matrix'!P8,'Kompetenz-Prozess-Matrix'!F12) -> 1 | M78: =PRODUCT('Rollen-Prozess-Matrix'!Q8,'Kompetenz-Prozess-Matrix'!F12) -> 0 | N78: =PRODUCT('Rollen-Prozess-Matrix'!R8,'Kompetenz-Prozess-Matrix'!F12) -> 0 | O78: =PRODUCT('Rollen-Prozess-Matrix'!S8,'Kompetenz-Prozess-Matrix'!F12) -> 2 | P78: =PRODUCT('Rollen-Prozess-Matrix'!T8,'Kompetenz-Prozess-Matrix'!F12) -> 0 | Q78: =PRODUCT('Rollen-Prozess-Matrix'!U8,'Kompetenz-Prozess-Matrix'!F12) -> 0
C79: 6.2.6 Wissensmanagement | D79: =PRODUCT('Rollen-Prozess-Matrix'!H9,'Kompetenz-Prozess-Matrix'!F13) -> 0 | E79: =PRODUCT('Rollen-Prozess-Matrix'!I9,'Kompetenz-Prozess-Matrix'!F13) -> 0 | F79: =PRODUCT('Rollen-Prozess-Matrix'!J9,'Kompetenz-Prozess-Matrix'!F13) -> 0 | G79: =PRODUCT('Rollen-Prozess-Matrix'!K9,'Kompetenz-Prozess-Matrix'!F13) -> 0 | H79: =PRODUCT('Rollen-Prozess-Matrix'!L9,'Kompetenz-Prozess-Matrix'!F13) -> 0 | I79: =PRODUCT('Rollen-Prozess-Matrix'!M9,'Kompetenz-Prozess-Matrix'!F13) -> 0 | J79: =PRODUCT('Rollen-Prozess-Matrix'!N9,'Kompetenz-Prozess-Matrix'!F13) -> 0 | K79: =PRODUCT('Rollen-Prozess-Matrix'!O9,'Kompetenz-Prozess-Matrix'!F13) -> 0 | L79: =PRODUCT('Rollen-Prozess-Matrix'!P9,'Kompetenz-Prozess-Matrix'!F13) -> 0 | M79: =PRODUCT('Rollen-Prozess-Matrix'!Q9,'Kompetenz-Prozess-Matrix'!F13) -> 0 | N79: =PRODUCT('Rollen-Prozess-Matrix'!R9,'Kompetenz-Prozess-Matrix'!F13) -> 0 | O79: =PRODUCT('Rollen-Prozess-Matrix'!S9,'Kompetenz-Prozess-Matrix'!F13) -> 0 | P79: =PRODUCT('Rollen-Prozess-Matrix'!T9,'Kompetenz-Prozess-Matrix'!F13) -> 0 | Q79: =PRODUCT('Rollen-Prozess-Matrix'!U9,'Kompetenz-Prozess-Matrix'!F13) -> 0
C80: 6.3.1 Projektierung/Projektplanung | D80: =PRODUCT('Rollen-Prozess-Matrix'!H10,'Kompetenz-Prozess-Matrix'!F14) -> 0 | E80: =PRODUCT('Rollen-Prozess-Matrix'!I10,'Kompetenz-Prozess-Matrix'!F14) -> 0 | F80: =PRODUCT('Rollen-Prozess-Matrix'!J10,'Kompetenz-Prozess-Matrix'!F14) -> 2 | G80: =PRODUCT('Rollen-Prozess-Matrix'!K10,'Kompetenz-Prozess-Matrix'!F14) -> 0 | H80: =PRODUCT('Rollen-Prozess-Matrix'!L10,'Kompetenz-Prozess-Matrix'!F14) -> 3 | I80: =PRODUCT('Rollen-Prozess-Matrix'!M10,'Kompetenz-Prozess-Matrix'!F14) -> 0 | J80: =PRODUCT('Rollen-Prozess-Matrix'!N10,'Kompetenz-Prozess-Matrix'!F14) -> 0 | K80: =PRODUCT('Rollen-Prozess-Matrix'!O10,'Kompetenz-Prozess-Matrix'!F14) -> 0 | L80: =PRODUCT('Rollen-Prozess-Matrix'!P10,'Kompetenz-Prozess-Matrix'!F14) -> 0 | M80: =PRODUCT('Rollen-Prozess-Matrix'!Q10,'Kompetenz-Prozess-Matrix'!F14) -> 0 | N80: =PRODUCT('Rollen-Prozess-Matrix'!R10,'Kompetenz-Prozess-Matrix'!F14) -> 0 | O80: =PRODUCT('Rollen-Prozess-Matrix'!S10,'Kompetenz-Prozess-Matrix'!F14) -> 0 | P80: =PRODUCT('Rollen-Prozess-Matrix'!T10,'Kompetenz-Prozess-Matrix'!F14) -> 0 | Q80: =PRODUCT('Rollen-Prozess-Matrix'!U10,'Kompetenz-Prozess-Matrix'!F14) -> 0
C81: 6.3.2 Projektbewertung und Steuerung | D81: =PRODUCT('Rollen-Prozess-Matrix'!H11,'Kompetenz-Prozess-Matrix'!F15) -> 0 | E81: =PRODUCT('Rollen-Prozess-Matrix'!I11,'Kompetenz-Prozess-Matrix'!F15) -> 0 | F81: =PRODUCT('Rollen-Prozess-Matrix'!J11,'Kompetenz-Prozess-Matrix'!F15) -> 2 | G81: =PRODUCT('Rollen-Prozess-Matrix'!K11,'Kompetenz-Prozess-Matrix'!F15) -> 0 | H81: =PRODUCT('Rollen-Prozess-Matrix'!L11,'Kompetenz-Prozess-Matrix'!F15) -> 3 | I81: =PRODUCT('Rollen-Prozess-Matrix'!M11,'Kompetenz-Prozess-Matrix'!F15) -> 0 | J81: =PRODUCT('Rollen-Prozess-Matrix'!N11,'Kompetenz-Prozess-Matrix'!F15) -> 0 | K81: =PRODUCT('Rollen-Prozess-Matrix'!O11,'Kompetenz-Prozess-Matrix'!F15) -> 0 | L81: =PRODUCT('Rollen-Prozess-Matrix'!P11,'Kompetenz-Prozess-Matrix'!F15) -> 0 | M81: =PRODUCT('Rollen-Prozess-Matrix'!Q11,'Kompetenz-Prozess-Matrix'!F15) -> 0 | N81: =PRODUCT('Rollen-Prozess-Matrix'!R11,'Kompetenz-Prozess-Matrix'!F15) -> 0 | O81: =PRODUCT('Rollen-Prozess-Matrix'!S11,'Kompetenz-Prozess-Matrix'!F15) -> 0 | P81: =PRODUCT('Rollen-Prozess-Matrix'!T11,'Kompetenz-Prozess-Matrix'!F15) -> 0 | Q81: =PRODUCT('Rollen-Prozess-Matrix'!U11,'Kompetenz-Prozess-Matrix'!F15) -> 1
C82: 6.3.3 Entscheidungsmanagement | D82: =PRODUCT('Rollen-Prozess-Matrix'!H12,'Kompetenz-Prozess-Matrix'!F16) -> 0 | E82: =PRODUCT('Rollen-Prozess-Matrix'!I12,'Kompetenz-Prozess-Matrix'!F16) -> 4 | F82: =PRODUCT('Rollen-Prozess-Matrix'!J12,'Kompetenz-Prozess-Matrix'!F16) -> 4 | G82: =PRODUCT('Rollen-Prozess-Matrix'!K12,'Kompetenz-Prozess-Matrix'!F16) -> 0 | H82: =PRODUCT('Rollen-Prozess-Matrix'!L12,'Kompetenz-Prozess-Matrix'!F16) -> 6 | I82: =PRODUCT('Rollen-Prozess-Matrix'!M12,'Kompetenz-Prozess-Matrix'!F16) -> 4 | J82: =PRODUCT('Rollen-Prozess-Matrix'!N12,'Kompetenz-Prozess-Matrix'!F16) -> 2 | K82: =PRODUCT('Rollen-Prozess-Matrix'!O12,'Kompetenz-Prozess-Matrix'!F16) -> 2 | L82: =PRODUCT('Rollen-Prozess-Matrix'!P12,'Kompetenz-Prozess-Matrix'!F16) -> 2 | M82: =PRODUCT('Rollen-Prozess-Matrix'!Q12,'Kompetenz-Prozess-Matrix'!F16) -> 0 | N82: =PRODUCT('Rollen-Prozess-Matrix'!R12,'Kompetenz-Prozess-Matrix'!F16) -> 0 | O82: =PRODUCT('Rollen-Prozess-Matrix'!S12,'Kompetenz-Prozess-Matrix'!F16) -> 0 | P82: =PRODUCT('Rollen-Prozess-Matrix'!T12,'Kompetenz-Prozess-Matrix'!F16) -> 2 | Q82: =PRODUCT('Rollen-Prozess-Matrix'!U12,'Kompetenz-Prozess-Matrix'!F16) -> 4
C83: 6.3.4 Risiko-Management | D83: =PRODUCT('Rollen-Prozess-Matrix'!H13,'Kompetenz-Prozess-Matrix'!F17) -> 0 | E83: =PRODUCT('Rollen-Prozess-Matrix'!I13,'Kompetenz-Prozess-Matrix'!F17) -> 2 | F83: =PRODUCT('Rollen-Prozess-Matrix'!J13,'Kompetenz-Prozess-Matrix'!F17) -> 4 | G83: =PRODUCT('Rollen-Prozess-Matrix'!K13,'Kompetenz-Prozess-Matrix'!F17) -> 0 | H83: =PRODUCT('Rollen-Prozess-Matrix'!L13,'Kompetenz-Prozess-Matrix'!F17) -> 6 | I83: =PRODUCT('Rollen-Prozess-Matrix'!M13,'Kompetenz-Prozess-Matrix'!F17) -> 4 | J83: =PRODUCT('Rollen-Prozess-Matrix'!N13,'Kompetenz-Prozess-Matrix'!F17) -> 2 | K83: =PRODUCT('Rollen-Prozess-Matrix'!O13,'Kompetenz-Prozess-Matrix'!F17) -> 2 | L83: =PRODUCT('Rollen-Prozess-Matrix'!P13,'Kompetenz-Prozess-Matrix'!F17) -> 0 | M83: =PRODUCT('Rollen-Prozess-Matrix'!Q13,'Kompetenz-Prozess-Matrix'!F17) -> 0 | N83: =PRODUCT('Rollen-Prozess-Matrix'!R13,'Kompetenz-Prozess-Matrix'!F17) -> 0 | O83: =PRODUCT('Rollen-Prozess-Matrix'!S13,'Kompetenz-Prozess-Matrix'!F17) -> 2 | P83: =PRODUCT('Rollen-Prozess-Matrix'!T13,'Kompetenz-Prozess-Matrix'!F17) -> 0 | Q83: =PRODUCT('Rollen-Prozess-Matrix'!U13,'Kompetenz-Prozess-Matrix'!F17) -> 0
... C104: Qualifizierung | D104: =PRODUCT('Rollen-Prozess-Matrix'!H34,'Kompetenz-Prozess-Matrix'!F38) -> 0 | E104: =PRODUCT('Rollen-Prozess-Matrix'!I34,'Kompetenz-Prozess-Matrix'!F38) -> 0 | F104: =PRODUCT('Rollen-Prozess-Matrix'!J34,'Kompetenz-Prozess-Matrix'!F38) -> 0 | G104: =PRODUCT('Rollen-Prozess-Matrix'!K34,'Kompetenz-Prozess-Matrix'!F38) -> 2 | H104: =PRODUCT('Rollen-Prozess-Matrix'!L34,'Kompetenz-Prozess-Matrix'!F38) -> 0 | I104: =PRODUCT('Rollen-Prozess-Matrix'!M34,'Kompetenz-Prozess-Matrix'!F38) -> 0 | J104: =PRODUCT('Rollen-Prozess-Matrix'!N34,'Kompetenz-Prozess-Matrix'!F38) -> 0 | K104: =PRODUCT('Rollen-Prozess-Matrix'!O34,'Kompetenz-Prozess-Matrix'!F38) -> 0 | L104: =PRODUCT('Rollen-Prozess-Matrix'!P34,'Kompetenz-Prozess-Matrix'!F38) -> 0 | M104: =PRODUCT('Rollen-Prozess-Matrix'!Q34,'Kompetenz-Prozess-Matrix'!F38) -> 0 | N104: =PRODUCT('Rollen-Prozess-Matrix'!R34,'Kompetenz-Prozess-Matrix'!F38) -> 0 | O104: =PRODUCT('Rollen-Prozess-Matrix'!S34,'Kompetenz-Prozess-Matrix'!F38) -> 0 | P104: =PRODUCT('Rollen-Prozess-Matrix'!T34,'Kompetenz-Prozess-Matrix'!F38) -> 0 | Q104: =PRODUCT('Rollen-Prozess-Matrix'!U34,'Kompetenz-Prozess-Matrix'!F38) -> 0
B105: Agiles Denken / Kunden-Nutzenorientierung | D105: =MAX(D106:D138) -> 2 | E105: =MAX(E106:E138) -> 4 | F105: =MAX(F106:F138) -> 4 | G105: =MAX(G106:G138) -> 4 | H105: =MAX(H106:H138) -> 6 | I105: =MAX(I106:I138) -> 4 | J105: =MAX(J106:J138) -> 4 | K105: =MAX(K106:K138) -> 2 | ... Q105: =MAX(Q106:Q138) -> 2 | S105: -
C106: 6.1.1 Akquisition | D106: =PRODUCT('Rollen-Prozess-Matrix'!H2,'Kompetenz-Prozess-Matrix'!G6) -> 0 | E106: =PRODUCT('Rollen-Prozess-Matrix'!I2,'Kompetenz-Prozess-Matrix'!G6) -> 0 | F106: =PRODUCT('Rollen-Prozess-Matrix'!J2,'Kompetenz-Prozess-Matrix'!G6) -> 0 | G106: =PRODUCT('Rollen-Prozess-Matrix'!K2,'Kompetenz-Prozess-Matrix'!G6) -> 0 | H106: =PRODUCT('Rollen-Prozess-Matrix'!L2,'Kompetenz-Prozess-Matrix'!G6) -> 0 | I106: =PRODUCT('Rollen-Prozess-Matrix'!M2,'Kompetenz-Prozess-Matrix'!G6) -> 0 | J106: =PRODUCT('Rollen-Prozess-Matrix'!N2,'Kompetenz-Prozess-Matrix'!G6) -> 0 | K106: =PRODUCT('Rollen-Prozess-Matrix'!O2,'Kompetenz-Prozess-Matrix'!G6) -> 0 | L106: =PRODUCT('Rollen-Prozess-Matrix'!P2,'Kompetenz-Prozess-Matrix'!G6) -> 0 | M106: =PRODUCT('Rollen-Prozess-Matrix'!Q2,'Kompetenz-Prozess-Matrix'!G6) -> 0 | N106: =PRODUCT('Rollen-Prozess-Matrix'!R2,'Kompetenz-Prozess-Matrix'!G6) -> 0 | O106: =PRODUCT('Rollen-Prozess-Matrix'!S2,'Kompetenz-Prozess-Matrix'!G6) -> 0 | P106: =PRODUCT('Rollen-Prozess-Matrix'!T2,'Kompetenz-Prozess-Matrix'!G6) -> 0 | Q106: =PRODUCT('Rollen-Prozess-Matrix'!U2,'Kompetenz-Prozess-Matrix'!G6) -> 0
C107: 6.1.2 Lieferung | D107: =PRODUCT('Rollen-Prozess-Matrix'!H3,'Kompetenz-Prozess-Matrix'!G7) -> 0 | E107: =PRODUCT('Rollen-Prozess-Matrix'!I3,'Kompetenz-Prozess-Matrix'!G7) -> 0 | F107: =PRODUCT('Rollen-Prozess-Matrix'!J3,'Kompetenz-Prozess-Matrix'!G7) -> 0 | G107: =PRODUCT('Rollen-Prozess-Matrix'!K3,'Kompetenz-Prozess-Matrix'!G7) -> 0 | H107: =PRODUCT('Rollen-Prozess-Matrix'!L3,'Kompetenz-Prozess-Matrix'!G7) -> 0 | I107: =PRODUCT('Rollen-Prozess-Matrix'!M3,'Kompetenz-Prozess-Matrix'!G7) -> 0 | J107: =PRODUCT('Rollen-Prozess-Matrix'!N3,'Kompetenz-Prozess-Matrix'!G7) -> 0 | K107: =PRODUCT('Rollen-Prozess-Matrix'!O3,'Kompetenz-Prozess-Matrix'!G7) -> 0 | L107: =PRODUCT('Rollen-Prozess-Matrix'!P3,'Kompetenz-Prozess-Matrix'!G7) -> 0 | M107: =PRODUCT('Rollen-Prozess-Matrix'!Q3,'Kompetenz-Prozess-Matrix'!G7) -> 0 | N107: =PRODUCT('Rollen-Prozess-Matrix'!R3,'Kompetenz-Prozess-Matrix'!G7) -> 0 | O107: =PRODUCT('Rollen-Prozess-Matrix'!S3,'Kompetenz-Prozess-Matrix'!G7) -> 0 | P107: =PRODUCT('Rollen-Prozess-Matrix'!T3,'Kompetenz-Prozess-Matrix'!G7) -> 0 | Q107: =PRODUCT('Rollen-Prozess-Matrix'!U3,'Kompetenz-Prozess-Matrix'!G7) -> 0
C108: 6.2.1 Lebenszyklus-Modell-Management | D108: =PRODUCT('Rollen-Prozess-Matrix'!H4,'Kompetenz-Prozess-Matrix'!G8) -> 0 | E108: =PRODUCT('Rollen-Prozess-Matrix'!I4,'Kompetenz-Prozess-Matrix'!G8) -> 0 | F108: =PRODUCT('Rollen-Prozess-Matrix'!J4,'Kompetenz-Prozess-Matrix'!G8) -> 0 | G108: =PRODUCT('Rollen-Prozess-Matrix'!K4,'Kompetenz-Prozess-Matrix'!G8) -> 1 | H108: =PRODUCT('Rollen-Prozess-Matrix'!L4,'Kompetenz-Prozess-Matrix'!G8) -> 3 | I108: =PRODUCT('Rollen-Prozess-Matrix'!M4,'Kompetenz-Prozess-Matrix'!G8) -> 0 | J108: =PRODUCT('Rollen-Prozess-Matrix'!N4,'Kompetenz-Prozess-Matrix'!G8) -> 0 | K108: =PRODUCT('Rollen-Prozess-Matrix'!O4,'Kompetenz-Prozess-Matrix'!G8) -> 0 | L108: =PRODUCT('Rollen-Prozess-Matrix'!P4,'Kompetenz-Prozess-Matrix'!G8) -> 0 | M108: =PRODUCT('Rollen-Prozess-Matrix'!Q4,'Kompetenz-Prozess-Matrix'!G8) -> 0 | N108: =PRODUCT('Rollen-Prozess-Matrix'!R4,'Kompetenz-Prozess-Matrix'!G8) -> 0 | O108: =PRODUCT('Rollen-Prozess-Matrix'!S4,'Kompetenz-Prozess-Matrix'!G8) -> 0 | P108: =PRODUCT('Rollen-Prozess-Matrix'!T4,'Kompetenz-Prozess-Matrix'!G8) -> 0 | Q108: =PRODUCT('Rollen-Prozess-Matrix'!U4,'Kompetenz-Prozess-Matrix'!G8) -> 0
C109: 6.2.2 Verwaltung der Infrastruktur | D109: =PRODUCT('Rollen-Prozess-Matrix'!H5,'Kompetenz-Prozess-Matrix'!G9) -> 0 | E109: =PRODUCT('Rollen-Prozess-Matrix'!I5,'Kompetenz-Prozess-Matrix'!G9) -> 0 | F109: =PRODUCT('Rollen-Prozess-Matrix'!J5,'Kompetenz-Prozess-Matrix'!G9) -> 0 | G109: =PRODUCT('Rollen-Prozess-Matrix'!K5,'Kompetenz-Prozess-Matrix'!G9) -> 0 | H109: =PRODUCT('Rollen-Prozess-Matrix'!L5,'Kompetenz-Prozess-Matrix'!G9) -> 0 | I109: =PRODUCT('Rollen-Prozess-Matrix'!M5,'Kompetenz-Prozess-Matrix'!G9) -> 0 | J109: =PRODUCT('Rollen-Prozess-Matrix'!N5,'Kompetenz-Prozess-Matrix'!G9) -> 0 | K109: =PRODUCT('Rollen-Prozess-Matrix'!O5,'Kompetenz-Prozess-Matrix'!G9) -> 0 | L109: =PRODUCT('Rollen-Prozess-Matrix'!P5,'Kompetenz-Prozess-Matrix'!G9) -> 0 | M109: =PRODUCT('Rollen-Prozess-Matrix'!Q5,'Kompetenz-Prozess-Matrix'!G9) -> 0 | N109: =PRODUCT('Rollen-Prozess-Matrix'!R5,'Kompetenz-Prozess-Matrix'!G9) -> 0 | O109: =PRODUCT('Rollen-Prozess-Matrix'!S5,'Kompetenz-Prozess-Matrix'!G9) -> 0 | P109: =PRODUCT('Rollen-Prozess-Matrix'!T5,'Kompetenz-Prozess-Matrix'!G9) -> 0 | Q109: =PRODUCT('Rollen-Prozess-Matrix'!U5,'Kompetenz-Prozess-Matrix'!G9) -> 0
C110: 6.2.3 Portfoliomanagement | D110: =PRODUCT('Rollen-Prozess-Matrix'!H6,'Kompetenz-Prozess-Matrix'!G10) -> 0 | E110: =PRODUCT('Rollen-Prozess-Matrix'!I6,'Kompetenz-Prozess-Matrix'!G10) -> 0 | F110: =PRODUCT('Rollen-Prozess-Matrix'!J6,'Kompetenz-Prozess-Matrix'!G10) -> 0 | G110: =PRODUCT('Rollen-Prozess-Matrix'!K6,'Kompetenz-Prozess-Matrix'!G10) -> 0 | H110: =PRODUCT('Rollen-Prozess-Matrix'!L6,'Kompetenz-Prozess-Matrix'!G10) -> 0 | I110: =PRODUCT('Rollen-Prozess-Matrix'!M6,'Kompetenz-Prozess-Matrix'!G10) -> 0 | J110: =PRODUCT('Rollen-Prozess-Matrix'!N6,'Kompetenz-Prozess-Matrix'!G10) -> 0 | K110: =PRODUCT('Rollen-Prozess-Matrix'!O6,'Kompetenz-Prozess-Matrix'!G10) -> 0 | L110: =PRODUCT('Rollen-Prozess-Matrix'!P6,'Kompetenz-Prozess-Matrix'!G10) -> 0 | M110: =PRODUCT('Rollen-Prozess-Matrix'!Q6,'Kompetenz-Prozess-Matrix'!G10) -> 0 | N110: =PRODUCT('Rollen-Prozess-Matrix'!R6,'Kompetenz-Prozess-Matrix'!G10) -> 0 | O110: =PRODUCT('Rollen-Prozess-Matrix'!S6,'Kompetenz-Prozess-Matrix'!G10) -> 0 | P110: =PRODUCT('Rollen-Prozess-Matrix'!T6,'Kompetenz-Prozess-Matrix'!G10) -> 0 | Q110: =PRODUCT('Rollen-Prozess-Matrix'!U6,'Kompetenz-Prozess-Matrix'!G10) -> 0
C111: 6.2.4 Personalwesen-Management | D111: =PRODUCT('Rollen-Prozess-Matrix'!H7,'Kompetenz-Prozess-Matrix'!G11) -> 0 | E111: =PRODUCT('Rollen-Prozess-Matrix'!I7,'Kompetenz-Prozess-Matrix'!G11) -> 0 | F111: =PRODUCT('Rollen-Prozess-Matrix'!J7,'Kompetenz-Prozess-Matrix'!G11) -> 0 | G111: =PRODUCT('Rollen-Prozess-Matrix'!K7,'Kompetenz-Prozess-Matrix'!G11) -> 0 | H111: =PRODUCT('Rollen-Prozess-Matrix'!L7,'Kompetenz-Prozess-Matrix'!G11) -> 0 | I111: =PRODUCT('Rollen-Prozess-Matrix'!M7,'Kompetenz-Prozess-Matrix'!G11) -> 0 | J111: =PRODUCT('Rollen-Prozess-Matrix'!N7,'Kompetenz-Prozess-Matrix'!G11) -> 0 | K111: =PRODUCT('Rollen-Prozess-Matrix'!O7,'Kompetenz-Prozess-Matrix'!G11) -> 0 | L111: =PRODUCT('Rollen-Prozess-Matrix'!P7,'Kompetenz-Prozess-Matrix'!G11) -> 0 | M111: =PRODUCT('Rollen-Prozess-Matrix'!Q7,'Kompetenz-Prozess-Matrix'!G11) -> 0 | N111: =PRODUCT('Rollen-Prozess-Matrix'!R7,'Kompetenz-Prozess-Matrix'!G11) -> 0 | O111: =PRODUCT('Rollen-Prozess-Matrix'!S7,'Kompetenz-Prozess-Matrix'!G11) -> 0 | P111: =PRODUCT('Rollen-Prozess-Matrix'!T7,'Kompetenz-Prozess-Matrix'!G11) -> 0 | Q111: =PRODUCT('Rollen-Prozess-Matrix'!U7,'Kompetenz-Prozess-Matrix'!G11) -> 0
C112: 6.2.5 Qualitätsmanagement | D112: =PRODUCT('Rollen-Prozess-Matrix'!H8,'Kompetenz-Prozess-Matrix'!G12) -> 0 | E112: =PRODUCT('Rollen-Prozess-Matrix'!I8,'Kompetenz-Prozess-Matrix'!G12) -> 0 | F112: =PRODUCT('Rollen-Prozess-Matrix'!J8,'Kompetenz-Prozess-Matrix'!G12) -> 0 | G112: =PRODUCT('Rollen-Prozess-Matrix'!K8,'Kompetenz-Prozess-Matrix'!G12) -> 0 | H112: =PRODUCT('Rollen-Prozess-Matrix'!L8,'Kompetenz-Prozess-Matrix'!G12) -> 0 | I112: =PRODUCT('Rollen-Prozess-Matrix'!M8,'Kompetenz-Prozess-Matrix'!G12) -> 0 | J112: =PRODUCT('Rollen-Prozess-Matrix'!N8,'Kompetenz-Prozess-Matrix'!G12) -> 0 | K112: =PRODUCT('Rollen-Prozess-Matrix'!O8,'Kompetenz-Prozess-Matrix'!G12) -> 0 | L112: =PRODUCT('Rollen-Prozess-Matrix'!P8,'Kompetenz-Prozess-Matrix'!G12) -> 0 | M112: =PRODUCT('Rollen-Prozess-Matrix'!Q8,'Kompetenz-Prozess-Matrix'!G12) -> 0 | N112: =PRODUCT('Rollen-Prozess-Matrix'!R8,'Kompetenz-Prozess-Matrix'!G12) -> 0 | O112: =PRODUCT('Rollen-Prozess-Matrix'!S8,'Kompetenz-Prozess-Matrix'!G12) -> 0 | P112: =PRODUCT('Rollen-Prozess-Matrix'!T8,'Kompetenz-Prozess-Matrix'!G12) -> 0 | Q112: =PRODUCT('Rollen-Prozess-Matrix'!U8,'Kompetenz-Prozess-Matrix'!G12) -> 0
C113: 6.2.6 Wissensmanagement | D113: =PRODUCT('Rollen-Prozess-Matrix'!H9,'Kompetenz-Prozess-Matrix'!G13) -> 0 | E113: =PRODUCT('Rollen-Prozess-Matrix'!I9,'Kompetenz-Prozess-Matrix'!G13) -> 0 | F113: =PRODUCT('Rollen-Prozess-Matrix'!J9,'Kompetenz-Prozess-Matrix'!G13) -> 0 | G113: =PRODUCT('Rollen-Prozess-Matrix'!K9,'Kompetenz-Prozess-Matrix'!G13) -> 0 | H113: =PRODUCT('Rollen-Prozess-Matrix'!L9,'Kompetenz-Prozess-Matrix'!G13) -> 0 | I113: =PRODUCT('Rollen-Prozess-Matrix'!M9,'Kompetenz-Prozess-Matrix'!G13) -> 0 | J113: =PRODUCT('Rollen-Prozess-Matrix'!N9,'Kompetenz-Prozess-Matrix'!G13) -> 0 | K113: =PRODUCT('Rollen-Prozess-Matrix'!O9,'Kompetenz-Prozess-Matrix'!G13) -> 0 | L113: =PRODUCT('Rollen-Prozess-Matrix'!P9,'Kompetenz-Prozess-Matrix'!G13) -> 0 | M113: =PRODUCT('Rollen-Prozess-Matrix'!Q9,'Kompetenz-Prozess-Matrix'!G13) -> 0 | N113: =PRODUCT('Rollen-Prozess-Matrix'!R9,'Kompetenz-Prozess-Matrix'!G13) -> 0 | O113: =PRODUCT('Rollen-Prozess-Matrix'!S9,'Kompetenz-Prozess-Matrix'!G13) -> 0 | P113: =PRODUCT('Rollen-Prozess-Matrix'!T9,'Kompetenz-Prozess-Matrix'!G13) -> 0 | Q113: =PRODUCT('Rollen-Prozess-Matrix'!U9,'Kompetenz-Prozess-Matrix'!G13) -> 0
C114: 6.3.1 Projektierung/Projektplanung | D114: =PRODUCT('Rollen-Prozess-Matrix'!H10,'Kompetenz-Prozess-Matrix'!G14) -> 0 | E114: =PRODUCT('Rollen-Prozess-Matrix'!I10,'Kompetenz-Prozess-Matrix'!G14) -> 0 | F114: =PRODUCT('Rollen-Prozess-Matrix'!J10,'Kompetenz-Prozess-Matrix'!G14) -> 4 | G114: =PRODUCT('Rollen-Prozess-Matrix'!K10,'Kompetenz-Prozess-Matrix'!G14) -> 0 | H114: =PRODUCT('Rollen-Prozess-Matrix'!L10,'Kompetenz-Prozess-Matrix'!G14) -> 6 | I114: =PRODUCT('Rollen-Prozess-Matrix'!M10,'Kompetenz-Prozess-Matrix'!G14) -> 0 | J114: =PRODUCT('Rollen-Prozess-Matrix'!N10,'Kompetenz-Prozess-Matrix'!G14) -> 0 | K114: =PRODUCT('Rollen-Prozess-Matrix'!O10,'Kompetenz-Prozess-Matrix'!G14) -> 0 | L114: =PRODUCT('Rollen-Prozess-Matrix'!P10,'Kompetenz-Prozess-Matrix'!G14) -> 0 | M114: =PRODUCT('Rollen-Prozess-Matrix'!Q10,'Kompetenz-Prozess-Matrix'!G14) -> 0 | N114: =PRODUCT('Rollen-Prozess-Matrix'!R10,'Kompetenz-Prozess-Matrix'!G14) -> 0 | O114: =PRODUCT('Rollen-Prozess-Matrix'!S10,'Kompetenz-Prozess-Matrix'!G14) -> 0 | P114: =PRODUCT('Rollen-Prozess-Matrix'!T10,'Kompetenz-Prozess-Matrix'!G14) -> 0 | Q114: =PRODUCT('Rollen-Prozess-Matrix'!U10,'Kompetenz-Prozess-Matrix'!G14) -> 0
C115: 6.3.2 Projektbewertung und Steuerung | D115: =PRODUCT('Rollen-Prozess-Matrix'!H11,'Kompetenz-Prozess-Matrix'!G15) -> 0 | E115: =PRODUCT('Rollen-Prozess-Matrix'!I11,'Kompetenz-Prozess-Matrix'!G15) -> 0 | F115: =PRODUCT('Rollen-Prozess-Matrix'!J11,'Kompetenz-Prozess-Matrix'!G15) -> 4 | G115: =PRODUCT('Rollen-Prozess-Matrix'!K11,'Kompetenz-Prozess-Matrix'!G15) -> 0 | H115: =PRODUCT('Rollen-Prozess-Matrix'!L11,'Kompetenz-Prozess-Matrix'!G15) -> 6 | I115: =PRODUCT('Rollen-Prozess-Matrix'!M11,'Kompetenz-Prozess-Matrix'!G15) -> 0 | J115: =PRODUCT('Rollen-Prozess-Matrix'!N11,'Kompetenz-Prozess-Matrix'!G15) -> 0 | K115: =PRODUCT('Rollen-Prozess-Matrix'!O11,'Kompetenz-Prozess-Matrix'!G15) -> 0 | L115: =PRODUCT('Rollen-Prozess-Matrix'!P11,'Kompetenz-Prozess-Matrix'!G15) -> 0 | M115: =PRODUCT('Rollen-Prozess-Matrix'!Q11,'Kompetenz-Prozess-Matrix'!G15) -> 0 | N115: =PRODUCT('Rollen-Prozess-Matrix'!R11,'Kompetenz-Prozess-Matrix'!G15) -> 0 | O115: =PRODUCT('Rollen-Prozess-Matrix'!S11,'Kompetenz-Prozess-Matrix'!G15) -> 0 | P115: =PRODUCT('Rollen-Prozess-Matrix'!T11,'Kompetenz-Prozess-Matrix'!G15) -> 0 | Q115: =PRODUCT('Rollen-Prozess-Matrix'!U11,'Kompetenz-Prozess-Matrix'!G15) -> 2
C116: 6.3.3 Entscheidungsmanagement | D116: =PRODUCT('Rollen-Prozess-Matrix'!H12,'Kompetenz-Prozess-Matrix'!G16) -> 0 | E116: =PRODUCT('Rollen-Prozess-Matrix'!I12,'Kompetenz-Prozess-Matrix'!G16) -> 2 | F116: =PRODUCT('Rollen-Prozess-Matrix'!J12,'Kompetenz-Prozess-Matrix'!G16) -> 2 | G116: =PRODUCT('Rollen-Prozess-Matrix'!K12,'Kompetenz-Prozess-Matrix'!G16) -> 0 | H116: =PRODUCT('Rollen-Prozess-Matrix'!L12,'Kompetenz-Prozess-Matrix'!G16) -> 3 | I116: =PRODUCT('Rollen-Prozess-Matrix'!M12,'Kompetenz-Prozess-Matrix'!G16) -> 2 | J116: =PRODUCT('Rollen-Prozess-Matrix'!N12,'Kompetenz-Prozess-Matrix'!G16) -> 1 | K116: =PRODUCT('Rollen-Prozess-Matrix'!O12,'Kompetenz-Prozess-Matrix'!G16) -> 1 | L116: =PRODUCT('Rollen-Prozess-Matrix'!P12,'Kompetenz-Prozess-Matrix'!G16) -> 1 | M116: =PRODUCT('Rollen-Prozess-Matrix'!Q12,'Kompetenz-Prozess-Matrix'!G16) -> 0 | N116: =PRODUCT('Rollen-Prozess-Matrix'!R12,'Kompetenz-Prozess-Matrix'!G16) -> 0 | O116: =PRODUCT('Rollen-Prozess-Matrix'!S12,'Kompetenz-Prozess-Matrix'!G16) -> 0 | P116: =PRODUCT('Rollen-Prozess-Matrix'!T12,'Kompetenz-Prozess-Matrix'!G16) -> 1 | Q116: =PRODUCT('Rollen-Prozess-Matrix'!U12,'Kompetenz-Prozess-Matrix'!G16) -> 2
C117: 6.3.4 Risiko-Management | D117: =PRODUCT('Rollen-Prozess-Matrix'!H13,'Kompetenz-Prozess-Matrix'!G17) -> 0 | E117: =PRODUCT('Rollen-Prozess-Matrix'!I13,'Kompetenz-Prozess-Matrix'!G17) -> 1 | F117: =PRODUCT('Rollen-Prozess-Matrix'!J13,'Kompetenz-Prozess-Matrix'!G17) -> 2 | G117: =PRODUCT('Rollen-Prozess-Matrix'!K13,'Kompetenz-Prozess-Matrix'!G17) -> 0 | H117: =PRODUCT('Rollen-Prozess-Matrix'!L13,'Kompetenz-Prozess-Matrix'!G17) -> 3 | I117: =PRODUCT('Rollen-Prozess-Matrix'!M13,'Kompetenz-Prozess-Matrix'!G17) -> 2 | J117: =PRODUCT('Rollen-Prozess-Matrix'!N13,'Kompetenz-Prozess-Matrix'!G17) -> 1 | K117: =PRODUCT('Rollen-Prozess-Matrix'!O13,'Kompetenz-Prozess-Matrix'!G17) -> 1 | L117: =PRODUCT('Rollen-Prozess-Matrix'!P13,'Kompetenz-Prozess-Matrix'!G17) -> 0 | M117: =PRODUCT('Rollen-Prozess-Matrix'!Q13,'Kompetenz-Prozess-Matrix'!G17) -> 0 | N117: =PRODUCT('Rollen-Prozess-Matrix'!R13,'Kompetenz-Prozess-Matrix'!G17) -> 0 | O117: =PRODUCT('Rollen-Prozess-Matrix'!S13,'Kompetenz-Prozess-Matrix'!G17) -> 1 | P117: =PRODUCT('Rollen-Prozess-Matrix'!T13,'Kompetenz-Prozess-Matrix'!G17) -> 0 | Q117: =PRODUCT('Rollen-Prozess-Matrix'!U13,'Kompetenz-Prozess-Matrix'!G17) -> 0
... C138: Qualifizierung | D138: =PRODUCT('Rollen-Prozess-Matrix'!H34,'Kompetenz-Prozess-Matrix'!G38) -> 0 | E138: =PRODUCT('Rollen-Prozess-Matrix'!I34,'Kompetenz-Prozess-Matrix'!G38) -> 0 | F138: =PRODUCT('Rollen-Prozess-Matrix'!J34,'Kompetenz-Prozess-Matrix'!G38) -> 0 | G138: =PRODUCT('Rollen-Prozess-Matrix'!K34,'Kompetenz-Prozess-Matrix'!G38) -> 4 | H138: =PRODUCT('Rollen-Prozess-Matrix'!L34,'Kompetenz-Prozess-Matrix'!G38) -> 0 | I138: =PRODUCT('Rollen-Prozess-Matrix'!M34,'Kompetenz-Prozess-Matrix'!G38) -> 0 | J138: =PRODUCT('Rollen-Prozess-Matrix'!N34,'Kompetenz-Prozess-Matrix'!G38) -> 0 | K138: =PRODUCT('Rollen-Prozess-Matrix'!O34,'Kompetenz-Prozess-Matrix'!G38) -> 0 | L138: =PRODUCT('Rollen-Prozess-Matrix'!P34,'Kompetenz-Prozess-Matrix'!G38) -> 0 | M138: =PRODUCT('Rollen-Prozess-Matrix'!Q34,'Kompetenz-Prozess-Matrix'!G38) -> 0 | N138: =PRODUCT('Rollen-Prozess-Matrix'!R34,'Kompetenz-Prozess-Matrix'!G38) -> 0 | O138: =PRODUCT('Rollen-Prozess-Matrix'!S34,'Kompetenz-Prozess-Matrix'!G38) -> 0 | P138: =PRODUCT('Rollen-Prozess-Matrix'!T34,'Kompetenz-Prozess-Matrix'!G38) -> 0 | Q138: =PRODUCT('Rollen-Prozess-Matrix'!U34,'Kompetenz-Prozess-Matrix'!G38) -> 0
A139: Fachkompetenzen | B139: Anforderungsmanagement | D139: =MAX(D140:D172) -> 2 | E139: =MAX(E140:E172) -> 4 | F139: =MAX(F140:F172) -> 2 | G139: =MAX(G140:G172) -> 4 | H139: =MAX(H140:H172) -> 6 | I139: =MAX(I140:I172) -> 4 | J139: =MAX(J140:J172) -> 2 | K139: =MAX(K140:K172) -> 2 | ... Q139: =MAX(Q140:Q172) -> 2 | S139: 1
C140: 6.1.1 Akquisition | D140: =PRODUCT('Rollen-Prozess-Matrix'!H2,'Kompetenz-Prozess-Matrix'!H6) -> 0 | E140: =PRODUCT('Rollen-Prozess-Matrix'!I2,'Kompetenz-Prozess-Matrix'!H6) -> 0 | F140: =PRODUCT('Rollen-Prozess-Matrix'!J2,'Kompetenz-Prozess-Matrix'!H6) -> 0 | G140: =PRODUCT('Rollen-Prozess-Matrix'!K2,'Kompetenz-Prozess-Matrix'!H6) -> 0 | H140: =PRODUCT('Rollen-Prozess-Matrix'!L2,'Kompetenz-Prozess-Matrix'!H6) -> 3 | I140: =PRODUCT('Rollen-Prozess-Matrix'!M2,'Kompetenz-Prozess-Matrix'!H6) -> 1 | J140: =PRODUCT('Rollen-Prozess-Matrix'!N2,'Kompetenz-Prozess-Matrix'!H6) -> 1 | K140: =PRODUCT('Rollen-Prozess-Matrix'!O2,'Kompetenz-Prozess-Matrix'!H6) -> 2 | L140: =PRODUCT('Rollen-Prozess-Matrix'!P2,'Kompetenz-Prozess-Matrix'!H6) -> 1 | M140: =PRODUCT('Rollen-Prozess-Matrix'!Q2,'Kompetenz-Prozess-Matrix'!H6) -> 0 | N140: =PRODUCT('Rollen-Prozess-Matrix'!R2,'Kompetenz-Prozess-Matrix'!H6) -> 0 | O140: =PRODUCT('Rollen-Prozess-Matrix'!S2,'Kompetenz-Prozess-Matrix'!H6) -> 0 | P140: =PRODUCT('Rollen-Prozess-Matrix'!T2,'Kompetenz-Prozess-Matrix'!H6) -> 0 | Q140: =PRODUCT('Rollen-Prozess-Matrix'!U2,'Kompetenz-Prozess-Matrix'!H6) -> 0
C141: 6.1.2 Lieferung | D141: =PRODUCT('Rollen-Prozess-Matrix'!H3,'Kompetenz-Prozess-Matrix'!H7) -> 0 | E141: =PRODUCT('Rollen-Prozess-Matrix'!I3,'Kompetenz-Prozess-Matrix'!H7) -> 2 | F141: =PRODUCT('Rollen-Prozess-Matrix'!J3,'Kompetenz-Prozess-Matrix'!H7) -> 1 | G141: =PRODUCT('Rollen-Prozess-Matrix'!K3,'Kompetenz-Prozess-Matrix'!H7) -> 0 | H141: =PRODUCT('Rollen-Prozess-Matrix'!L3,'Kompetenz-Prozess-Matrix'!H7) -> 3 | I141: =PRODUCT('Rollen-Prozess-Matrix'!M3,'Kompetenz-Prozess-Matrix'!H7) -> 1 | J141: =PRODUCT('Rollen-Prozess-Matrix'!N3,'Kompetenz-Prozess-Matrix'!H7) -> 0 | K141: =PRODUCT('Rollen-Prozess-Matrix'!O3,'Kompetenz-Prozess-Matrix'!H7) -> 1 | L141: =PRODUCT('Rollen-Prozess-Matrix'!P3,'Kompetenz-Prozess-Matrix'!H7) -> 0 | M141: =PRODUCT('Rollen-Prozess-Matrix'!Q3,'Kompetenz-Prozess-Matrix'!H7) -> 0 | N141: =PRODUCT('Rollen-Prozess-Matrix'!R3,'Kompetenz-Prozess-Matrix'!H7) -> 1 | O141: =PRODUCT('Rollen-Prozess-Matrix'!S3,'Kompetenz-Prozess-Matrix'!H7) -> 0 | P141: =PRODUCT('Rollen-Prozess-Matrix'!T3,'Kompetenz-Prozess-Matrix'!H7) -> 0 | Q141: =PRODUCT('Rollen-Prozess-Matrix'!U3,'Kompetenz-Prozess-Matrix'!H7) -> 0
C142: 6.2.1 Lebenszyklus-Modell-Management | D142: =PRODUCT('Rollen-Prozess-Matrix'!H4,'Kompetenz-Prozess-Matrix'!H8) -> 0 | E142: =PRODUCT('Rollen-Prozess-Matrix'!I4,'Kompetenz-Prozess-Matrix'!H8) -> 0 | F142: =PRODUCT('Rollen-Prozess-Matrix'!J4,'Kompetenz-Prozess-Matrix'!H8) -> 0 | G142: =PRODUCT('Rollen-Prozess-Matrix'!K4,'Kompetenz-Prozess-Matrix'!H8) -> 2 | H142: =PRODUCT('Rollen-Prozess-Matrix'!L4,'Kompetenz-Prozess-Matrix'!H8) -> 6 | I142: =PRODUCT('Rollen-Prozess-Matrix'!M4,'Kompetenz-Prozess-Matrix'!H8) -> 0 | J142: =PRODUCT('Rollen-Prozess-Matrix'!N4,'Kompetenz-Prozess-Matrix'!H8) -> 0 | K142: =PRODUCT('Rollen-Prozess-Matrix'!O4,'Kompetenz-Prozess-Matrix'!H8) -> 0 | L142: =PRODUCT('Rollen-Prozess-Matrix'!P4,'Kompetenz-Prozess-Matrix'!H8) -> 0 | M142: =PRODUCT('Rollen-Prozess-Matrix'!Q4,'Kompetenz-Prozess-Matrix'!H8) -> 0 | N142: =PRODUCT('Rollen-Prozess-Matrix'!R4,'Kompetenz-Prozess-Matrix'!H8) -> 0 | O142: =PRODUCT('Rollen-Prozess-Matrix'!S4,'Kompetenz-Prozess-Matrix'!H8) -> 0 | P142: =PRODUCT('Rollen-Prozess-Matrix'!T4,'Kompetenz-Prozess-Matrix'!H8) -> 0 | Q142: =PRODUCT('Rollen-Prozess-Matrix'!U4,'Kompetenz-Prozess-Matrix'!H8) -> 0
C143: 6.2.2 Verwaltung der Infrastruktur | D143: =PRODUCT('Rollen-Prozess-Matrix'!H5,'Kompetenz-Prozess-Matrix'!H9) -> 0 | E143: =PRODUCT('Rollen-Prozess-Matrix'!I5,'Kompetenz-Prozess-Matrix'!H9) -> 0 | F143: =PRODUCT('Rollen-Prozess-Matrix'!J5,'Kompetenz-Prozess-Matrix'!H9) -> 0 | G143: =PRODUCT('Rollen-Prozess-Matrix'!K5,'Kompetenz-Prozess-Matrix'!H9) -> 2 | H143: =PRODUCT('Rollen-Prozess-Matrix'!L5,'Kompetenz-Prozess-Matrix'!H9) -> 3 | I143: =PRODUCT('Rollen-Prozess-Matrix'!M5,'Kompetenz-Prozess-Matrix'!H9) -> 0 | J143: =PRODUCT('Rollen-Prozess-Matrix'!N5,'Kompetenz-Prozess-Matrix'!H9) -> 0 | K143: =PRODUCT('Rollen-Prozess-Matrix'!O5,'Kompetenz-Prozess-Matrix'!H9) -> 0 | L143: =PRODUCT('Rollen-Prozess-Matrix'!P5,'Kompetenz-Prozess-Matrix'!H9) -> 0 | M143: =PRODUCT('Rollen-Prozess-Matrix'!Q5,'Kompetenz-Prozess-Matrix'!H9) -> 0 | N143: =PRODUCT('Rollen-Prozess-Matrix'!R5,'Kompetenz-Prozess-Matrix'!H9) -> 0 | O143: =PRODUCT('Rollen-Prozess-Matrix'!S5,'Kompetenz-Prozess-Matrix'!H9) -> 0 | P143: =PRODUCT('Rollen-Prozess-Matrix'!T5,'Kompetenz-Prozess-Matrix'!H9) -> 0 | Q143: =PRODUCT('Rollen-Prozess-Matrix'!U5,'Kompetenz-Prozess-Matrix'!H9) -> 0
C144: 6.2.3 Portfoliomanagement | D144: =PRODUCT('Rollen-Prozess-Matrix'!H6,'Kompetenz-Prozess-Matrix'!H10) -> 0 | E144: =PRODUCT('Rollen-Prozess-Matrix'!I6,'Kompetenz-Prozess-Matrix'!H10) -> 0 | F144: =PRODUCT('Rollen-Prozess-Matrix'!J6,'Kompetenz-Prozess-Matrix'!H10) -> 0 | G144: =PRODUCT('Rollen-Prozess-Matrix'!K6,'Kompetenz-Prozess-Matrix'!H10) -> 0 | H144: =PRODUCT('Rollen-Prozess-Matrix'!L6,'Kompetenz-Prozess-Matrix'!H10) -> 0 | I144: =PRODUCT('Rollen-Prozess-Matrix'!M6,'Kompetenz-Prozess-Matrix'!H10) -> 0 | J144: =PRODUCT('Rollen-Prozess-Matrix'!N6,'Kompetenz-Prozess-Matrix'!H10) -> 0 | K144: =PRODUCT('Rollen-Prozess-Matrix'!O6,'Kompetenz-Prozess-Matrix'!H10) -> 0 | L144: =PRODUCT('Rollen-Prozess-Matrix'!P6,'Kompetenz-Prozess-Matrix'!H10) -> 0 | M144: =PRODUCT('Rollen-Prozess-Matrix'!Q6,'Kompetenz-Prozess-Matrix'!H10) -> 0 | N144: =PRODUCT('Rollen-Prozess-Matrix'!R6,'Kompetenz-Prozess-Matrix'!H10) -> 0 | O144: =PRODUCT('Rollen-Prozess-Matrix'!S6,'Kompetenz-Prozess-Matrix'!H10) -> 0 | P144: =PRODUCT('Rollen-Prozess-Matrix'!T6,'Kompetenz-Prozess-Matrix'!H10) -> 0 | Q144: =PRODUCT('Rollen-Prozess-Matrix'!U6,'Kompetenz-Prozess-Matrix'!H10) -> 0
C145: 6.2.4 Personalwesen-Management | D145: =PRODUCT('Rollen-Prozess-Matrix'!H7,'Kompetenz-Prozess-Matrix'!H11) -> 0 | E145: =PRODUCT('Rollen-Prozess-Matrix'!I7,'Kompetenz-Prozess-Matrix'!H11) -> 0 | F145: =PRODUCT('Rollen-Prozess-Matrix'!J7,'Kompetenz-Prozess-Matrix'!H11) -> 0 | G145: =PRODUCT('Rollen-Prozess-Matrix'!K7,'Kompetenz-Prozess-Matrix'!H11) -> 0 | H145: =PRODUCT('Rollen-Prozess-Matrix'!L7,'Kompetenz-Prozess-Matrix'!H11) -> 0 | I145: =PRODUCT('Rollen-Prozess-Matrix'!M7,'Kompetenz-Prozess-Matrix'!H11) -> 0 | J145: =PRODUCT('Rollen-Prozess-Matrix'!N7,'Kompetenz-Prozess-Matrix'!H11) -> 0 | K145: =PRODUCT('Rollen-Prozess-Matrix'!O7,'Kompetenz-Prozess-Matrix'!H11) -> 0 | L145: =PRODUCT('Rollen-Prozess-Matrix'!P7,'Kompetenz-Prozess-Matrix'!H11) -> 0 | M145: =PRODUCT('Rollen-Prozess-Matrix'!Q7,'Kompetenz-Prozess-Matrix'!H11) -> 0 | N145: =PRODUCT('Rollen-Prozess-Matrix'!R7,'Kompetenz-Prozess-Matrix'!H11) -> 0 | O145: =PRODUCT('Rollen-Prozess-Matrix'!S7,'Kompetenz-Prozess-Matrix'!H11) -> 0 | P145: =PRODUCT('Rollen-Prozess-Matrix'!T7,'Kompetenz-Prozess-Matrix'!H11) -> 0 | Q145: =PRODUCT('Rollen-Prozess-Matrix'!U7,'Kompetenz-Prozess-Matrix'!H11) -> 0
C146: 6.2.5 Qualitätsmanagement | D146: =PRODUCT('Rollen-Prozess-Matrix'!H8,'Kompetenz-Prozess-Matrix'!H12) -> 0 | E146: =PRODUCT('Rollen-Prozess-Matrix'!I8,'Kompetenz-Prozess-Matrix'!H12) -> 0 | F146: =PRODUCT('Rollen-Prozess-Matrix'!J8,'Kompetenz-Prozess-Matrix'!H12) -> 0 | G146: =PRODUCT('Rollen-Prozess-Matrix'!K8,'Kompetenz-Prozess-Matrix'!H12) -> 0 | H146: =PRODUCT('Rollen-Prozess-Matrix'!L8,'Kompetenz-Prozess-Matrix'!H12) -> 6 | I146: =PRODUCT('Rollen-Prozess-Matrix'!M8,'Kompetenz-Prozess-Matrix'!H12) -> 0 | J146: =PRODUCT('Rollen-Prozess-Matrix'!N8,'Kompetenz-Prozess-Matrix'!H12) -> 0 | K146: =PRODUCT('Rollen-Prozess-Matrix'!O8,'Kompetenz-Prozess-Matrix'!H12) -> 0 | L146: =PRODUCT('Rollen-Prozess-Matrix'!P8,'Kompetenz-Prozess-Matrix'!H12) -> 2 | M146: =PRODUCT('Rollen-Prozess-Matrix'!Q8,'Kompetenz-Prozess-Matrix'!H12) -> 0 | N146: =PRODUCT('Rollen-Prozess-Matrix'!R8,'Kompetenz-Prozess-Matrix'!H12) -> 0 | O146: =PRODUCT('Rollen-Prozess-Matrix'!S8,'Kompetenz-Prozess-Matrix'!H12) -> 4 | P146: =PRODUCT('Rollen-Prozess-Matrix'!T8,'Kompetenz-Prozess-Matrix'!H12) -> 0 | Q146: =PRODUCT('Rollen-Prozess-Matrix'!U8,'Kompetenz-Prozess-Matrix'!H12) -> 0
C147: 6.2.6 Wissensmanagement | D147: =PRODUCT('Rollen-Prozess-Matrix'!H9,'Kompetenz-Prozess-Matrix'!H13) -> 0 | E147: =PRODUCT('Rollen-Prozess-Matrix'!I9,'Kompetenz-Prozess-Matrix'!H13) -> 0 | F147: =PRODUCT('Rollen-Prozess-Matrix'!J9,'Kompetenz-Prozess-Matrix'!H13) -> 0 | G147: =PRODUCT('Rollen-Prozess-Matrix'!K9,'Kompetenz-Prozess-Matrix'!H13) -> 0 | H147: =PRODUCT('Rollen-Prozess-Matrix'!L9,'Kompetenz-Prozess-Matrix'!H13) -> 0 | I147: =PRODUCT('Rollen-Prozess-Matrix'!M9,'Kompetenz-Prozess-Matrix'!H13) -> 0 | J147: =PRODUCT('Rollen-Prozess-Matrix'!N9,'Kompetenz-Prozess-Matrix'!H13) -> 0 | K147: =PRODUCT('Rollen-Prozess-Matrix'!O9,'Kompetenz-Prozess-Matrix'!H13) -> 0 | L147: =PRODUCT('Rollen-Prozess-Matrix'!P9,'Kompetenz-Prozess-Matrix'!H13) -> 0 | M147: =PRODUCT('Rollen-Prozess-Matrix'!Q9,'Kompetenz-Prozess-Matrix'!H13) -> 0 | N147: =PRODUCT('Rollen-Prozess-Matrix'!R9,'Kompetenz-Prozess-Matrix'!H13) -> 0 | O147: =PRODUCT('Rollen-Prozess-Matrix'!S9,'Kompetenz-Prozess-Matrix'!H13) -> 0 | P147: =PRODUCT('Rollen-Prozess-Matrix'!T9,'Kompetenz-Prozess-Matrix'!H13) -> 0 | Q147: =PRODUCT('Rollen-Prozess-Matrix'!U9,'Kompetenz-Prozess-Matrix'!H13) -> 0
C148: 6.3.1 Projektierung/Projektplanung | D148: =PRODUCT('Rollen-Prozess-Matrix'!H10,'Kompetenz-Prozess-Matrix'!H14) -> 0 | E148: =PRODUCT('Rollen-Prozess-Matrix'!I10,'Kompetenz-Prozess-Matrix'!H14) -> 0 | F148: =PRODUCT('Rollen-Prozess-Matrix'!J10,'Kompetenz-Prozess-Matrix'!H14) -> 2 | G148: =PRODUCT('Rollen-Prozess-Matrix'!K10,'Kompetenz-Prozess-Matrix'!H14) -> 0 | H148: =PRODUCT('Rollen-Prozess-Matrix'!L10,'Kompetenz-Prozess-Matrix'!H14) -> 3 | I148: =PRODUCT('Rollen-Prozess-Matrix'!M10,'Kompetenz-Prozess-Matrix'!H14) -> 0 | J148: =PRODUCT('Rollen-Prozess-Matrix'!N10,'Kompetenz-Prozess-Matrix'!H14) -> 0 | K148: =PRODUCT('Rollen-Prozess-Matrix'!O10,'Kompetenz-Prozess-Matrix'!H14) -> 0 | L148: =PRODUCT('Rollen-Prozess-Matrix'!P10,'Kompetenz-Prozess-Matrix'!H14) -> 0 | M148: =PRODUCT('Rollen-Prozess-Matrix'!Q10,'Kompetenz-Prozess-Matrix'!H14) -> 0 | N148: =PRODUCT('Rollen-Prozess-Matrix'!R10,'Kompetenz-Prozess-Matrix'!H14) -> 0 | O148: =PRODUCT('Rollen-Prozess-Matrix'!S10,'Kompetenz-Prozess-Matrix'!H14) -> 0 | P148: =PRODUCT('Rollen-Prozess-Matrix'!T10,'Kompetenz-Prozess-Matrix'!H14) -> 0 | Q148: =PRODUCT('Rollen-Prozess-Matrix'!U10,'Kompetenz-Prozess-Matrix'!H14) -> 0
C149: 6.3.2 Projektbewertung und Steuerung | D149: =PRODUCT('Rollen-Prozess-Matrix'!H11,'Kompetenz-Prozess-Matrix'!H15) -> 0 | E149: =PRODUCT('Rollen-Prozess-Matrix'!I11,'Kompetenz-Prozess-Matrix'!H15) -> 0 | F149: =PRODUCT('Rollen-Prozess-Matrix'!J11,'Kompetenz-Prozess-Matrix'!H15) -> 2 | G149: =PRODUCT('Rollen-Prozess-Matrix'!K11,'Kompetenz-Prozess-Matrix'!H15) -> 0 | H149: =PRODUCT('Rollen-Prozess-Matrix'!L11,'Kompetenz-Prozess-Matrix'!H15) -> 3 | I149: =PRODUCT('Rollen-Prozess-Matrix'!M11,'Kompetenz-Prozess-Matrix'!H15) -> 0 | J149: =PRODUCT('Rollen-Prozess-Matrix'!N11,'Kompetenz-Prozess-Matrix'!H15) -> 0 | K149: =PRODUCT('Rollen-Prozess-Matrix'!O11,'Kompetenz-Prozess-Matrix'!H15) -> 0 | L149: =PRODUCT('Rollen-Prozess-Matrix'!P11,'Kompetenz-Prozess-Matrix'!H15) -> 0 | M149: =PRODUCT('Rollen-Prozess-Matrix'!Q11,'Kompetenz-Prozess-Matrix'!H15) -> 0 | N149: =PRODUCT('Rollen-Prozess-Matrix'!R11,'Kompetenz-Prozess-Matrix'!H15) -> 0 | O149: =PRODUCT('Rollen-Prozess-Matrix'!S11,'Kompetenz-Prozess-Matrix'!H15) -> 0 | P149: =PRODUCT('Rollen-Prozess-Matrix'!T11,'Kompetenz-Prozess-Matrix'!H15) -> 0 | Q149: =PRODUCT('Rollen-Prozess-Matrix'!U11,'Kompetenz-Prozess-Matrix'!H15) -> 1
C150: 6.3.3 Entscheidungsmanagement | D150: =PRODUCT('Rollen-Prozess-Matrix'!H12,'Kompetenz-Prozess-Matrix'!H16) -> 0 | E150: =PRODUCT('Rollen-Prozess-Matrix'!I12,'Kompetenz-Prozess-Matrix'!H16) -> 0 | F150: =PRODUCT('Rollen-Prozess-Matrix'!J12,'Kompetenz-Prozess-Matrix'!H16) -> 0 | G150: =PRODUCT('Rollen-Prozess-Matrix'!K12,'Kompetenz-Prozess-Matrix'!H16) -> 0 | H150: =PRODUCT('Rollen-Prozess-Matrix'!L12,'Kompetenz-Prozess-Matrix'!H16) -> 0 | I150: =PRODUCT('Rollen-Prozess-Matrix'!M12,'Kompetenz-Prozess-Matrix'!H16) -> 0 | J150: =PRODUCT('Rollen-Prozess-Matrix'!N12,'Kompetenz-Prozess-Matrix'!H16) -> 0 | K150: =PRODUCT('Rollen-Prozess-Matrix'!O12,'Kompetenz-Prozess-Matrix'!H16) -> 0 | L150: =PRODUCT('Rollen-Prozess-Matrix'!P12,'Kompetenz-Prozess-Matrix'!H16) -> 0 | M150: =PRODUCT('Rollen-Prozess-Matrix'!Q12,'Kompetenz-Prozess-Matrix'!H16) -> 0 | N150: =PRODUCT('Rollen-Prozess-Matrix'!R12,'Kompetenz-Prozess-Matrix'!H16) -> 0 | O150: =PRODUCT('Rollen-Prozess-Matrix'!S12,'Kompetenz-Prozess-Matrix'!H16) -> 0 | P150: =PRODUCT('Rollen-Prozess-Matrix'!T12,'Kompetenz-Prozess-Matrix'!H16) -> 0 | Q150: =PRODUCT('Rollen-Prozess-Matrix'!U12,'Kompetenz-Prozess-Matrix'!H16) -> 0
C151: 6.3.4 Risiko-Management | D151: =PRODUCT('Rollen-Prozess-Matrix'!H13,'Kompetenz-Prozess-Matrix'!H17) -> 0 | E151: =PRODUCT('Rollen-Prozess-Matrix'!I13,'Kompetenz-Prozess-Matrix'!H17) -> 1 | F151: =PRODUCT('Rollen-Prozess-Matrix'!J13,'Kompetenz-Prozess-Matrix'!H17) -> 2 | G151: =PRODUCT('Rollen-Prozess-Matrix'!K13,'Kompetenz-Prozess-Matrix'!H17) -> 0 | H151: =PRODUCT('Rollen-Prozess-Matrix'!L13,'Kompetenz-Prozess-Matrix'!H17) -> 3 | I151: =PRODUCT('Rollen-Prozess-Matrix'!M13,'Kompetenz-Prozess-Matrix'!H17) -> 2 | J151: =PRODUCT('Rollen-Prozess-Matrix'!N13,'Kompetenz-Prozess-Matrix'!H17) -> 1 | K151: =PRODUCT('Rollen-Prozess-Matrix'!O13,'Kompetenz-Prozess-Matrix'!H17) -> 1 | L151: =PRODUCT('Rollen-Prozess-Matrix'!P13,'Kompetenz-Prozess-Matrix'!H17) -> 0 | M151: =PRODUCT('Rollen-Prozess-Matrix'!Q13,'Kompetenz-Prozess-Matrix'!H17) -> 0 | N151: =PRODUCT('Rollen-Prozess-Matrix'!R13,'Kompetenz-Prozess-Matrix'!H17) -> 0 | O151: =PRODUCT('Rollen-Prozess-Matrix'!S13,'Kompetenz-Prozess-Matrix'!H17) -> 1 | P151: =PRODUCT('Rollen-Prozess-Matrix'!T13,'Kompetenz-Prozess-Matrix'!H17) -> 0 | Q151: =PRODUCT('Rollen-Prozess-Matrix'!U13,'Kompetenz-Prozess-Matrix'!H17) -> 0
... C172: Qualifizierung | D172: =PRODUCT('Rollen-Prozess-Matrix'!H34,'Kompetenz-Prozess-Matrix'!H38) -> 0 | E172: =PRODUCT('Rollen-Prozess-Matrix'!I34,'Kompetenz-Prozess-Matrix'!H38) -> 0 | F172: =PRODUCT('Rollen-Prozess-Matrix'!J34,'Kompetenz-Prozess-Matrix'!H38) -> 0 | G172: =PRODUCT('Rollen-Prozess-Matrix'!K34,'Kompetenz-Prozess-Matrix'!H38) -> 4 | H172: =PRODUCT('Rollen-Prozess-Matrix'!L34,'Kompetenz-Prozess-Matrix'!H38) -> 0 | I172: =PRODUCT('Rollen-Prozess-Matrix'!M34,'Kompetenz-Prozess-Matrix'!H38) -> 0 | J172: =PRODUCT('Rollen-Prozess-Matrix'!N34,'Kompetenz-Prozess-Matrix'!H38) -> 0 | K172: =PRODUCT('Rollen-Prozess-Matrix'!O34,'Kompetenz-Prozess-Matrix'!H38) -> 0 | L172: =PRODUCT('Rollen-Prozess-Matrix'!P34,'Kompetenz-Prozess-Matrix'!H38) -> 0 | M172: =PRODUCT('Rollen-Prozess-Matrix'!Q34,'Kompetenz-Prozess-Matrix'!H38) -> 0 | N172: =PRODUCT('Rollen-Prozess-Matrix'!R34,'Kompetenz-Prozess-Matrix'!H38) -> 0 | O172: =PRODUCT('Rollen-Prozess-Matrix'!S34,'Kompetenz-Prozess-Matrix'!H38) -> 0 | P172: =PRODUCT('Rollen-Prozess-Matrix'!T34,'Kompetenz-Prozess-Matrix'!H38) -> 0 | Q172: =PRODUCT('Rollen-Prozess-Matrix'!U34,'Kompetenz-Prozess-Matrix'!H38) -> 0
B173: System-Architekturgestaltung | D173: =MAX(D174:D206) -> 0 | E173: =MAX(E174:E206) -> 2 | F173: =MAX(F174:F206) -> 2 | G173: =MAX(G174:G206) -> 4 | H173: =MAX(H174:H206) -> 6 | I173: =MAX(I174:I206) -> 4 | J173: =MAX(J174:J206) -> 4 | K173: =MAX(K174:K206) -> 2 | ... Q173: =MAX(Q174:Q206) -> 1 | S173: 1
C174: 6.1.1 Akquisition | D174: =PRODUCT('Rollen-Prozess-Matrix'!H2,'Kompetenz-Prozess-Matrix'!I6) -> 0 | E174: =PRODUCT('Rollen-Prozess-Matrix'!I2,'Kompetenz-Prozess-Matrix'!I6) -> 0 | F174: =PRODUCT('Rollen-Prozess-Matrix'!J2,'Kompetenz-Prozess-Matrix'!I6) -> 0 | G174: =PRODUCT('Rollen-Prozess-Matrix'!K2,'Kompetenz-Prozess-Matrix'!I6) -> 0 | H174: =PRODUCT('Rollen-Prozess-Matrix'!L2,'Kompetenz-Prozess-Matrix'!I6) -> 0 | I174: =PRODUCT('Rollen-Prozess-Matrix'!M2,'Kompetenz-Prozess-Matrix'!I6) -> 0 | J174: =PRODUCT('Rollen-Prozess-Matrix'!N2,'Kompetenz-Prozess-Matrix'!I6) -> 0 | K174: =PRODUCT('Rollen-Prozess-Matrix'!O2,'Kompetenz-Prozess-Matrix'!I6) -> 0 | L174: =PRODUCT('Rollen-Prozess-Matrix'!P2,'Kompetenz-Prozess-Matrix'!I6) -> 0 | M174: =PRODUCT('Rollen-Prozess-Matrix'!Q2,'Kompetenz-Prozess-Matrix'!I6) -> 0 | N174: =PRODUCT('Rollen-Prozess-Matrix'!R2,'Kompetenz-Prozess-Matrix'!I6) -> 0 | O174: =PRODUCT('Rollen-Prozess-Matrix'!S2,'Kompetenz-Prozess-Matrix'!I6) -> 0 | P174: =PRODUCT('Rollen-Prozess-Matrix'!T2,'Kompetenz-Prozess-Matrix'!I6) -> 0 | Q174: =PRODUCT('Rollen-Prozess-Matrix'!U2,'Kompetenz-Prozess-Matrix'!I6) -> 0
C175: 6.1.2 Lieferung | D175: =PRODUCT('Rollen-Prozess-Matrix'!H3,'Kompetenz-Prozess-Matrix'!I7) -> 0 | E175: =PRODUCT('Rollen-Prozess-Matrix'!I3,'Kompetenz-Prozess-Matrix'!I7) -> 0 | F175: =PRODUCT('Rollen-Prozess-Matrix'!J3,'Kompetenz-Prozess-Matrix'!I7) -> 0 | G175: =PRODUCT('Rollen-Prozess-Matrix'!K3,'Kompetenz-Prozess-Matrix'!I7) -> 0 | H175: =PRODUCT('Rollen-Prozess-Matrix'!L3,'Kompetenz-Prozess-Matrix'!I7) -> 0 | I175: =PRODUCT('Rollen-Prozess-Matrix'!M3,'Kompetenz-Prozess-Matrix'!I7) -> 0 | J175: =PRODUCT('Rollen-Prozess-Matrix'!N3,'Kompetenz-Prozess-Matrix'!I7) -> 0 | K175: =PRODUCT('Rollen-Prozess-Matrix'!O3,'Kompetenz-Prozess-Matrix'!I7) -> 0 | L175: =PRODUCT('Rollen-Prozess-Matrix'!P3,'Kompetenz-Prozess-Matrix'!I7) -> 0 | M175: =PRODUCT('Rollen-Prozess-Matrix'!Q3,'Kompetenz-Prozess-Matrix'!I7) -> 0 | N175: =PRODUCT('Rollen-Prozess-Matrix'!R3,'Kompetenz-Prozess-Matrix'!I7) -> 0 | O175: =PRODUCT('Rollen-Prozess-Matrix'!S3,'Kompetenz-Prozess-Matrix'!I7) -> 0 | P175: =PRODUCT('Rollen-Prozess-Matrix'!T3,'Kompetenz-Prozess-Matrix'!I7) -> 0 | Q175: =PRODUCT('Rollen-Prozess-Matrix'!U3,'Kompetenz-Prozess-Matrix'!I7) -> 0
C176: 6.2.1 Lebenszyklus-Modell-Management | D176: =PRODUCT('Rollen-Prozess-Matrix'!H4,'Kompetenz-Prozess-Matrix'!I8) -> 0 | E176: =PRODUCT('Rollen-Prozess-Matrix'!I4,'Kompetenz-Prozess-Matrix'!I8) -> 0 | F176: =PRODUCT('Rollen-Prozess-Matrix'!J4,'Kompetenz-Prozess-Matrix'!I8) -> 0 | G176: =PRODUCT('Rollen-Prozess-Matrix'!K4,'Kompetenz-Prozess-Matrix'!I8) -> 2 | H176: =PRODUCT('Rollen-Prozess-Matrix'!L4,'Kompetenz-Prozess-Matrix'!I8) -> 6 | I176: =PRODUCT('Rollen-Prozess-Matrix'!M4,'Kompetenz-Prozess-Matrix'!I8) -> 0 | J176: =PRODUCT('Rollen-Prozess-Matrix'!N4,'Kompetenz-Prozess-Matrix'!I8) -> 0 | K176: =PRODUCT('Rollen-Prozess-Matrix'!O4,'Kompetenz-Prozess-Matrix'!I8) -> 0 | L176: =PRODUCT('Rollen-Prozess-Matrix'!P4,'Kompetenz-Prozess-Matrix'!I8) -> 0 | M176: =PRODUCT('Rollen-Prozess-Matrix'!Q4,'Kompetenz-Prozess-Matrix'!I8) -> 0 | N176: =PRODUCT('Rollen-Prozess-Matrix'!R4,'Kompetenz-Prozess-Matrix'!I8) -> 0 | O176: =PRODUCT('Rollen-Prozess-Matrix'!S4,'Kompetenz-Prozess-Matrix'!I8) -> 0 | P176: =PRODUCT('Rollen-Prozess-Matrix'!T4,'Kompetenz-Prozess-Matrix'!I8) -> 0 | Q176: =PRODUCT('Rollen-Prozess-Matrix'!U4,'Kompetenz-Prozess-Matrix'!I8) -> 0
C177: 6.2.2 Verwaltung der Infrastruktur | D177: =PRODUCT('Rollen-Prozess-Matrix'!H5,'Kompetenz-Prozess-Matrix'!I9) -> 0 | E177: =PRODUCT('Rollen-Prozess-Matrix'!I5,'Kompetenz-Prozess-Matrix'!I9) -> 0 | F177: =PRODUCT('Rollen-Prozess-Matrix'!J5,'Kompetenz-Prozess-Matrix'!I9) -> 0 | G177: =PRODUCT('Rollen-Prozess-Matrix'!K5,'Kompetenz-Prozess-Matrix'!I9) -> 2 | H177: =PRODUCT('Rollen-Prozess-Matrix'!L5,'Kompetenz-Prozess-Matrix'!I9) -> 3 | I177: =PRODUCT('Rollen-Prozess-Matrix'!M5,'Kompetenz-Prozess-Matrix'!I9) -> 0 | J177: =PRODUCT('Rollen-Prozess-Matrix'!N5,'Kompetenz-Prozess-Matrix'!I9) -> 0 | K177: =PRODUCT('Rollen-Prozess-Matrix'!O5,'Kompetenz-Prozess-Matrix'!I9) -> 0 | L177: =PRODUCT('Rollen-Prozess-Matrix'!P5,'Kompetenz-Prozess-Matrix'!I9) -> 0 | M177: =PRODUCT('Rollen-Prozess-Matrix'!Q5,'Kompetenz-Prozess-Matrix'!I9) -> 0 | N177: =PRODUCT('Rollen-Prozess-Matrix'!R5,'Kompetenz-Prozess-Matrix'!I9) -> 0 | O177: =PRODUCT('Rollen-Prozess-Matrix'!S5,'Kompetenz-Prozess-Matrix'!I9) -> 0 | P177: =PRODUCT('Rollen-Prozess-Matrix'!T5,'Kompetenz-Prozess-Matrix'!I9) -> 0 | Q177: =PRODUCT('Rollen-Prozess-Matrix'!U5,'Kompetenz-Prozess-Matrix'!I9) -> 0
C178: 6.2.3 Portfoliomanagement | D178: =PRODUCT('Rollen-Prozess-Matrix'!H6,'Kompetenz-Prozess-Matrix'!I10) -> 0 | E178: =PRODUCT('Rollen-Prozess-Matrix'!I6,'Kompetenz-Prozess-Matrix'!I10) -> 0 | F178: =PRODUCT('Rollen-Prozess-Matrix'!J6,'Kompetenz-Prozess-Matrix'!I10) -> 0 | G178: =PRODUCT('Rollen-Prozess-Matrix'!K6,'Kompetenz-Prozess-Matrix'!I10) -> 0 | H178: =PRODUCT('Rollen-Prozess-Matrix'!L6,'Kompetenz-Prozess-Matrix'!I10) -> 0 | I178: =PRODUCT('Rollen-Prozess-Matrix'!M6,'Kompetenz-Prozess-Matrix'!I10) -> 0 | J178: =PRODUCT('Rollen-Prozess-Matrix'!N6,'Kompetenz-Prozess-Matrix'!I10) -> 0 | K178: =PRODUCT('Rollen-Prozess-Matrix'!O6,'Kompetenz-Prozess-Matrix'!I10) -> 0 | L178: =PRODUCT('Rollen-Prozess-Matrix'!P6,'Kompetenz-Prozess-Matrix'!I10) -> 0 | M178: =PRODUCT('Rollen-Prozess-Matrix'!Q6,'Kompetenz-Prozess-Matrix'!I10) -> 0 | N178: =PRODUCT('Rollen-Prozess-Matrix'!R6,'Kompetenz-Prozess-Matrix'!I10) -> 0 | O178: =PRODUCT('Rollen-Prozess-Matrix'!S6,'Kompetenz-Prozess-Matrix'!I10) -> 0 | P178: =PRODUCT('Rollen-Prozess-Matrix'!T6,'Kompetenz-Prozess-Matrix'!I10) -> 0 | Q178: =PRODUCT('Rollen-Prozess-Matrix'!U6,'Kompetenz-Prozess-Matrix'!I10) -> 0
C179: 6.2.4 Personalwesen-Management | D179: =PRODUCT('Rollen-Prozess-Matrix'!H7,'Kompetenz-Prozess-Matrix'!I11) -> 0 | E179: =PRODUCT('Rollen-Prozess-Matrix'!I7,'Kompetenz-Prozess-Matrix'!I11) -> 0 | F179: =PRODUCT('Rollen-Prozess-Matrix'!J7,'Kompetenz-Prozess-Matrix'!I11) -> 0 | G179: =PRODUCT('Rollen-Prozess-Matrix'!K7,'Kompetenz-Prozess-Matrix'!I11) -> 0 | H179: =PRODUCT('Rollen-Prozess-Matrix'!L7,'Kompetenz-Prozess-Matrix'!I11) -> 0 | I179: =PRODUCT('Rollen-Prozess-Matrix'!M7,'Kompetenz-Prozess-Matrix'!I11) -> 0 | J179: =PRODUCT('Rollen-Prozess-Matrix'!N7,'Kompetenz-Prozess-Matrix'!I11) -> 0 | K179: =PRODUCT('Rollen-Prozess-Matrix'!O7,'Kompetenz-Prozess-Matrix'!I11) -> 0 | L179: =PRODUCT('Rollen-Prozess-Matrix'!P7,'Kompetenz-Prozess-Matrix'!I11) -> 0 | M179: =PRODUCT('Rollen-Prozess-Matrix'!Q7,'Kompetenz-Prozess-Matrix'!I11) -> 0 | N179: =PRODUCT('Rollen-Prozess-Matrix'!R7,'Kompetenz-Prozess-Matrix'!I11) -> 0 | O179: =PRODUCT('Rollen-Prozess-Matrix'!S7,'Kompetenz-Prozess-Matrix'!I11) -> 0 | P179: =PRODUCT('Rollen-Prozess-Matrix'!T7,'Kompetenz-Prozess-Matrix'!I11) -> 0 | Q179: =PRODUCT('Rollen-Prozess-Matrix'!U7,'Kompetenz-Prozess-Matrix'!I11) -> 0
C180: 6.2.5 Qualitätsmanagement | D180: =PRODUCT('Rollen-Prozess-Matrix'!H8,'Kompetenz-Prozess-Matrix'!I12) -> 0 | E180: =PRODUCT('Rollen-Prozess-Matrix'!I8,'Kompetenz-Prozess-Matrix'!I12) -> 0 | F180: =PRODUCT('Rollen-Prozess-Matrix'!J8,'Kompetenz-Prozess-Matrix'!I12) -> 0 | G180: =PRODUCT('Rollen-Prozess-Matrix'!K8,'Kompetenz-Prozess-Matrix'!I12) -> 0 | H180: =PRODUCT('Rollen-Prozess-Matrix'!L8,'Kompetenz-Prozess-Matrix'!I12) -> 6 | I180: =PRODUCT('Rollen-Prozess-Matrix'!M8,'Kompetenz-Prozess-Matrix'!I12) -> 0 | J180: =PRODUCT('Rollen-Prozess-Matrix'!N8,'Kompetenz-Prozess-Matrix'!I12) -> 0 | K180: =PRODUCT('Rollen-Prozess-Matrix'!O8,'Kompetenz-Prozess-Matrix'!I12) -> 0 | L180: =PRODUCT('Rollen-Prozess-Matrix'!P8,'Kompetenz-Prozess-Matrix'!I12) -> 2 | M180: =PRODUCT('Rollen-Prozess-Matrix'!Q8,'Kompetenz-Prozess-Matrix'!I12) -> 0 | N180: =PRODUCT('Rollen-Prozess-Matrix'!R8,'Kompetenz-Prozess-Matrix'!I12) -> 0 | O180: =PRODUCT('Rollen-Prozess-Matrix'!S8,'Kompetenz-Prozess-Matrix'!I12) -> 4 | P180: =PRODUCT('Rollen-Prozess-Matrix'!T8,'Kompetenz-Prozess-Matrix'!I12) -> 0 | Q180: =PRODUCT('Rollen-Prozess-Matrix'!U8,'Kompetenz-Prozess-Matrix'!I12) -> 0
C181: 6.2.6 Wissensmanagement | D181: =PRODUCT('Rollen-Prozess-Matrix'!H9,'Kompetenz-Prozess-Matrix'!I13) -> 0 | E181: =PRODUCT('Rollen-Prozess-Matrix'!I9,'Kompetenz-Prozess-Matrix'!I13) -> 0 | F181: =PRODUCT('Rollen-Prozess-Matrix'!J9,'Kompetenz-Prozess-Matrix'!I13) -> 0 | G181: =PRODUCT('Rollen-Prozess-Matrix'!K9,'Kompetenz-Prozess-Matrix'!I13) -> 2 | H181: =PRODUCT('Rollen-Prozess-Matrix'!L9,'Kompetenz-Prozess-Matrix'!I13) -> 3 | I181: =PRODUCT('Rollen-Prozess-Matrix'!M9,'Kompetenz-Prozess-Matrix'!I13) -> 0 | J181: =PRODUCT('Rollen-Prozess-Matrix'!N9,'Kompetenz-Prozess-Matrix'!I13) -> 0 | K181: =PRODUCT('Rollen-Prozess-Matrix'!O9,'Kompetenz-Prozess-Matrix'!I13) -> 0 | L181: =PRODUCT('Rollen-Prozess-Matrix'!P9,'Kompetenz-Prozess-Matrix'!I13) -> 0 | M181: =PRODUCT('Rollen-Prozess-Matrix'!Q9,'Kompetenz-Prozess-Matrix'!I13) -> 0 | N181: =PRODUCT('Rollen-Prozess-Matrix'!R9,'Kompetenz-Prozess-Matrix'!I13) -> 0 | O181: =PRODUCT('Rollen-Prozess-Matrix'!S9,'Kompetenz-Prozess-Matrix'!I13) -> 0 | P181: =PRODUCT('Rollen-Prozess-Matrix'!T9,'Kompetenz-Prozess-Matrix'!I13) -> 0 | Q181: =PRODUCT('Rollen-Prozess-Matrix'!U9,'Kompetenz-Prozess-Matrix'!I13) -> 0
C182: 6.3.1 Projektierung/Projektplanung | D182: =PRODUCT('Rollen-Prozess-Matrix'!H10,'Kompetenz-Prozess-Matrix'!I14) -> 0 | E182: =PRODUCT('Rollen-Prozess-Matrix'!I10,'Kompetenz-Prozess-Matrix'!I14) -> 0 | F182: =PRODUCT('Rollen-Prozess-Matrix'!J10,'Kompetenz-Prozess-Matrix'!I14) -> 2 | G182: =PRODUCT('Rollen-Prozess-Matrix'!K10,'Kompetenz-Prozess-Matrix'!I14) -> 0 | H182: =PRODUCT('Rollen-Prozess-Matrix'!L10,'Kompetenz-Prozess-Matrix'!I14) -> 3 | I182: =PRODUCT('Rollen-Prozess-Matrix'!M10,'Kompetenz-Prozess-Matrix'!I14) -> 0 | J182: =PRODUCT('Rollen-Prozess-Matrix'!N10,'Kompetenz-Prozess-Matrix'!I14) -> 0 | K182: =PRODUCT('Rollen-Prozess-Matrix'!O10,'Kompetenz-Prozess-Matrix'!I14) -> 0 | L182: =PRODUCT('Rollen-Prozess-Matrix'!P10,'Kompetenz-Prozess-Matrix'!I14) -> 0 | M182: =PRODUCT('Rollen-Prozess-Matrix'!Q10,'Kompetenz-Prozess-Matrix'!I14) -> 0 | N182: =PRODUCT('Rollen-Prozess-Matrix'!R10,'Kompetenz-Prozess-Matrix'!I14) -> 0 | O182: =PRODUCT('Rollen-Prozess-Matrix'!S10,'Kompetenz-Prozess-Matrix'!I14) -> 0 | P182: =PRODUCT('Rollen-Prozess-Matrix'!T10,'Kompetenz-Prozess-Matrix'!I14) -> 0 | Q182: =PRODUCT('Rollen-Prozess-Matrix'!U10,'Kompetenz-Prozess-Matrix'!I14) -> 0
C183: 6.3.2 Projektbewertung und Steuerung | D183: =PRODUCT('Rollen-Prozess-Matrix'!H11,'Kompetenz-Prozess-Matrix'!I15) -> 0 | E183: =PRODUCT('Rollen-Prozess-Matrix'!I11,'Kompetenz-Prozess-Matrix'!I15) -> 0 | F183: =PRODUCT('Rollen-Prozess-Matrix'!J11,'Kompetenz-Prozess-Matrix'!I15) -> 2 | G183: =PRODUCT('Rollen-Prozess-Matrix'!K11,'Kompetenz-Prozess-Matrix'!I15) -> 0 | H183: =PRODUCT('Rollen-Prozess-Matrix'!L11,'Kompetenz-Prozess-Matrix'!I15) -> 3 | I183: =PRODUCT('Rollen-Prozess-Matrix'!M11,'Kompetenz-Prozess-Matrix'!I15) -> 0 | J183: =PRODUCT('Rollen-Prozess-Matrix'!N11,'Kompetenz-Prozess-Matrix'!I15) -> 0 | K183: =PRODUCT('Rollen-Prozess-Matrix'!O11,'Kompetenz-Prozess-Matrix'!I15) -> 0 | L183: =PRODUCT('Rollen-Prozess-Matrix'!P11,'Kompetenz-Prozess-Matrix'!I15) -> 0 | M183: =PRODUCT('Rollen-Prozess-Matrix'!Q11,'Kompetenz-Prozess-Matrix'!I15) -> 0 | N183: =PRODUCT('Rollen-Prozess-Matrix'!R11,'Kompetenz-Prozess-Matrix'!I15) -> 0 | O183: =PRODUCT('Rollen-Prozess-Matrix'!S11,'Kompetenz-Prozess-Matrix'!I15) -> 0 | P183: =PRODUCT('Rollen-Prozess-Matrix'!T11,'Kompetenz-Prozess-Matrix'!I15) -> 0 | Q183: =PRODUCT('Rollen-Prozess-Matrix'!U11,'Kompetenz-Prozess-Matrix'!I15) -> 1
C184: 6.3.3 Entscheidungsmanagement | D184: =PRODUCT('Rollen-Prozess-Matrix'!H12,'Kompetenz-Prozess-Matrix'!I16) -> 0 | E184: =PRODUCT('Rollen-Prozess-Matrix'!I12,'Kompetenz-Prozess-Matrix'!I16) -> 0 | F184: =PRODUCT('Rollen-Prozess-Matrix'!J12,'Kompetenz-Prozess-Matrix'!I16) -> 0 | G184: =PRODUCT('Rollen-Prozess-Matrix'!K12,'Kompetenz-Prozess-Matrix'!I16) -> 0 | H184: =PRODUCT('Rollen-Prozess-Matrix'!L12,'Kompetenz-Prozess-Matrix'!I16) -> 0 | I184: =PRODUCT('Rollen-Prozess-Matrix'!M12,'Kompetenz-Prozess-Matrix'!I16) -> 0 | J184: =PRODUCT('Rollen-Prozess-Matrix'!N12,'Kompetenz-Prozess-Matrix'!I16) -> 0 | K184: =PRODUCT('Rollen-Prozess-Matrix'!O12,'Kompetenz-Prozess-Matrix'!I16) -> 0 | L184: =PRODUCT('Rollen-Prozess-Matrix'!P12,'Kompetenz-Prozess-Matrix'!I16) -> 0 | M184: =PRODUCT('Rollen-Prozess-Matrix'!Q12,'Kompetenz-Prozess-Matrix'!I16) -> 0 | N184: =PRODUCT('Rollen-Prozess-Matrix'!R12,'Kompetenz-Prozess-Matrix'!I16) -> 0 | O184: =PRODUCT('Rollen-Prozess-Matrix'!S12,'Kompetenz-Prozess-Matrix'!I16) -> 0 | P184: =PRODUCT('Rollen-Prozess-Matrix'!T12,'Kompetenz-Prozess-Matrix'!I16) -> 0 | Q184: =PRODUCT('Rollen-Prozess-Matrix'!U12,'Kompetenz-Prozess-Matrix'!I16) -> 0
C185: 6.3.4 Risiko-Management | D185: =PRODUCT('Rollen-Prozess-Matrix'!H13,'Kompetenz-Prozess-Matrix'!I17) -> 0 | E185: =PRODUCT('Rollen-Prozess-Matrix'!I13,'Kompetenz-Prozess-Matrix'!I17) -> 0 | F185: =PRODUCT('Rollen-Prozess-Matrix'!J13,'Kompetenz-Prozess-Matrix'!I17) -> 0 | G185: =PRODUCT('Rollen-Prozess-Matrix'!K13,'Kompetenz-Prozess-Matrix'!I17) -> 0 | H185: =PRODUCT('Rollen-Prozess-Matrix'!L13,'Kompetenz-Prozess-Matrix'!I17) -> 0 | I185: =PRODUCT('Rollen-Prozess-Matrix'!M13,'Kompetenz-Prozess-Matrix'!I17) -> 0 | J185: =PRODUCT('Rollen-Prozess-Matrix'!N13,'Kompetenz-Prozess-Matrix'!I17) -> 0 | K185: =PRODUCT('Rollen-Prozess-Matrix'!O13,'Kompetenz-Prozess-Matrix'!I17) -> 0 | L185: =PRODUCT('Rollen-Prozess-Matrix'!P13,'Kompetenz-Prozess-Matrix'!I17) -> 0 | M185: =PRODUCT('Rollen-Prozess-Matrix'!Q13,'Kompetenz-Prozess-Matrix'!I17) -> 0 | N185: =PRODUCT('Rollen-Prozess-Matrix'!R13,'Kompetenz-Prozess-Matrix'!I17) -> 0 | O185: =PRODUCT('Rollen-Prozess-Matrix'!S13,'Kompetenz-Prozess-Matrix'!I17) -> 0 | P185: =PRODUCT('Rollen-Prozess-Matrix'!T13,'Kompetenz-Prozess-Matrix'!I17) -> 0 | Q185: =PRODUCT('Rollen-Prozess-Matrix'!U13,'Kompetenz-Prozess-Matrix'!I17) -> 0
... C206: Qualifizierung | D206: =PRODUCT('Rollen-Prozess-Matrix'!H34,'Kompetenz-Prozess-Matrix'!I38) -> 0 | E206: =PRODUCT('Rollen-Prozess-Matrix'!I34,'Kompetenz-Prozess-Matrix'!I38) -> 0 | F206: =PRODUCT('Rollen-Prozess-Matrix'!J34,'Kompetenz-Prozess-Matrix'!I38) -> 0 | G206: =PRODUCT('Rollen-Prozess-Matrix'!K34,'Kompetenz-Prozess-Matrix'!I38) -> 4 | H206: =PRODUCT('Rollen-Prozess-Matrix'!L34,'Kompetenz-Prozess-Matrix'!I38) -> 0 | I206: =PRODUCT('Rollen-Prozess-Matrix'!M34,'Kompetenz-Prozess-Matrix'!I38) -> 0 | J206: =PRODUCT('Rollen-Prozess-Matrix'!N34,'Kompetenz-Prozess-Matrix'!I38) -> 0 | K206: =PRODUCT('Rollen-Prozess-Matrix'!O34,'Kompetenz-Prozess-Matrix'!I38) -> 0 | L206: =PRODUCT('Rollen-Prozess-Matrix'!P34,'Kompetenz-Prozess-Matrix'!I38) -> 0 | M206: =PRODUCT('Rollen-Prozess-Matrix'!Q34,'Kompetenz-Prozess-Matrix'!I38) -> 0 | N206: =PRODUCT('Rollen-Prozess-Matrix'!R34,'Kompetenz-Prozess-Matrix'!I38) -> 0 | O206: =PRODUCT('Rollen-Prozess-Matrix'!S34,'Kompetenz-Prozess-Matrix'!I38) -> 0 | P206: =PRODUCT('Rollen-Prozess-Matrix'!T34,'Kompetenz-Prozess-Matrix'!I38) -> 0 | Q206: =PRODUCT('Rollen-Prozess-Matrix'!U34,'Kompetenz-Prozess-Matrix'!I38) -> 0
B207: Integration, Verifikation & Validierung | D207: =MAX(D208:D240) -> 2 | E207: =MAX(E208:E240) -> 2 | F207: =MAX(F208:F240) -> 2 | G207: =MAX(G208:G240) -> 4 | H207: =MAX(H208:H240) -> 6 | I207: =MAX(I208:I240) -> 2 | J207: =MAX(J208:J240) -> 2 | K207: =MAX(K208:K240) -> 2 | ... Q207: =MAX(Q208:Q240) -> 1 | S207: 1
C208: 6.1.1 Akquisition | D208: =PRODUCT('Rollen-Prozess-Matrix'!H2,'Kompetenz-Prozess-Matrix'!J6) -> 0 | E208: =PRODUCT('Rollen-Prozess-Matrix'!I2,'Kompetenz-Prozess-Matrix'!J6) -> 0 | F208: =PRODUCT('Rollen-Prozess-Matrix'!J2,'Kompetenz-Prozess-Matrix'!J6) -> 0 | G208: =PRODUCT('Rollen-Prozess-Matrix'!K2,'Kompetenz-Prozess-Matrix'!J6) -> 0 | H208: =PRODUCT('Rollen-Prozess-Matrix'!L2,'Kompetenz-Prozess-Matrix'!J6) -> 0 | I208: =PRODUCT('Rollen-Prozess-Matrix'!M2,'Kompetenz-Prozess-Matrix'!J6) -> 0 | J208: =PRODUCT('Rollen-Prozess-Matrix'!N2,'Kompetenz-Prozess-Matrix'!J6) -> 0 | K208: =PRODUCT('Rollen-Prozess-Matrix'!O2,'Kompetenz-Prozess-Matrix'!J6) -> 0 | L208: =PRODUCT('Rollen-Prozess-Matrix'!P2,'Kompetenz-Prozess-Matrix'!J6) -> 0 | M208: =PRODUCT('Rollen-Prozess-Matrix'!Q2,'Kompetenz-Prozess-Matrix'!J6) -> 0 | N208: =PRODUCT('Rollen-Prozess-Matrix'!R2,'Kompetenz-Prozess-Matrix'!J6) -> 0 | O208: =PRODUCT('Rollen-Prozess-Matrix'!S2,'Kompetenz-Prozess-Matrix'!J6) -> 0 | P208: =PRODUCT('Rollen-Prozess-Matrix'!T2,'Kompetenz-Prozess-Matrix'!J6) -> 0 | Q208: =PRODUCT('Rollen-Prozess-Matrix'!U2,'Kompetenz-Prozess-Matrix'!J6) -> 0
C209: 6.1.2 Lieferung | D209: =PRODUCT('Rollen-Prozess-Matrix'!H3,'Kompetenz-Prozess-Matrix'!J7) -> 0 | E209: =PRODUCT('Rollen-Prozess-Matrix'!I3,'Kompetenz-Prozess-Matrix'!J7) -> 0 | F209: =PRODUCT('Rollen-Prozess-Matrix'!J3,'Kompetenz-Prozess-Matrix'!J7) -> 0 | G209: =PRODUCT('Rollen-Prozess-Matrix'!K3,'Kompetenz-Prozess-Matrix'!J7) -> 0 | H209: =PRODUCT('Rollen-Prozess-Matrix'!L3,'Kompetenz-Prozess-Matrix'!J7) -> 0 | I209: =PRODUCT('Rollen-Prozess-Matrix'!M3,'Kompetenz-Prozess-Matrix'!J7) -> 0 | J209: =PRODUCT('Rollen-Prozess-Matrix'!N3,'Kompetenz-Prozess-Matrix'!J7) -> 0 | K209: =PRODUCT('Rollen-Prozess-Matrix'!O3,'Kompetenz-Prozess-Matrix'!J7) -> 0 | L209: =PRODUCT('Rollen-Prozess-Matrix'!P3,'Kompetenz-Prozess-Matrix'!J7) -> 0 | M209: =PRODUCT('Rollen-Prozess-Matrix'!Q3,'Kompetenz-Prozess-Matrix'!J7) -> 0 | N209: =PRODUCT('Rollen-Prozess-Matrix'!R3,'Kompetenz-Prozess-Matrix'!J7) -> 0 | O209: =PRODUCT('Rollen-Prozess-Matrix'!S3,'Kompetenz-Prozess-Matrix'!J7) -> 0 | P209: =PRODUCT('Rollen-Prozess-Matrix'!T3,'Kompetenz-Prozess-Matrix'!J7) -> 0 | Q209: =PRODUCT('Rollen-Prozess-Matrix'!U3,'Kompetenz-Prozess-Matrix'!J7) -> 0
C210: 6.2.1 Lebenszyklus-Modell-Management | D210: =PRODUCT('Rollen-Prozess-Matrix'!H4,'Kompetenz-Prozess-Matrix'!J8) -> 0 | E210: =PRODUCT('Rollen-Prozess-Matrix'!I4,'Kompetenz-Prozess-Matrix'!J8) -> 0 | F210: =PRODUCT('Rollen-Prozess-Matrix'!J4,'Kompetenz-Prozess-Matrix'!J8) -> 0 | G210: =PRODUCT('Rollen-Prozess-Matrix'!K4,'Kompetenz-Prozess-Matrix'!J8) -> 2 | H210: =PRODUCT('Rollen-Prozess-Matrix'!L4,'Kompetenz-Prozess-Matrix'!J8) -> 6 | I210: =PRODUCT('Rollen-Prozess-Matrix'!M4,'Kompetenz-Prozess-Matrix'!J8) -> 0 | J210: =PRODUCT('Rollen-Prozess-Matrix'!N4,'Kompetenz-Prozess-Matrix'!J8) -> 0 | K210: =PRODUCT('Rollen-Prozess-Matrix'!O4,'Kompetenz-Prozess-Matrix'!J8) -> 0 | L210: =PRODUCT('Rollen-Prozess-Matrix'!P4,'Kompetenz-Prozess-Matrix'!J8) -> 0 | M210: =PRODUCT('Rollen-Prozess-Matrix'!Q4,'Kompetenz-Prozess-Matrix'!J8) -> 0 | N210: =PRODUCT('Rollen-Prozess-Matrix'!R4,'Kompetenz-Prozess-Matrix'!J8) -> 0 | O210: =PRODUCT('Rollen-Prozess-Matrix'!S4,'Kompetenz-Prozess-Matrix'!J8) -> 0 | P210: =PRODUCT('Rollen-Prozess-Matrix'!T4,'Kompetenz-Prozess-Matrix'!J8) -> 0 | Q210: =PRODUCT('Rollen-Prozess-Matrix'!U4,'Kompetenz-Prozess-Matrix'!J8) -> 0
C211: 6.2.2 Verwaltung der Infrastruktur | D211: =PRODUCT('Rollen-Prozess-Matrix'!H5,'Kompetenz-Prozess-Matrix'!J9) -> 0 | E211: =PRODUCT('Rollen-Prozess-Matrix'!I5,'Kompetenz-Prozess-Matrix'!J9) -> 0 | F211: =PRODUCT('Rollen-Prozess-Matrix'!J5,'Kompetenz-Prozess-Matrix'!J9) -> 0 | G211: =PRODUCT('Rollen-Prozess-Matrix'!K5,'Kompetenz-Prozess-Matrix'!J9) -> 0 | H211: =PRODUCT('Rollen-Prozess-Matrix'!L5,'Kompetenz-Prozess-Matrix'!J9) -> 0 | I211: =PRODUCT('Rollen-Prozess-Matrix'!M5,'Kompetenz-Prozess-Matrix'!J9) -> 0 | J211: =PRODUCT('Rollen-Prozess-Matrix'!N5,'Kompetenz-Prozess-Matrix'!J9) -> 0 | K211: =PRODUCT('Rollen-Prozess-Matrix'!O5,'Kompetenz-Prozess-Matrix'!J9) -> 0 | L211: =PRODUCT('Rollen-Prozess-Matrix'!P5,'Kompetenz-Prozess-Matrix'!J9) -> 0 | M211: =PRODUCT('Rollen-Prozess-Matrix'!Q5,'Kompetenz-Prozess-Matrix'!J9) -> 0 | N211: =PRODUCT('Rollen-Prozess-Matrix'!R5,'Kompetenz-Prozess-Matrix'!J9) -> 0 | O211: =PRODUCT('Rollen-Prozess-Matrix'!S5,'Kompetenz-Prozess-Matrix'!J9) -> 0 | P211: =PRODUCT('Rollen-Prozess-Matrix'!T5,'Kompetenz-Prozess-Matrix'!J9) -> 0 | Q211: =PRODUCT('Rollen-Prozess-Matrix'!U5,'Kompetenz-Prozess-Matrix'!J9) -> 0
C212: 6.2.3 Portfoliomanagement | D212: =PRODUCT('Rollen-Prozess-Matrix'!H6,'Kompetenz-Prozess-Matrix'!J10) -> 0 | E212: =PRODUCT('Rollen-Prozess-Matrix'!I6,'Kompetenz-Prozess-Matrix'!J10) -> 0 | F212: =PRODUCT('Rollen-Prozess-Matrix'!J6,'Kompetenz-Prozess-Matrix'!J10) -> 0 | G212: =PRODUCT('Rollen-Prozess-Matrix'!K6,'Kompetenz-Prozess-Matrix'!J10) -> 0 | H212: =PRODUCT('Rollen-Prozess-Matrix'!L6,'Kompetenz-Prozess-Matrix'!J10) -> 0 | I212: =PRODUCT('Rollen-Prozess-Matrix'!M6,'Kompetenz-Prozess-Matrix'!J10) -> 0 | J212: =PRODUCT('Rollen-Prozess-Matrix'!N6,'Kompetenz-Prozess-Matrix'!J10) -> 0 | K212: =PRODUCT('Rollen-Prozess-Matrix'!O6,'Kompetenz-Prozess-Matrix'!J10) -> 0 | L212: =PRODUCT('Rollen-Prozess-Matrix'!P6,'Kompetenz-Prozess-Matrix'!J10) -> 0 | M212: =PRODUCT('Rollen-Prozess-Matrix'!Q6,'Kompetenz-Prozess-Matrix'!J10) -> 0 | N212: =PRODUCT('Rollen-Prozess-Matrix'!R6,'Kompetenz-Prozess-Matrix'!J10) -> 0 | O212: =PRODUCT('Rollen-Prozess-Matrix'!S6,'Kompetenz-Prozess-Matrix'!J10) -> 0 | P212: =PRODUCT('Rollen-Prozess-Matrix'!T6,'Kompetenz-Prozess-Matrix'!J10) -> 0 | Q212: =PRODUCT('Rollen-Prozess-Matrix'!U6,'Kompetenz-Prozess-Matrix'!J10) -> 0
C213: 6.2.4 Personalwesen-Management | D213: =PRODUCT('Rollen-Prozess-Matrix'!H7,'Kompetenz-Prozess-Matrix'!J11) -> 0 | E213: =PRODUCT('Rollen-Prozess-Matrix'!I7,'Kompetenz-Prozess-Matrix'!J11) -> 0 | F213: =PRODUCT('Rollen-Prozess-Matrix'!J7,'Kompetenz-Prozess-Matrix'!J11) -> 0 | G213: =PRODUCT('Rollen-Prozess-Matrix'!K7,'Kompetenz-Prozess-Matrix'!J11) -> 0 | H213: =PRODUCT('Rollen-Prozess-Matrix'!L7,'Kompetenz-Prozess-Matrix'!J11) -> 0 | I213: =PRODUCT('Rollen-Prozess-Matrix'!M7,'Kompetenz-Prozess-Matrix'!J11) -> 0 | J213: =PRODUCT('Rollen-Prozess-Matrix'!N7,'Kompetenz-Prozess-Matrix'!J11) -> 0 | K213: =PRODUCT('Rollen-Prozess-Matrix'!O7,'Kompetenz-Prozess-Matrix'!J11) -> 0 | L213: =PRODUCT('Rollen-Prozess-Matrix'!P7,'Kompetenz-Prozess-Matrix'!J11) -> 0 | M213: =PRODUCT('Rollen-Prozess-Matrix'!Q7,'Kompetenz-Prozess-Matrix'!J11) -> 0 | N213: =PRODUCT('Rollen-Prozess-Matrix'!R7,'Kompetenz-Prozess-Matrix'!J11) -> 0 | O213: =PRODUCT('Rollen-Prozess-Matrix'!S7,'Kompetenz-Prozess-Matrix'!J11) -> 0 | P213: =PRODUCT('Rollen-Prozess-Matrix'!T7,'Kompetenz-Prozess-Matrix'!J11) -> 0 | Q213: =PRODUCT('Rollen-Prozess-Matrix'!U7,'Kompetenz-Prozess-Matrix'!J11) -> 0
C214: 6.2.5 Qualitätsmanagement | D214: =PRODUCT('Rollen-Prozess-Matrix'!H8,'Kompetenz-Prozess-Matrix'!J12) -> 0 | E214: =PRODUCT('Rollen-Prozess-Matrix'!I8,'Kompetenz-Prozess-Matrix'!J12) -> 0 | F214: =PRODUCT('Rollen-Prozess-Matrix'!J8,'Kompetenz-Prozess-Matrix'!J12) -> 0 | G214: =PRODUCT('Rollen-Prozess-Matrix'!K8,'Kompetenz-Prozess-Matrix'!J12) -> 0 | H214: =PRODUCT('Rollen-Prozess-Matrix'!L8,'Kompetenz-Prozess-Matrix'!J12) -> 0 | I214: =PRODUCT('Rollen-Prozess-Matrix'!M8,'Kompetenz-Prozess-Matrix'!J12) -> 0 | J214: =PRODUCT('Rollen-Prozess-Matrix'!N8,'Kompetenz-Prozess-Matrix'!J12) -> 0 | K214: =PRODUCT('Rollen-Prozess-Matrix'!O8,'Kompetenz-Prozess-Matrix'!J12) -> 0 | L214: =PRODUCT('Rollen-Prozess-Matrix'!P8,'Kompetenz-Prozess-Matrix'!J12) -> 0 | M214: =PRODUCT('Rollen-Prozess-Matrix'!Q8,'Kompetenz-Prozess-Matrix'!J12) -> 0 | N214: =PRODUCT('Rollen-Prozess-Matrix'!R8,'Kompetenz-Prozess-Matrix'!J12) -> 0 | O214: =PRODUCT('Rollen-Prozess-Matrix'!S8,'Kompetenz-Prozess-Matrix'!J12) -> 0 | P214: =PRODUCT('Rollen-Prozess-Matrix'!T8,'Kompetenz-Prozess-Matrix'!J12) -> 0 | Q214: =PRODUCT('Rollen-Prozess-Matrix'!U8,'Kompetenz-Prozess-Matrix'!J12) -> 0
C215: 6.2.6 Wissensmanagement | D215: =PRODUCT('Rollen-Prozess-Matrix'!H9,'Kompetenz-Prozess-Matrix'!J13) -> 0 | E215: =PRODUCT('Rollen-Prozess-Matrix'!I9,'Kompetenz-Prozess-Matrix'!J13) -> 0 | F215: =PRODUCT('Rollen-Prozess-Matrix'!J9,'Kompetenz-Prozess-Matrix'!J13) -> 0 | G215: =PRODUCT('Rollen-Prozess-Matrix'!K9,'Kompetenz-Prozess-Matrix'!J13) -> 0 | H215: =PRODUCT('Rollen-Prozess-Matrix'!L9,'Kompetenz-Prozess-Matrix'!J13) -> 0 | I215: =PRODUCT('Rollen-Prozess-Matrix'!M9,'Kompetenz-Prozess-Matrix'!J13) -> 0 | J215: =PRODUCT('Rollen-Prozess-Matrix'!N9,'Kompetenz-Prozess-Matrix'!J13) -> 0 | K215: =PRODUCT('Rollen-Prozess-Matrix'!O9,'Kompetenz-Prozess-Matrix'!J13) -> 0 | L215: =PRODUCT('Rollen-Prozess-Matrix'!P9,'Kompetenz-Prozess-Matrix'!J13) -> 0 | M215: =PRODUCT('Rollen-Prozess-Matrix'!Q9,'Kompetenz-Prozess-Matrix'!J13) -> 0 | N215: =PRODUCT('Rollen-Prozess-Matrix'!R9,'Kompetenz-Prozess-Matrix'!J13) -> 0 | O215: =PRODUCT('Rollen-Prozess-Matrix'!S9,'Kompetenz-Prozess-Matrix'!J13) -> 0 | P215: =PRODUCT('Rollen-Prozess-Matrix'!T9,'Kompetenz-Prozess-Matrix'!J13) -> 0 | Q215: =PRODUCT('Rollen-Prozess-Matrix'!U9,'Kompetenz-Prozess-Matrix'!J13) -> 0
C216: 6.3.1 Projektierung/Projektplanung | D216: =PRODUCT('Rollen-Prozess-Matrix'!H10,'Kompetenz-Prozess-Matrix'!J14) -> 0 | E216: =PRODUCT('Rollen-Prozess-Matrix'!I10,'Kompetenz-Prozess-Matrix'!J14) -> 0 | F216: =PRODUCT('Rollen-Prozess-Matrix'!J10,'Kompetenz-Prozess-Matrix'!J14) -> 2 | G216: =PRODUCT('Rollen-Prozess-Matrix'!K10,'Kompetenz-Prozess-Matrix'!J14) -> 0 | H216: =PRODUCT('Rollen-Prozess-Matrix'!L10,'Kompetenz-Prozess-Matrix'!J14) -> 3 | I216: =PRODUCT('Rollen-Prozess-Matrix'!M10,'Kompetenz-Prozess-Matrix'!J14) -> 0 | J216: =PRODUCT('Rollen-Prozess-Matrix'!N10,'Kompetenz-Prozess-Matrix'!J14) -> 0 | K216: =PRODUCT('Rollen-Prozess-Matrix'!O10,'Kompetenz-Prozess-Matrix'!J14) -> 0 | L216: =PRODUCT('Rollen-Prozess-Matrix'!P10,'Kompetenz-Prozess-Matrix'!J14) -> 0 | M216: =PRODUCT('Rollen-Prozess-Matrix'!Q10,'Kompetenz-Prozess-Matrix'!J14) -> 0 | N216: =PRODUCT('Rollen-Prozess-Matrix'!R10,'Kompetenz-Prozess-Matrix'!J14) -> 0 | O216: =PRODUCT('Rollen-Prozess-Matrix'!S10,'Kompetenz-Prozess-Matrix'!J14) -> 0 | P216: =PRODUCT('Rollen-Prozess-Matrix'!T10,'Kompetenz-Prozess-Matrix'!J14) -> 0 | Q216: =PRODUCT('Rollen-Prozess-Matrix'!U10,'Kompetenz-Prozess-Matrix'!J14) -> 0
C217: 6.3.2 Projektbewertung und Steuerung | D217: =PRODUCT('Rollen-Prozess-Matrix'!H11,'Kompetenz-Prozess-Matrix'!J15) -> 0 | E217: =PRODUCT('Rollen-Prozess-Matrix'!I11,'Kompetenz-Prozess-Matrix'!J15) -> 0 | F217: =PRODUCT('Rollen-Prozess-Matrix'!J11,'Kompetenz-Prozess-Matrix'!J15) -> 2 | G217: =PRODUCT('Rollen-Prozess-Matrix'!K11,'Kompetenz-Prozess-Matrix'!J15) -> 0 | H217: =PRODUCT('Rollen-Prozess-Matrix'!L11,'Kompetenz-Prozess-Matrix'!J15) -> 3 | I217: =PRODUCT('Rollen-Prozess-Matrix'!M11,'Kompetenz-Prozess-Matrix'!J15) -> 0 | J217: =PRODUCT('Rollen-Prozess-Matrix'!N11,'Kompetenz-Prozess-Matrix'!J15) -> 0 | K217: =PRODUCT('Rollen-Prozess-Matrix'!O11,'Kompetenz-Prozess-Matrix'!J15) -> 0 | L217: =PRODUCT('Rollen-Prozess-Matrix'!P11,'Kompetenz-Prozess-Matrix'!J15) -> 0 | M217: =PRODUCT('Rollen-Prozess-Matrix'!Q11,'Kompetenz-Prozess-Matrix'!J15) -> 0 | N217: =PRODUCT('Rollen-Prozess-Matrix'!R11,'Kompetenz-Prozess-Matrix'!J15) -> 0 | O217: =PRODUCT('Rollen-Prozess-Matrix'!S11,'Kompetenz-Prozess-Matrix'!J15) -> 0 | P217: =PRODUCT('Rollen-Prozess-Matrix'!T11,'Kompetenz-Prozess-Matrix'!J15) -> 0 | Q217: =PRODUCT('Rollen-Prozess-Matrix'!U11,'Kompetenz-Prozess-Matrix'!J15) -> 1
C218: 6.3.3 Entscheidungsmanagement | D218: =PRODUCT('Rollen-Prozess-Matrix'!H12,'Kompetenz-Prozess-Matrix'!J16) -> 0 | E218: =PRODUCT('Rollen-Prozess-Matrix'!I12,'Kompetenz-Prozess-Matrix'!J16) -> 0 | F218: =PRODUCT('Rollen-Prozess-Matrix'!J12,'Kompetenz-Prozess-Matrix'!J16) -> 0 | G218: =PRODUCT('Rollen-Prozess-Matrix'!K12,'Kompetenz-Prozess-Matrix'!J16) -> 0 | H218: =PRODUCT('Rollen-Prozess-Matrix'!L12,'Kompetenz-Prozess-Matrix'!J16) -> 0 | I218: =PRODUCT('Rollen-Prozess-Matrix'!M12,'Kompetenz-Prozess-Matrix'!J16) -> 0 | J218: =PRODUCT('Rollen-Prozess-Matrix'!N12,'Kompetenz-Prozess-Matrix'!J16) -> 0 | K218: =PRODUCT('Rollen-Prozess-Matrix'!O12,'Kompetenz-Prozess-Matrix'!J16) -> 0 | L218: =PRODUCT('Rollen-Prozess-Matrix'!P12,'Kompetenz-Prozess-Matrix'!J16) -> 0 | M218: =PRODUCT('Rollen-Prozess-Matrix'!Q12,'Kompetenz-Prozess-Matrix'!J16) -> 0 | N218: =PRODUCT('Rollen-Prozess-Matrix'!R12,'Kompetenz-Prozess-Matrix'!J16) -> 0 | O218: =PRODUCT('Rollen-Prozess-Matrix'!S12,'Kompetenz-Prozess-Matrix'!J16) -> 0 | P218: =PRODUCT('Rollen-Prozess-Matrix'!T12,'Kompetenz-Prozess-Matrix'!J16) -> 0 | Q218: =PRODUCT('Rollen-Prozess-Matrix'!U12,'Kompetenz-Prozess-Matrix'!J16) -> 0
C219: 6.3.4 Risiko-Management | D219: =PRODUCT('Rollen-Prozess-Matrix'!H13,'Kompetenz-Prozess-Matrix'!J17) -> 0 | E219: =PRODUCT('Rollen-Prozess-Matrix'!I13,'Kompetenz-Prozess-Matrix'!J17) -> 0 | F219: =PRODUCT('Rollen-Prozess-Matrix'!J13,'Kompetenz-Prozess-Matrix'!J17) -> 0 | G219: =PRODUCT('Rollen-Prozess-Matrix'!K13,'Kompetenz-Prozess-Matrix'!J17) -> 0 | H219: =PRODUCT('Rollen-Prozess-Matrix'!L13,'Kompetenz-Prozess-Matrix'!J17) -> 0 | I219: =PRODUCT('Rollen-Prozess-Matrix'!M13,'Kompetenz-Prozess-Matrix'!J17) -> 0 | J219: =PRODUCT('Rollen-Prozess-Matrix'!N13,'Kompetenz-Prozess-Matrix'!J17) -> 0 | K219: =PRODUCT('Rollen-Prozess-Matrix'!O13,'Kompetenz-Prozess-Matrix'!J17) -> 0 | L219: =PRODUCT('Rollen-Prozess-Matrix'!P13,'Kompetenz-Prozess-Matrix'!J17) -> 0 | M219: =PRODUCT('Rollen-Prozess-Matrix'!Q13,'Kompetenz-Prozess-Matrix'!J17) -> 0 | N219: =PRODUCT('Rollen-Prozess-Matrix'!R13,'Kompetenz-Prozess-Matrix'!J17) -> 0 | O219: =PRODUCT('Rollen-Prozess-Matrix'!S13,'Kompetenz-Prozess-Matrix'!J17) -> 0 | P219: =PRODUCT('Rollen-Prozess-Matrix'!T13,'Kompetenz-Prozess-Matrix'!J17) -> 0 | Q219: =PRODUCT('Rollen-Prozess-Matrix'!U13,'Kompetenz-Prozess-Matrix'!J17) -> 0
... C240: Qualifizierung | D240: =PRODUCT('Rollen-Prozess-Matrix'!H34,'Kompetenz-Prozess-Matrix'!J38) -> 0 | E240: =PRODUCT('Rollen-Prozess-Matrix'!I34,'Kompetenz-Prozess-Matrix'!J38) -> 0 | F240: =PRODUCT('Rollen-Prozess-Matrix'!J34,'Kompetenz-Prozess-Matrix'!J38) -> 0 | G240: =PRODUCT('Rollen-Prozess-Matrix'!K34,'Kompetenz-Prozess-Matrix'!J38) -> 4 | H240: =PRODUCT('Rollen-Prozess-Matrix'!L34,'Kompetenz-Prozess-Matrix'!J38) -> 0 | I240: =PRODUCT('Rollen-Prozess-Matrix'!M34,'Kompetenz-Prozess-Matrix'!J38) -> 0 | J240: =PRODUCT('Rollen-Prozess-Matrix'!N34,'Kompetenz-Prozess-Matrix'!J38) -> 0 | K240: =PRODUCT('Rollen-Prozess-Matrix'!O34,'Kompetenz-Prozess-Matrix'!J38) -> 0 | L240: =PRODUCT('Rollen-Prozess-Matrix'!P34,'Kompetenz-Prozess-Matrix'!J38) -> 0 | M240: =PRODUCT('Rollen-Prozess-Matrix'!Q34,'Kompetenz-Prozess-Matrix'!J38) -> 0 | N240: =PRODUCT('Rollen-Prozess-Matrix'!R34,'Kompetenz-Prozess-Matrix'!J38) -> 0 | O240: =PRODUCT('Rollen-Prozess-Matrix'!S34,'Kompetenz-Prozess-Matrix'!J38) -> 0 | P240: =PRODUCT('Rollen-Prozess-Matrix'!T34,'Kompetenz-Prozess-Matrix'!J38) -> 0 | Q240: =PRODUCT('Rollen-Prozess-Matrix'!U34,'Kompetenz-Prozess-Matrix'!J38) -> 0
B241: Betrieb, Service und Instandhaltung | D241: =MAX(D242:D274) -> 4 | E241: =MAX(E242:E274) -> 1 | F241: =MAX(F242:F274) -> 2 | G241: =MAX(G242:G274) -> 4 | H241: =MAX(H242:H274) -> 6 | I241: =MAX(I242:I274) -> 2 | J241: =MAX(J242:J274) -> 1 | K241: =MAX(K242:K274) -> 1 | ... Q241: =MAX(Q242:Q274) -> 1 | S241: 1
...

Sheet Lernziele
B2: Definition: Ein Lernziel ist eine Beschreibung des Zustands, in dem sich die Teilnehmer am Ende des Unterrichts/Moduls hinsichtlich Kompetenz, Wissen und Qualifikationen befinden.
B3: Hinweise zur Formulierung von Lernzielen | D3: Beispiel: Am Ende des zweitägigen Kurses wissen die Teilnehmer alle zehn wichtigen Produkteigenschaften und ihre Nutzen. Sie erklären die Eigenschaften und Nutzen in einem simulierten Kundengespräch. Damit sind die Teilnehmer befähigt, das anschließende Verkaufstraining erfolgreich zu absolvieren. | F3: 1 | G3: Kennen | H3: Seminare/Webinar. Serious Gaming | J3: Seminare/Webinar. Serious Gaming
B4: Lernziele sollten SMART-Formuliert sein. | F4: 2 | G4: Verstehen | H4: Blenden Learning | J4: Blenden Learning
B5: Lernziele sollten positiv formuliert sein | F5: 4 | G5: Anwenden | H5: Coaching, Train ing on the Job, Tutorials | J5: Coaching, Train ing on the Job, Tutorials
B6: Mess- und Beobachtbarkeit durch "indem" | F6: 6 | G6: Beherrschen | H6: Erfahrung | J6: Erfahrung
B7: Nutzenformulierung durch "damit" und "um zu"
B8: Lernziele sollten Prozesse, Methoden und Tools berücksichtigen
B9: Abgleich der Kompetenzlevel mit dem Reifegradmodell
D12: Allgemeine Lernziele je Kompetenzlevel | G12: Beherrschen = Die Kompetenz und PMT gestalten können.
B14: Kompetenz | D14: 1 | E14: 2 | F14: 4 | G14: 6 | I14: SE-Qualifizierungsarchetypen
C15: Definition | D15: Kennen | E15: Verstehen | F15: Anwenden | G15: Beherrschen | H15: Inhalte | I15: Gemeinsames Grundverständnis | J15: SE für Fürungskräfte | K15: Orientiweung in Pilotprojekt | L15: Bedarfsgerechte projektorientierte Schulungen | M15: kontinuierliche Begleitung | N15: Train the Trainer
B16: Systemisches Denken | C16: Die Kompetenz fundamentale Konzepte des Systemdenkens im Systems Engineering anzuwenden und die Rolle des eigenen Systems in seinem Gesamtkontext zu verstehen. | D16: Der Teilnehmer kennt die Zusammenhänge seines Systems und die dazugehörigen Systemgrenzen. | E16: Der Teilnehmer versteht die Wechselwirkung der einezelnen Komponenten die das System ausmacht. | F16: Der Teilnehmer ist in der Lage, sein vorliegendes System zu analysieren und daraus kontinuierliche Verbesserungen abzuleiten. | G16: Der Teilnehmer ist in der Lage Systemisches Denken in das Unternehmen zu tragen und andere dafür zu begeistern. | H16: Motivation für SE Begriffsdefinitionen (Index) Werte des SE Vorgehensmodelle SE (V-Modell) SE Standards SE-Männchern | I16: 2 | J16: 4 | K16: 4 | L16: 4 | M16: 2 | N16: 6
B17: Systemmodellierung und -analyse | C17: Die Kompetenz exakte Daten und Informationen mit HIlfe von domäne-übergreifenden Modellen bereitzustellen, um das technische Verständnis und das Treffen von Entscheidungen zu unterstützen. | D17: Die Teilnehmer kennen die Grundlage der Modellierung und deren Benefits. | E17: Die Teilnehmer verstehen wie Modelle ihre Arbeit unterstützen. Sie sind in der Lage einfach Modelle zu lesen. | F17: Die Teilnehmer sind in der Lage eigene Systemmodelle für ihre relevanten Umfang eigenständig zu definieren. Sie Sind befähigt Sie können zwischen domänen-übergreifenden und domänenspezifischen Modellen unterscheiden, | G17: Die Teilnehmer können Vorgaben für (notwendige) Modelle machen und Richtlinine für gute Modellierung schreiben. | H17: Modelltheorie Simulation | I17: 2 | J17: 1 | K17: 4 | L17: 4 | M17: 4 | N17: 6
B18: Berücksichtigung von Systemlebenszyklus-phasen | C18: Die Kompetenz während der Realisierung eines Systems die anderen Lebenszyklen außer der Betriebsphase in den Systemanforderungen, -architekturen und -designs zu berücksichtigen. | D18: Die Teilnehmer kennt die Lebenszyklusphasen seines Systems | E18: Der Teilnehmer verseht warum und wie alle Lebenszyklusphasen im Rahmen der Entwicklung berachtet werden müssen. | F18: Der Teilmnehmer ist in der Lage für die für ihn relevanten Umfänge alle Lebenszyklusphasen zu identifizierne , zu berücksichtuigen und zu bewerten | G18: Der Teilnehmer ist in der Lage Konzepte hinsichtlich der Berücksichtigung von allen Lebenszyklusphasen zu bewerten. | H18: Lebenszyklusphasen Betriebskosten während der Lebenszyklus | I18: 2 | J18: 1 | K18: 4 | L18: 4 | M18: 4 | N18: 6
B19: Kunden-Nutzenorientierung | C19: Die Kompetenz die agilen Werte / den Kundennutzen in den Mittelpunkt der Entwicklung zu stellen. | D19: Die Teilnehmerin ikennt die Grundprinzipien des agilen Denkens. | E19: Die Teilnehmerin versteht wie Agiles Denken in den Arbeitsalltag integiert werden kann | F19: Die Teilnehmerin ist ind er Lage ein System nach agilen Denkweisen zu entwickeln und den Kundennutzen in den mittelpuinkt zu stellen. | G19: Die Teilnehmerin ist in der Lage Agilkes Denken in das Unternehmen zu tragen und andere dafür zu begeistern. | H19: Agiles Manifest | I19: 2 | J19: 2 | K19: 4 | L19: 4 | M19: 2 | N19: 6
B20: Anforderungs-management | C20: Die Kompetenz Bedürfnisse und Erwartungen der Stakeholder zu analysieren und daraus Anforderungen für ein System festzulegen. | D20: Prozess: Die Teilnehmer können Bedarfe, Stakeholderanforderung, Systemanforderung, und System-Element-Anforderungen unterscheiden. Sie kennen die Bedeutung von Traceability und verstehen warum Werkzeuge /Tools) dafür notwendig sind, Methode: Die Teilnehmer kennen den grundlegenden Ablauf, des Anforderungsmanagements. Dazu gehört das indetifizieren, formulieren, ableiten und analysieren von Anforderungen Tool: Die Teilnehmer wissen, das es ein Werkzeug für das Anforderungsmanagement gibt. | E20: Prozess: Die Teilnehmer verstehen wie Anforderungsquellen identifiziert, Anforderungen hergeleitet, geschrieben werden. Sie kennen die unterschiedlichen Arten und Ebenen von Anforderungen Methode: Die Teilnehmer können Anforderung-dokumenten oder -modellen lesen (verknüpfungen etc.). Sie können Kontextbeschreibungen und Schnittstellenspezifikationen lesen und verstehen Tool: Die Teilnehmer können im Anforderungswerkzeug lesen und Anforderungn anschauen und kommentieren/reviewen. | F20: Prozess: Der Teilnehmer kann selbständig Anforderungsquellen identifizieren, Anforderungen daraus ableiten, schreiben, in Anforderungsdokumenten oder -modellen dokumentieren, verknüpfen, ableiten analysieren. Methode: Die Teilnehmer können selbständig Anforderungsdokumente oder -modelle dokumentieren, verknüpfen und analysieren. Sie können Kontextbeschreibungen und Schnittstellenspezifikationen erstellen und analysieren Tool: Die Teilnehmer können in einem Anforderungswerkzeug Anforderungn definieren, verknüpfen und analysieren. | G20: Prozess: Die Teilnehmer sind in der Lage Unzulänglichkeiten im Prozess zu erkennen und Verbesserungsvorschläge zu erarbeiten. Methode: Er ist in der Lage Kontext- und Schnittstellenbeschreibungen zu erstellen und diese mit Stakeholdern zu diskutieren. Tool: Die Teilnehmer können in einem Anforderungswerkzeug erweiterte Funktionen nutzen und neue Templates, Attribute und Features anlegen. | H20: Der Anfordeurngsprozess im Unternehmen Identifikation und Analyse aller Stakeholder Typen von Anforderungen, Bedarfen Einschränkungen aus anderen Lebvenskyluspahsen (V&V, Wartung, etc.) Anforderungen an Anforderungen Traceability von Anforderungen Dokumentation von Anforderungen (Id, text, Tool etc.) Identifikation von Anforderungen Hierarchie und Ableiten von Anforderungen Erhebnung, Definition, Analyse und Bewertung von Anforderungen Entwurf von Szenarien/ Use Cases Beschreibung der Endnutzer Definition der Systemgrenze Identifikation externe Shcnittstellen BalckBox-Betrachtung Verifikationskrierten, Validierungskriterien Einfluss von Einschränkungen auf Systemarchitektur und Design | I20: 2 | J20: 1 | K20: 4 | L20: 4 | M20: 4 | N20: 6
B21: System-Architekturgestaltung | C21: Die Kompetenz die zu einem System zugehörigen Elemente, ihrer Hierarchie, sowie ihrer Schnittstellen oder ihres Verhaltens und der damit verbundenen abgeleiteten Anforderungen zur Entwicklung einer implementierbaren Lösung zu definieren. | D21: Prozess: Die Teilnehmer kennen den Zweck von Architekturmodellen. Sie können Sie grob in den Entwicklungsprozess einordnen. Methode: Die Teilnehmer wissen, das es eine dedizierte Methodik und Modellierungssprache zur Architekturmodellierung gibt. Tool: Die Teilnehmer wissen, das es ein dediziertes Werkzeug für das Viewing und ggf. die Bearbeitung von Architekturmodellen gibt. | E21: Prozess: Die Teilnehmer können nachvollziehen, warum Architekturmodelle als In- und Outputs des Entwicklungsprozesses relevant sind. Methode: Die Teilnehmer können Architekturmodelle lesen und daraus für sie relevante Informationen entnehmen. Tool: Die Teilnehmer können Architekturmodelle in einem Werkzeug anschauen und kommentieren/reviewen. | F21: Prozess: Die Teilnehmer kennen relevante Prozessschritte für Architekturmodelle und wissen woher im Entwicklungsprozess ihre Inputs kommen und welche Outputs sie darin produzieren. Methode: Die Teilnehmer können Architekturmodelle von durchschnittlicher Komplexität erstellen. Sie sind in der Lage für sie relevante Informationen reproduzierbar und im Einklang mit der Methode und Modellierungssprache abbilden zu können. Tool: Die Teilnehmer können Architekturmodelle in einem Werkzeug erstellen und analysieren. | G21: Prozess: Die Teilnehmer sind in der Lage Unzulänglichkeiten im Prozess zu erkennen und Verbesserungsvorschläge zu erarbeiten. Methode: Die Teilnehmer sind in der Lage, Modelle von hoher Komplexität zu erstellen und zu verwalten. Sie können Unzulänglichkeiten in der Methode oder der Modellierungssprache zu erkennen und Verbesserungsvorschläge zu erarbeiten. Tool: Die Teilnehmer können erweiterte Funktionen nutzen und Templates anlegen. | H21: Der Architekturprozess im Unternehmen Entwicklung von funktionalen, logischer Architektur Synthese – Ableitung der physischen Architektur aus der logischen Architektur Zuordnung von Anforderungen zur Architektur inkl. ableiten von Anforderungen weitere Architektur Sichten (Scurity, Safety etc.) Bildern von Alternativen, Auswahl von Alternativen Kriteren für Achitekturen (Vergleichsstudien) Schnittstellen und Interaktionen zwischen Systemelementen, externen Systemen und Umsystemen Beziehung zwischen funktionellen und phys. Elementen | I21: 2 | J21: 1 | K21: 4 | L21: 4 | N21: 6
B22: Integration, Verifikation & Validierung | C22: Die Kompetenz eine Menge von Systemelementen zu einer verifizier- oder validierbaren Einheit zu integrieren bzw. den objektiven Nachweis, das ein System die spezifizierten Anforderungen erfüllt (Validierung), oder seiner beabsichtigten Eigenschaften in der vorgesehenen Einsatzumgebung erreicht (Validierung), durchzuführen. | D22: Der Teilnehmer kennt die Ziele der Verifikation und Validierung sowie kennt verschiedene Arten und Vorgehensweisen der V&V. | E22: Der Teilnehmer kann Testpläne, Testfälle und -ergebnisse lesen und verstehen. | F22: Der Teilnehmer kann Testpläne erstellen. Er ist in der Lage die Tests und Simulationen durchzuführen und zu dokumentieren. | G22: Der Teilnehmer ist in der Lage selbständig und frühzeitig eine Teststrategie sowie einen Erprobungsplan aufzusetzen. Anhand der Anforderungen und Verifikation / Validierungskriterien kann er notwendige Testfälle ableiten. Er ist in der Lage die Tests und Simulationen zu orchestrieren und zu dokumentieren. | H22: Systemintegrationsstrategien Begriffsdefinition IVV Verifikationsprozeduren (System, Element, Gerät) Verifikationsmethoden Traceabilkity zu Anforderungen Validationsprozeduren Korrekturmaßnahmen Validierungsmethoden V&V in den Phasen des Lebenszyklus (insb. früher Phase) Endabnahme des Systems | I22: 2 | J22: 1 | K22: 4 | L22: 4 | N22: 6
B23: Betrieb, Service und Instandhaltung | C23: Die Kompetenz das System in Betrieb zu nehmen, zu betreiben und seine Fähigkeiten/Funktionalitäten über seine Lebensdauer aufrechterhalten wird. | D23: Die Teilnehmer kennen die Zeile der Betriebs-, Service- und Instandhaltungsphase. Sie wissen das diese bereits in der Entwicklung berücksichtigung finden und das es Tätigkeiten in der jewieligen Phase gibt. | E23: Die Teilnehmer verstehen, wie die Phasen Betrieb, Service und Instandhaltung in der Enwtcikllung berücksichtigt werden. Sie sind in der Lage die Tätigkeiten die im Rahmen des Lebenszyklus notwendig sind zu nennen. | F23: Die Teilnehmer verstehen, wie die Phasen Betrieb, Service und Instandhaltung in der Enwtcikllung berücksichtigt werden. Sie sind in der Lage die Phasen abzuwickelon und für zukünftige Projekte verbesserungen zu identifizieren. | G23: Die Teilnehmer sind in der Lage die Organisationsprozesse für den Betrieb, die Wartung und die Instandhaltung zu definieren., | H23: Betriebsstrategien Auswertung Betriebsdaten Anwenderfeedback einholen und bewerten Aufzeichnen von Leistungsdaten, Fehlermeldungen Wartungsstrategien Verbrauchmaterialien Instandhaltungsanalysen Weiter und Wiederverwenden Deaktivieren,Außer Betrieb nehmen Entsorgungsstrategie | I23: 1 | J23: 1 | K23: 4 | L23: 4 | N23: 6
B24: Agile Methodenkompetenz | C24: Die Kompetenz Methoden anzuwenden, welche die Agilenwerte im Projektkontext unterstützen und paralleles arbeiten ermöglichen | D24: Methode: Der Teilnehmer kennt die Agilen Werte und die relevanten agilen Methoden | E24: Methode: Der Teilnehmer versteht die Grundlagen der agilen Arbeitsweisen und versteht wie sich die agilen Methoden in einem Entwicklungsprozess anwenden lassen. | F24: Methode: der Teilnehmer kann in einem agilen Umfeld arbeiten. Er ist in der Lage die dafür notwedigen Methoden anzuwenden. | G24: Der Teilnehmer kann für ein projekt die relevanten agilen Methoden definieren und umsetzen. Der Teilnehmer ist überzeigt davon agile Methoden gewinnbringend eizusetzen und kann andere dazu motivieren. | H24: Scrum SAFe | I24: 2 | J24: 1 | K24: 4 | L24: 4 | N24: 6
B25: Selbstorganisation | C25: Die Kompetenz sich selbst zu organisieren und Aufgaben | D25: Die Teilnehmer kennen die Konzepte der Selbstorganisation. | E25: Die Teilnehmer verstrehen wie die Konzepte der Selbstorganisation ihren Arbeitsalltag beeinflussen | F25: Die Teilnehmer sind in der Lage selbstorganisiert Projekte, Prozesse und Aufgaben abzuarbeiten. | G25: Die Teilnehmer sind in der Lage selbstorganisiert Projekte, Prozesse und Aufgaben abzuarbeiten. | H25: Eigenes Verhalten und persönliche Eigenschaften Zeitmanagement, persönlich. Arbeitsorganisation | I25: 2 | J25: 1 | K25: 4 | L25: 4 | N25: 6
B26: Kommunikation & Zusammenarbeit | C26: Die Kompetenz konstruktiv, effizient und bewusst, auch domaineübergreifend, zu kommunizieren und dabei die Gefühle anderer Menschen zu erfassen und zu berücksichtzigen sowie Beziehungen zu Kollegen und Vorgesetzten nachhaltig und fair zu gestalten. | D26: Teilnehmer kennt die Notwendigkeit dieser Kompetenzen | E26: Teilnehmer erkennt und versteht die Relevanz dieser Kompetenz, insbesondere in Hinblick auf die Anwendung von SE | F26: Teilnehmer ist in der Lage konstruktiv und effizient zu kommunizieren und gleichzeitig empathisch gegenüber seinem Kommunikationspartner zu sein. | G26: Teilnehmer ist darüber hinaus in der Lage, seine Beziehungen zu Kollegen und Vorgesetzen nachhaltig und fair zu gestalten. | H26: Stakeholdergerechte Kommunikation Grundlagen Kommunikationstechnik (4 Seiten,. Selbstbild., Fremdbild,Johari Fenster (Joseph Luft, Harry Ingham)) Zusammenarbeit untersch., Persönlichkeiten Verhandlungstechnik Zwischenmenschliche Kommunikation Sozialkompetenets Verhalten Methoden der Konfliktlösung und Motivation Feedbackregeln,. Aktives zuhören | I26: 1 | J26: 4 | K26: 4 | L26: 4 | N26: 6
B27: Führen | C27: Die Kompetenz geeignete Ziele für ein System bzw. Systemelement auszuwählen, bei Bedarf zu verhandeln und mit einem Team effizient zu erreichen und dabei ggf. Teammitglieder bei der Lösung von Problemen anzuleiten. | D27: Teilnehmer kennt die Notwendigkeit dieser Kompetenzen | E27: Teilnehmer versteht die Relevanz bzgl. der Definition von Zielen für ein System und kann diese für das gesamte Team verständlich definieren | F27: Teilnehmer ist in der Lage, die Ziele mit dem Team zu verhandeln und einen effizienten Weg zu Erreichung dieser zu finden. | G27: Teilnehmer ist in der Lage, Teammitglieder strategisch weiterzuentwickeln, sodass diese sich bei Lösungsfindung weiterentwickeln | H27: Definition Team, Teamführung Phasen einer Team-Entwicklung Charaktere in einem Team (Persönlichkeitsmodell (z.B. Riemann - Thomann), Nähe gegen Entfernung, Dauer gegen Änderungen) Eigenmschaften und Methodne zu teamführung Situationsführungstheorie Kolloboration, Besonderheiten und Eigenschaften eines erfolgreichen Teams Führungsstile: (Hersey und Blanchard) | I27: 1 | J27: 4 | K27: 4 | L27: 4 | N27: 6
B28: Projektmanagement | C28: Die Kompetenz Aktivitäten zu identifizieren, planen, koordinieren und anzupassen um ein zufriedenstellendes System, Produkt oder Service mit angemessener Qualität, Finanzen und Zeit zu liefern. | D28: Prozess: Der Teilnehmer kennt das Themenfeldprojektemanagement und kann seine Tätigkeiten in einen Projektplan einordnen Methode: Der Teilnehmer kennt die gängigen Methoden des Projektmanagementgs. Tool: Die Teilnehmer verstehen warum ein Werkzeug zum Projektmanagement eingesetzt wird. | E28: Prozess : Der Teilnehmer versteht den Projektauftrag und kann das Projektmanagement in dem Kontext des System Engineerings einordnen. Metzhoden: Der Teilnehmer kann eigenständig die für Ihn relevanten (Projekt-)Pläne erstellen und entsprechende Statusberichte erzeugen (hinsichtlich Q-K-T). Tool: Der Teilnehmer ist in der Lage die Planung im jeweiligen Werkzeug durchzuführen. | F28: Prozess & Methode: Der Teilnehmer ist in der Lage einen Projektauftrag zu definieren und Rahmenbedingung festzulegen, komplexe Projektpläne zu erstellen und aussagekräftige Berichte zu erzeugen. In der Kommunikation mit Stakeholdern ist er geübt. Tool: Der Teilnehmer ist in der Lage die Planung im jeweiligen Werkzeug durchzuführen. | G28: Prozess: Der Teilnehmer ist in der Lage Unzulänglichkeiten im Prozess zu identifizieren und Verbesserungsvorschläge zu machen. Er ist in der Lage Berichte, Pläne und Aufträge an alle Stakeholder erfolgreich zu kommunizieren. Tool: Die Teilnehmer können erweiterte Funktionen nutzen und Templates anlegen. | H28: Projektziele und -scope PSP - Projekte planen Arbeispakete Zeitplan, Budgetplan, SE-Plan Ressourcen, Rollen, Verantwortlichkeiten Freigabe Projektstruktur Review Meilensteine Korrekturmaßnahmen und Änderungen Projektabschluss Bestimmung von KPIs Berichtswesen Auswertung | I28: 2 | J28: 2 | K28: 4 | L28: 4 | N28: 6
B29: Entscheidungs-management | C29: Die Kompetenz strukturiert und analytisch ein objektives Set von Alternativen zu identifizieren, zu charakterisieren und zu evaluieren und dabei Risiken und Chancen zu berücksichtigen | D29: Die Teilnehmer kennen die wesentlichen Entscheidungsgremiien und wissen wie Entscheidungen getroffen werden | E29: Die Teilnehmer lernen Entscheidungsunterstützungsmethoden kennen und verstehen welche Entscheidungen Sie selbst treffen können und welche von Gremine etc. getroffen werden. | F29: Die Teilnehmer sind in der Lage für ihre relevanten Umfänge Entscheidungen vorzubereiten oder selbst zu treffen und diese entsprechend zu dokumentieren. Sie können Methoden der Entscheidungsunterstützung (z.B. Nutzwertanalyse) anwenden. | G29: Die Teilnehmer können Entscheidungen bewerten und sind in der Lage übergreifende Entscheidungsgremien zu definieren und etablieren. Sie können gute Guidlines für das treffen von Entscheidungen definieren. | H29: Entscheidungsstrategie Auswertung von Alternativen Aufzeichnung der Entscheidungen Risikoprofile Risikoidentifikation Umgang mit Risiken (Planung, Maßnahmen) Präventive Maßnahmen Technologische Einordnung Projekt | I29: 1 | J29: 4 | K29: 4 | L29: 4 | N29: 6
B30: Informations-management | C30: Die Fähigkeit alle Aspekten von Informationen für bestimmte Stakeholder zu adressieren, um die richtigen Informationen zum passenden Zeitpunkt, in der passenden Sicherheit zu liefern. | D30: Der Teilnehmer kennt die Vorteile eines etablierten Informations- und Wissensmanagements. | E30: Der Teilnehmer kennt die wesentlichen Plattformen für einen Wissen-Transfer und weiß, welche Informationen an wen weitergegeben werden müssen. | F30: Der Teilnehmer kennt die wesentlichen Plattformen für einen Wissen-Transfer. Er ist in der Lage Ablagestrukturen und Dokumentationsrichtlinien für Projekte zu definieren und kann die relevanten Informationen an der entsprechenden Stelle zur Verfügung stellen. | G30: Der Teilnehmer kann einen umfangreichen Informationsmanagementpriozess definieren. | H30: Kommunikationsplanung Informationsverteilung Informationsspeicherung | I30: 1 | J30: 2 | K30: 4 | L30: 4 | N30: 6
B31: Konfigurations-management | C31: Die Fähigkeit Systemfunktionen, Leistung und physikalischen Eigenschaften über den Lebenszyklus stimmig zu gestalten und die Konsistenz sicherzustellen. | D31: Porzess. Der TN versteht die Notwendgkeit des Konfigurationsmanagements Tool: Der TN weiß, in wechen Werkzeugen knfigurationen zu bilden sind. | E31: Prozess: Der Teilnehmer versteht das Vorgehen zur Festlegung von Konfigurationsitems. Er ist fähig die für ihn relevanten Konfigurationsitems zu erkennen und eine integre Konfiguration für seine relevanten Umfänge zu bilden. Tool: Der TN ist in der Lage in dem(n) Werkzeug(en) für seine Umfänge zu bilden | F31: Prozess: Der Teilnehmer kann sinnvolle Konfigurationsitems definieren. Er ist fähig die für ihn relevanten Konfigurationsitems zu erkennen und eine integre Konfiguration für seine relevanten Umfänge zu bilden. Tool: Der TN ist in der Lage in dem(n) Werkzeug(en) Konfigurationsitems zu definieren und für seine Umfänge zu bilden | G31: Prozess: Er ist fähig alle relevanten Konfigurationsitems zu erkennen und eine integre Konfiguration über alle Konfigurationsitems zu bilden. Er ist in der Lage Verbesserungen zu indetifizieren und Lösungsvorschläge herauszuarbeiten. Er kann andere beim bilden von Konfigurationen unterstützen. Tool: Der TN ist in der Lage in dem(n) Werkzeug(en) Konfigurationsitems zu definieren und für alle Umfänge eine Konfiguration zu bilden. | H31: Konfigurationsitem Konfigurationen bilden Konfigurationskontrolle Konfigurationskontrollzyklus (V&V, Auswertung, Freigabe) Konfigurationsdokumentation Baselines Änderungsmanagement | I31: 1 | J31: 1 | K31: 4 | L31: 4 | N31: 6

Sheet gQP - Kundenvertreter
A2: generischer | B2: Qualifizierungsplan | C2: Kundenvertreter ohne Vorwissen
A4: Modul | B4: Kompetenz / Module | C4: Niveau | E4: Übergeordnete Lernziele | F4: Inhaltsempferhlung | G4: Methoden | H4: Übungen | I4: Format Empfehlung
A5: Modul 1 | B5: Systemisches Denken | C5: 2 | D5: =VLOOKUP(C5,Lernziele!F$3:G$6,2,FALSE) -> Verstehen | E5: {=_xlfn.IFS(C5=Lernziele!D$14,VLOOKUP(B5,Lernziele!B$16:G$31,3,FALSE),C5=Lernziele!E$14,VLOOKUP(B5,Lernziele!B$16:G$31,4,FALSE),C5=Lernziele!F$14,VLOOKUP(B5,Lernziele!B$16:G$31,5,FALSE),C5=Lernziele!G$14,VLOOKUP(B5,Lernziele!B$16:G$31,6,FALSE))} -> Der Teilnehmer versteht die Wechselwirkung der einezelnen Komponenten die das System ausmacht. | F5: =VLOOKUP(B5,Lernziele!B16:J31,7,FALSE) -> Motivation für SE Begriffsdefinitionen (Index) Werte des SE Vorgehensmodelle SE (V-Modell) SE Standards SE-Männchern | G5: =VLOOKUP(B5,Lernziele!B16:L31,8,FALSE) -> 2 | I5: {=_xlfn.IFS(C5=Lernziele!F$3,"=Lernziele!H$3",C5=Lernziele!F$4,_xlfn.TEXTJOIN("; ",TRUE,Lernziele!J$3,Lernziele!J$4),C5=Lernziele!F$5,_xlfn.TEXTJOIN("; ",TRUE,Lernziele!J$3,Lernziele!J$4,Lernziele!J$5),C5=Lernziele!F$6,_xlfn.TEXTJOIN("; ",TRUE,Lernziele!J$3,Lernziele!J$4,Lernziele!J$5,Lernziele!J$6))} -> Seminare/Webinar. Serious Gaming; Blenden Learning
A6: Modul 2 | B6: Systemmodellierung und -analyse | C6: =VLOOKUP(B6,'Rollen-Kompetenzen-Matrix'!B$3:Q$546,4,FALSE) -> 4 | D6: =VLOOKUP(C6,Lernziele!F$3:G$6,2,FALSE) -> Anwenden | E6: {=_xlfn.IFS(C6=Lernziele!D$14,VLOOKUP(B6,Lernziele!B$16:G$31,3,FALSE),C6=Lernziele!E$14,VLOOKUP(B6,Lernziele!B$16:G$31,4,FALSE),C6=Lernziele!F$14,VLOOKUP(B6,Lernziele!B$16:G$31,5,FALSE),C6=Lernziele!G$14,VLOOKUP(B6,Lernziele!B$16:G$31,6,FALSE))} -> Die Teilnehmer sind in der Lage eigene Systemmodelle für ihre relevanten Umfang eigenständig zu definieren. Sie Sind befähigt Sie können zwischen domänen-übergreifenden und domänenspezifischen Modellen unterscheiden, | F6: =VLOOKUP(B6,Lernziele!B17:J31,7,FALSE) -> Modelltheorie Simulation | G6: =VLOOKUP(B6,Lernziele!B17:L32,8,FALSE) -> 2 | I6: {=_xlfn.IFS(C6=Lernziele!F$3,"=Lernziele!H$3",C6=Lernziele!F$4,_xlfn.TEXTJOIN("; ",TRUE,Lernziele!J$3,Lernziele!J$4),C6=Lernziele!F$5,_xlfn.TEXTJOIN("; ",TRUE,Lernziele!J$3,Lernziele!J$4,Lernziele!J$5),C6=Lernziele!F$6,_xlfn.TEXTJOIN("; ",TRUE,Lernziele!J$3,Lernziele!J$4,Lernziele!J$5,Lernziele!J$6))} -> Seminare/Webinar. Serious Gaming; Blenden Learning; Coaching, Train ing on the Job, Tutorials
A7: Modul 3 | B7: Berücksichtigung von Systemlebenszyklusphasen | C7: =VLOOKUP(B7,'Rollen-Kompetenzen-Matrix'!B$3:Q$546,4,FALSE) -> 4 | D7: =VLOOKUP(C7,Lernziele!F$3:G$6,2,FALSE) -> Anwenden | E7: {=_xlfn.IFS(C7=Lernziele!D$14,VLOOKUP(B7,Lernziele!B$16:G$31,3,FALSE),C7=Lernziele!E$14,VLOOKUP(B7,Lernziele!B$16:G$31,4,FALSE),C7=Lernziele!F$14,VLOOKUP(B7,Lernziele!B$16:G$31,5,FALSE),C7=Lernziele!G$14,VLOOKUP(B7,Lernziele!B$16:G$31,6,FALSE))} -> #N/A | F7: =VLOOKUP(B7,Lernziele!B18:J32,7,FALSE) -> #N/A | G7: =VLOOKUP(B7,Lernziele!B18:L33,8,FALSE) -> #N/A | I7: {=_xlfn.IFS(C7=Lernziele!F$3,"=Lernziele!H$3",C7=Lernziele!F$4,_xlfn.TEXTJOIN("; ",TRUE,Lernziele!J$3,Lernziele!J$4),C7=Lernziele!F$5,_xlfn.TEXTJOIN("; ",TRUE,Lernziele!J$3,Lernziele!J$4,Lernziele!J$5),C7=Lernziele!F$6,_xlfn.TEXTJOIN("; ",TRUE,Lernziele!J$3,Lernziele!J$4,Lernziele!J$5,Lernziele!J$6))} -> Seminare/Webinar. Serious Gaming; Blenden Learning; Coaching, Train ing on the Job, Tutorials
A8: Modul 4 | B8: Agiles Denken / Kunden-Nutzenorientierung | C8: =VLOOKUP(B8,'Rollen-Kompetenzen-Matrix'!B$3:Q$546,4,FALSE) -> 4 | D8: =VLOOKUP(C8,Lernziele!F$3:G$6,2,FALSE) -> Anwenden | E8: {=_xlfn.IFS(C8=Lernziele!D$14,VLOOKUP(B8,Lernziele!B$16:G$31,3,FALSE),C8=Lernziele!E$14,VLOOKUP(B8,Lernziele!B$16:G$31,4,FALSE),C8=Lernziele!F$14,VLOOKUP(B8,Lernziele!B$16:G$31,5,FALSE),C8=Lernziele!G$14,VLOOKUP(B8,Lernziele!B$16:G$31,6,FALSE))} -> #N/A | F8: =VLOOKUP(B8,Lernziele!B19:J33,7,FALSE) -> #N/A | G8: =VLOOKUP(B8,Lernziele!B19:L34,8,FALSE) -> #N/A | I8: {=_xlfn.IFS(C8=Lernziele!F$3,"=Lernziele!H$3",C8=Lernziele!F$4,_xlfn.TEXTJOIN("; ",TRUE,Lernziele!J$3,Lernziele!J$4),C8=Lernziele!F$5,_xlfn.TEXTJOIN("; ",TRUE,Lernziele!J$3,Lernziele!J$4,Lernziele!J$5),C8=Lernziele!F$6,_xlfn.TEXTJOIN("; ",TRUE,Lernziele!J$3,Lernziele!J$4,Lernziele!J$5,Lernziele!J$6))} -> Seminare/Webinar. Serious Gaming; Blenden Learning; Coaching, Train ing on the Job, Tutorials
A9: Modul 5 | B9: Anforderungsmanagement | C9: =VLOOKUP(B9,'Rollen-Kompetenzen-Matrix'!B$3:Q$546,4,FALSE) -> 4 | D9: =VLOOKUP(C9,Lernziele!F$3:G$6,2,FALSE) -> Anwenden | E9: {=_xlfn.IFS(C9=Lernziele!D$14,VLOOKUP(B9,Lernziele!B$16:G$31,3,FALSE),C9=Lernziele!E$14,VLOOKUP(B9,Lernziele!B$16:G$31,4,FALSE),C9=Lernziele!F$14,VLOOKUP(B9,Lernziele!B$16:G$31,5,FALSE),C9=Lernziele!G$14,VLOOKUP(B9,Lernziele!B$16:G$31,6,FALSE))} -> #N/A | F9: =VLOOKUP(B9,Lernziele!B20:J34,7,FALSE) -> #N/A | G9: =VLOOKUP(B9,Lernziele!B20:L35,8,FALSE) -> #N/A | I9: {=_xlfn.IFS(C9=Lernziele!F$3,"=Lernziele!H$3",C9=Lernziele!F$4,_xlfn.TEXTJOIN("; ",TRUE,Lernziele!J$3,Lernziele!J$4),C9=Lernziele!F$5,_xlfn.TEXTJOIN("; ",TRUE,Lernziele!J$3,Lernziele!J$4,Lernziele!J$5),C9=Lernziele!F$6,_xlfn.TEXTJOIN("; ",TRUE,Lernziele!J$3,Lernziele!J$4,Lernziele!J$5,Lernziele!J$6))} -> Seminare/Webinar. Serious Gaming; Blenden Learning; Coaching, Train ing on the Job, Tutorials
A10: Modul 6 | B10: System-Architekturgestaltung | C10: =VLOOKUP(B10,'Rollen-Kompetenzen-Matrix'!B$3:Q$546,4,FALSE) -> 2 | D10: =VLOOKUP(C10,Lernziele!F$3:G$6,2,FALSE) -> Verstehen | E10: {=_xlfn.IFS(C10=Lernziele!D$14,VLOOKUP(B10,Lernziele!B$16:G$31,3,FALSE),C10=Lernziele!E$14,VLOOKUP(B10,Lernziele!B$16:G$31,4,FALSE),C10=Lernziele!F$14,VLOOKUP(B10,Lernziele!B$16:G$31,5,FALSE),C10=Lernziele!G$14,VLOOKUP(B10,Lernziele!B$16:G$31,6,FALSE))} -> Prozess: Die Teilnehmer können nachvollziehen, warum Architekturmodelle als In- und Outputs des Entwicklungsprozesses relevant sind. Methode: Die Teilnehmer können Architekturmodelle lesen und daraus für sie relevante Informationen entnehmen. Tool: Die Teilnehmer können Architekturmodelle in einem Werkzeug anschauen und kommentieren/reviewen. | F10: =VLOOKUP(B10,Lernziele!B21:J35,7,FALSE) -> Der Architekturprozess im Unternehmen Entwicklung von funktionalen, logischer Architektur Synthese – Ableitung der physischen Architektur aus der logischen Architektur Zuordnung von Anforderungen zur Architektur inkl. ableiten von Anforderungen weitere Architektur Sichten (Scurity, Safety etc.) Bildern von Alternativen, Auswahl von Alternativen Kriteren für Achitekturen (Vergleichsstudien) Schnittstellen und Interaktionen zwischen Systemelementen, externen Systemen und Umsystemen Beziehung zwischen funktionellen und phys. Elementen | G10: =VLOOKUP(B10,Lernziele!B21:L36,8,FALSE) -> 2 | I10: {=_xlfn.IFS(C10=Lernziele!F$3,"=Lernziele!H$3",C10=Lernziele!F$4,_xlfn.TEXTJOIN("; ",TRUE,Lernziele!J$3,Lernziele!J$4),C10=Lernziele!F$5,_xlfn.TEXTJOIN("; ",TRUE,Lernziele!J$3,Lernziele!J$4,Lernziele!J$5),C10=Lernziele!F$6,_xlfn.TEXTJOIN("; ",TRUE,Lernziele!J$3,Lernziele!J$4,Lernziele!J$5,Lernziele!J$6))} -> Seminare/Webinar. Serious Gaming; Blenden Learning
A11: Modul 7 | B11: Integration, Verifikation & Validierung | C11: =VLOOKUP(B11,'Rollen-Kompetenzen-Matrix'!B$3:Q$546,4,FALSE) -> 2 | D11: =VLOOKUP(C11,Lernziele!F$3:G$6,2,FALSE) -> Verstehen | E11: {=_xlfn.IFS(C11=Lernziele!D$14,VLOOKUP(B11,Lernziele!B$16:G$31,3,FALSE),C11=Lernziele!E$14,VLOOKUP(B11,Lernziele!B$16:G$31,4,FALSE),C11=Lernziele!F$14,VLOOKUP(B11,Lernziele!B$16:G$31,5,FALSE),C11=Lernziele!G$14,VLOOKUP(B11,Lernziele!B$16:G$31,6,FALSE))} -> Der Teilnehmer kann Testpläne, Testfälle und -ergebnisse lesen und verstehen. | F11: =VLOOKUP(B11,Lernziele!B22:J36,7,FALSE) -> Systemintegrationsstrategien Begriffsdefinition IVV Verifikationsprozeduren (System, Element, Gerät) Verifikationsmethoden Traceabilkity zu Anforderungen Validationsprozeduren Korrekturmaßnahmen Validierungsmethoden V&V in den Phasen des Lebenszyklus (insb. früher Phase) Endabnahme des Systems | I11: {=_xlfn.IFS(C11=Lernziele!F$3,"=Lernziele!H$3",C11=Lernziele!F$4,_xlfn.TEXTJOIN("; ",TRUE,Lernziele!J$3,Lernziele!J$4),C11=Lernziele!F$5,_xlfn.TEXTJOIN("; ",TRUE,Lernziele!J$3,Lernziele!J$4,Lernziele!J$5),C11=Lernziele!F$6,_xlfn.TEXTJOIN("; ",TRUE,Lernziele!J$3,Lernziele!J$4,Lernziele!J$5,Lernziele!J$6))} -> Seminare/Webinar. Serious Gaming; Blenden Learning
A12: Modul 8 | B12: Betrieb, Service und Instandhaltung | C12: =VLOOKUP(B12,'Rollen-Kompetenzen-Matrix'!B$3:Q$546,4,FALSE) -> 1 | D12: =VLOOKUP(C12,Lernziele!F$3:G$6,2,FALSE) -> Kennen | E12: {=_xlfn.IFS(C12=Lernziele!D$14,VLOOKUP(B12,Lernziele!B$16:G$31,3,FALSE),C12=Lernziele!E$14,VLOOKUP(B12,Lernziele!B$16:G$31,4,FALSE),C12=Lernziele!F$14,VLOOKUP(B12,Lernziele!B$16:G$31,5,FALSE),C12=Lernziele!G$14,VLOOKUP(B12,Lernziele!B$16:G$31,6,FALSE))} -> Die Teilnehmer kennen die Zeile der Betriebs-, Service- und Instandhaltungsphase. Sie wissen das diese bereits in der Entwicklung berücksichtigung finden und das es Tätigkeiten in der jewieligen Phase gibt. | F12: =VLOOKUP(B12,Lernziele!B23:J37,7,FALSE) -> Betriebsstrategien Auswertung Betriebsdaten Anwenderfeedback einholen und bewerten Aufzeichnen von Leistungsdaten, Fehlermeldungen Wartungsstrategien Verbrauchmaterialien Instandhaltungsanalysen Weiter und Wiederverwenden Deaktivieren,Außer Betrieb nehmen Entsorgungsstrategie | I12: {=_xlfn.IFS(C12=Lernziele!F$3,"=Lernziele!H$3",C12=Lernziele!F$4,_xlfn.TEXTJOIN("; ",TRUE,Lernziele!J$3,Lernziele!J$4),C12=Lernziele!F$5,_xlfn.TEXTJOIN("; ",TRUE,Lernziele!J$3,Lernziele!J$4,Lernziele!J$5),C12=Lernziele!F$6,_xlfn.TEXTJOIN("; ",TRUE,Lernziele!J$3,Lernziele!J$4,Lernziele!J$5,Lernziele!J$6))} -> =Lernziele!H$3
A13: Modul 9 | B13: Agile Methodenkompetenz | C13: =VLOOKUP(B13,'Rollen-Kompetenzen-Matrix'!B$3:Q$546,4,FALSE) -> 4 | D13: =VLOOKUP(C13,Lernziele!F$3:G$6,2,FALSE) -> Anwenden | E13: {=_xlfn.IFS(C13=Lernziele!D$14,VLOOKUP(B13,Lernziele!B$16:G$31,3,FALSE),C13=Lernziele!E$14,VLOOKUP(B13,Lernziele!B$16:G$31,4,FALSE),C13=Lernziele!F$14,VLOOKUP(B13,Lernziele!B$16:G$31,5,FALSE),C13=Lernziele!G$14,VLOOKUP(B13,Lernziele!B$16:G$31,6,FALSE))} -> Methode: der Teilnehmer kann in einem agilen Umfeld arbeiten. Er ist in der Lage die dafür notwedigen Methoden anzuwenden. | F13: =VLOOKUP(B13,Lernziele!B24:J38,7,FALSE) -> Scrum SAFe | I13: {=_xlfn.IFS(C13=Lernziele!F$3,"=Lernziele!H$3",C13=Lernziele!F$4,_xlfn.TEXTJOIN("; ",TRUE,Lernziele!J$3,Lernziele!J$4),C13=Lernziele!F$5,_xlfn.TEXTJOIN("; ",TRUE,Lernziele!J$3,Lernziele!J$4,Lernziele!J$5),C13=Lernziele!F$6,_xlfn.TEXTJOIN("; ",TRUE,Lernziele!J$3,Lernziele!J$4,Lernziele!J$5,Lernziele!J$6))} -> Seminare/Webinar. Serious Gaming; Blenden Learning; Coaching, Train ing on the Job, Tutorials
A14: Modul 10 | B14: Selbstorganisation | C14: =VLOOKUP(B14,'Rollen-Kompetenzen-Matrix'!B$3:Q$546,4,FALSE) -> 4 | D14: =VLOOKUP(C14,Lernziele!F$3:G$6,2,FALSE) -> Anwenden | E14: {=_xlfn.IFS(C14=Lernziele!D$14,VLOOKUP(B14,Lernziele!B$16:G$31,3,FALSE),C14=Lernziele!E$14,VLOOKUP(B14,Lernziele!B$16:G$31,4,FALSE),C14=Lernziele!F$14,VLOOKUP(B14,Lernziele!B$16:G$31,5,FALSE),C14=Lernziele!G$14,VLOOKUP(B14,Lernziele!B$16:G$31,6,FALSE))} -> Die Teilnehmer sind in der Lage selbstorganisiert Projekte, Prozesse und Aufgaben abzuarbeiten. | F14: =VLOOKUP(B14,Lernziele!B25:J39,7,FALSE) -> Eigenes Verhalten und persönliche Eigenschaften Zeitmanagement, persönlich. Arbeitsorganisation | I14: {=_xlfn.IFS(C14=Lernziele!F$3,"=Lernziele!H$3",C14=Lernziele!F$4,_xlfn.TEXTJOIN("; ",TRUE,Lernziele!J$3,Lernziele!J$4),C14=Lernziele!F$5,_xlfn.TEXTJOIN("; ",TRUE,Lernziele!J$3,Lernziele!J$4,Lernziele!J$5),C14=Lernziele!F$6,_xlfn.TEXTJOIN("; ",TRUE,Lernziele!J$3,Lernziele!J$4,Lernziele!J$5,Lernziele!J$6))} -> Seminare/Webinar. Serious Gaming; Blenden Learning; Coaching, Train ing on the Job, Tutorials
A15: Modul 11 | B15: Kommunikation & Zusammenarbeit | C15: =VLOOKUP(B15,'Rollen-Kompetenzen-Matrix'!B$3:Q$546,4,FALSE) -> 4 | D15: =VLOOKUP(C15,Lernziele!F$3:G$6,2,FALSE) -> Anwenden | E15: {=_xlfn.IFS(C15=Lernziele!D$14,VLOOKUP(B15,Lernziele!B$16:G$31,3,FALSE),C15=Lernziele!E$14,VLOOKUP(B15,Lernziele!B$16:G$31,4,FALSE),C15=Lernziele!F$14,VLOOKUP(B15,Lernziele!B$16:G$31,5,FALSE),C15=Lernziele!G$14,VLOOKUP(B15,Lernziele!B$16:G$31,6,FALSE))} -> Teilnehmer ist in der Lage konstruktiv und effizient zu kommunizieren und gleichzeitig empathisch gegenüber seinem Kommunikationspartner zu sein. | F15: =VLOOKUP(B15,Lernziele!B26:J40,7,FALSE) -> Stakeholdergerechte Kommunikation Grundlagen Kommunikationstechnik (4 Seiten,. Selbstbild., Fremdbild,Johari Fenster (Joseph Luft, Harry Ingham)) Zusammenarbeit untersch., Persönlichkeiten Verhandlungstechnik Zwischenmenschliche Kommunikation Sozialkompetenets Verhalten Methoden der Konfliktlösung und Motivation Feedbackregeln,. Aktives zuhören | I15: {=_xlfn.IFS(C15=Lernziele!F$3,"=Lernziele!H$3",C15=Lernziele!F$4,_xlfn.TEXTJOIN("; ",TRUE,Lernziele!J$3,Lernziele!J$4),C15=Lernziele!F$5,_xlfn.TEXTJOIN("; ",TRUE,Lernziele!J$3,Lernziele!J$4,Lernziele!J$5),C15=Lernziele!F$6,_xlfn.TEXTJOIN("; ",TRUE,Lernziele!J$3,Lernziele!J$4,Lernziele!J$5,Lernziele!J$6))} -> Seminare/Webinar. Serious Gaming; Blenden Learning; Coaching, Train ing on the Job, Tutorials
A16: Modul 12 | B16: Führen | C16: =VLOOKUP(B16,'Rollen-Kompetenzen-Matrix'!B$3:Q$546,4,FALSE) -> 2 | D16: =VLOOKUP(C16,Lernziele!F$3:G$6,2,FALSE) -> Verstehen | E16: {=_xlfn.IFS(C16=Lernziele!D$14,VLOOKUP(B16,Lernziele!B$16:G$31,3,FALSE),C16=Lernziele!E$14,VLOOKUP(B16,Lernziele!B$16:G$31,4,FALSE),C16=Lernziele!F$14,VLOOKUP(B16,Lernziele!B$16:G$31,5,FALSE),C16=Lernziele!G$14,VLOOKUP(B16,Lernziele!B$16:G$31,6,FALSE))} -> Teilnehmer versteht die Relevanz bzgl. der Definition von Zielen für ein System und kann diese für das gesamte Team verständlich definieren | F16: =VLOOKUP(B16,Lernziele!B27:J41,7,FALSE) -> Definition Team, Teamführung Phasen einer Team-Entwicklung Charaktere in einem Team (Persönlichkeitsmodell (z.B. Riemann - Thomann), Nähe gegen Entfernung, Dauer gegen Änderungen) Eigenmschaften und Methodne zu teamführung Situationsführungstheorie Kolloboration, Besonderheiten und Eigenschaften eines erfolgreichen Teams Führungsstile: (Hersey und Blanchard) | I16: {=_xlfn.IFS(C16=Lernziele!F$3,"=Lernziele!H$3",C16=Lernziele!F$4,_xlfn.TEXTJOIN("; ",TRUE,Lernziele!J$3,Lernziele!J$4),C16=Lernziele!F$5,_xlfn.TEXTJOIN("; ",TRUE,Lernziele!J$3,Lernziele!J$4,Lernziele!J$5),C16=Lernziele!F$6,_xlfn.TEXTJOIN("; ",TRUE,Lernziele!J$3,Lernziele!J$4,Lernziele!J$5,Lernziele!J$6))} -> Seminare/Webinar. Serious Gaming; Blenden Learning
A17: Modul 13 | B17: Projektmanagement | C17: =VLOOKUP(B17,'Rollen-Kompetenzen-Matrix'!B$3:Q$546,4,FALSE) -> 2 | D17: =VLOOKUP(C17,Lernziele!F$3:G$6,2,FALSE) -> Verstehen | E17: {=_xlfn.IFS(C17=Lernziele!D$14,VLOOKUP(B17,Lernziele!B$16:G$31,3,FALSE),C17=Lernziele!E$14,VLOOKUP(B17,Lernziele!B$16:G$31,4,FALSE),C17=Lernziele!F$14,VLOOKUP(B17,Lernziele!B$16:G$31,5,FALSE),C17=Lernziele!G$14,VLOOKUP(B17,Lernziele!B$16:G$31,6,FALSE))} -> Prozess : Der Teilnehmer versteht den Projektauftrag und kann das Projektmanagement in dem Kontext des System Engineerings einordnen. Metzhoden: Der Teilnehmer kann eigenständig die für Ihn relevanten (Projekt-)Pläne erstellen und entsprechende Statusberichte erzeugen (hinsichtlich Q-K-T). Tool: Der Teilnehmer ist in der Lage die Planung im jeweiligen Werkzeug durchzuführen. | F17: =VLOOKUP(B17,Lernziele!B28:J42,7,FALSE) -> Projektziele und -scope PSP - Projekte planen Arbeispakete Zeitplan, Budgetplan, SE-Plan Ressourcen, Rollen, Verantwortlichkeiten Freigabe Projektstruktur Review Meilensteine Korrekturmaßnahmen und Änderungen Projektabschluss Bestimmung von KPIs Berichtswesen Auswertung | I17: {=_xlfn.IFS(C17=Lernziele!F$3,"=Lernziele!H$3",C17=Lernziele!F$4,_xlfn.TEXTJOIN("; ",TRUE,Lernziele!J$3,Lernziele!J$4),C17=Lernziele!F$5,_xlfn.TEXTJOIN("; ",TRUE,Lernziele!J$3,Lernziele!J$4,Lernziele!J$5),C17=Lernziele!F$6,_xlfn.TEXTJOIN("; ",TRUE,Lernziele!J$3,Lernziele!J$4,Lernziele!J$5,Lernziele!J$6))} -> Seminare/Webinar. Serious Gaming; Blenden Learning
A18: Modul 14 | B18: Entscheidungsmanagement | C18: =VLOOKUP(B18,'Rollen-Kompetenzen-Matrix'!B$3:Q$546,4,FALSE) -> 4 | D18: =VLOOKUP(C18,Lernziele!F$3:G$6,2,FALSE) -> Anwenden | E18: {=_xlfn.IFS(C18=Lernziele!D$14,VLOOKUP(B18,Lernziele!B$16:G$31,3,FALSE),C18=Lernziele!E$14,VLOOKUP(B18,Lernziele!B$16:G$31,4,FALSE),C18=Lernziele!F$14,VLOOKUP(B18,Lernziele!B$16:G$31,5,FALSE),C18=Lernziele!G$14,VLOOKUP(B18,Lernziele!B$16:G$31,6,FALSE))} -> #N/A | F18: =VLOOKUP(B18,Lernziele!B29:J43,7,FALSE) -> #N/A | I18: {=_xlfn.IFS(C18=Lernziele!F$3,"=Lernziele!H$3",C18=Lernziele!F$4,_xlfn.TEXTJOIN("; ",TRUE,Lernziele!J$3,Lernziele!J$4),C18=Lernziele!F$5,_xlfn.TEXTJOIN("; ",TRUE,Lernziele!J$3,Lernziele!J$4,Lernziele!J$5),C18=Lernziele!F$6,_xlfn.TEXTJOIN("; ",TRUE,Lernziele!J$3,Lernziele!J$4,Lernziele!J$5,Lernziele!J$6))} -> Seminare/Webinar. Serious Gaming; Blenden Learning; Coaching, Train ing on the Job, Tutorials
A19: Modul 15 | B19: Informationsmanagement | C19: =VLOOKUP(B19,'Rollen-Kompetenzen-Matrix'!B$3:Q$546,4,FALSE) -> 2 | D19: =VLOOKUP(C19,Lernziele!F$3:G$6,2,FALSE) -> Verstehen | E19: {=_xlfn.IFS(C19=Lernziele!D$14,VLOOKUP(B19,Lernziele!B$16:G$31,3,FALSE),C19=Lernziele!E$14,VLOOKUP(B19,Lernziele!B$16:G$31,4,FALSE),C19=Lernziele!F$14,VLOOKUP(B19,Lernziele!B$16:G$31,5,FALSE),C19=Lernziele!G$14,VLOOKUP(B19,Lernziele!B$16:G$31,6,FALSE))} -> #N/A | F19: =VLOOKUP(B19,Lernziele!B30:J44,7,FALSE) -> #N/A | I19: {=_xlfn.IFS(C19=Lernziele!F$3,"=Lernziele!H$3",C19=Lernziele!F$4,_xlfn.TEXTJOIN("; ",TRUE,Lernziele!J$3,Lernziele!J$4),C19=Lernziele!F$5,_xlfn.TEXTJOIN("; ",TRUE,Lernziele!J$3,Lernziele!J$4,Lernziele!J$5),C19=Lernziele!F$6,_xlfn.TEXTJOIN("; ",TRUE,Lernziele!J$3,Lernziele!J$4,Lernziele!J$5,Lernziele!J$6))} -> Seminare/Webinar. Serious Gaming; Blenden Learning
A20: Modul 16 | B20: Konfigurationsmanagement | C20: =VLOOKUP(B20,'Rollen-Kompetenzen-Matrix'!B$3:Q$546,4,FALSE) -> 2 | D20: =VLOOKUP(C20,Lernziele!F$3:G$6,2,FALSE) -> Verstehen | E20: {=_xlfn.IFS(C20=Lernziele!D$14,VLOOKUP(B20,Lernziele!B$16:G$31,3,FALSE),C20=Lernziele!E$14,VLOOKUP(B20,Lernziele!B$16:G$31,4,FALSE),C20=Lernziele!F$14,VLOOKUP(B20,Lernziele!B$16:G$31,5,FALSE),C20=Lernziele!G$14,VLOOKUP(B20,Lernziele!B$16:G$31,6,FALSE))} -> #N/A | F20: =VLOOKUP(B20,Lernziele!B31:J45,7,FALSE) -> #N/A | I20: {=_xlfn.IFS(C20=Lernziele!F$3,"=Lernziele!H$3",C20=Lernziele!F$4,_xlfn.TEXTJOIN("; ",TRUE,Lernziele!J$3,Lernziele!J$4),C20=Lernziele!F$5,_xlfn.TEXTJOIN("; ",TRUE,Lernziele!J$3,Lernziele!J$4,Lernziele!J$5),C20=Lernziele!F$6,_xlfn.TEXTJOIN("; ",TRUE,Lernziele!J$3,Lernziele!J$4,Lernziele!J$5,Lernziele!J$6))} -> Seminare/Webinar. Serious Gaming; Blenden Learning
B44: Entscheidungsmanagement
B46: Informationsmanagement
B48: Konfigurationsmanagement

Sheet Tabelle1
B3: Kompetenz | C3: Definition | D3: 1 | E3: 2 | F3: 4 | G3: 6
D4: Kennen | E4: Verstehen | F4: Anwenden | G4: Beherrschen
B5: Systemisches Denken | C5: Die Kompetenz fundamentale Konzepte des Systemdenkens im Systems Engineering anzuwenden und die Rolle des eigenen Systems in seinem Gesamtkontext zu verstehen. | D5: Der Teilnehmer kennt die Zusammenhänge seines Systems und die dazugehörigen Systemgrenzen. | E5: Der Teilnehmer versteht die Wechselwirkung der einezelnen Komponenten die das System ausmacht. | F5: Der Teilnehmer ist in der Lage, sein vorliegendes System zu analysieren und daraus kontinuierliche Verbesserungen abzuleiten. | G5: Der Teilnehmer ist in der Lage Systemisches Denken in das Unternehmen zu tragen und andere dafür zu begeistern.
B6: Systemmodellierung und -analyse | C6: Die Kompetenz exakte Daten und Informationen mit HIlfe von domäne-übergreifenden Modellen bereitzustellen, um das technische Verständnis und das Treffen von Entscheidungen zu unterstützen. | D6: Die Teilnehmer kennen die Grundlage der Modellierung und deren Benefits. | E6: Die Teilnehmer verstehen wie Modelle ihre Arbeit unterstützen. Sie sind in der Lage einfach Modelle zu lesen. | F6: Die Teilnehmer sind in der Lage eigene Systemmodelle für ihre relevanten Umfang eigenständig zu definieren. Sie Sind befähigt Sie können zwischen domänen-übergreifenden und domänenspezifischen Modellen unterscheiden, | G6: Die Teilnehmer können Vorgaben für (notwendige) Modelle machen und Richtlinine für gute Modellierung schreiben.
B7: Berücksichtigung von Systemlebenszyklusphasen | C7: Die Kompetenz während der Realisierung eines Systems die anderen Lebenszyklen außer der Betriebsphase in den Systemanforderungen, -architekturen und -designs zu berücksichtigen. | D7: Die Teilnehmer kennt die Lebenszyklusphasen seines Systems | E7: Der Teilnehmer verseht warum und wie alle Lebenszyklusphasen im Rahmen der Entwicklung berachtet werden müssen. | F7: Der Teilmnehmer ist in der Lage für die für ihn relevanten Umfänge alle Lebenszyklusphasen zu identifizierne , zu berücksichtuigen und zu bewerten | G7: Der Teilnehmer ist in der Lage Konzepte hinsichtlich der Berücksichtigung von allen Lebenszyklusphasen zu bewerten.
B8: Agiles Denken / Kunden-Nutzenorientierung | C8: Die Kompetenz die agilen Werte / den Kundennutzen in den Mittelpunkt der Entwicklung zu stellen. | D8: Die Teilnehmerin ikennt die Grundprinzipien des agilen Denkens. | E8: Die Teilnehmerin versteht wie Agiles Denken in den Arbeitsalltag integiert werden kann | F8: Die Teilnehmerin ist ind er Lage ein System nach agilen Denkweisen zu entwickeln und den Kundennutzen in den mittelpuinkt zu stellen. | G8: Die Teilnehmerin ist in der Lage Agilkes Denken in das Unternehmen zu tragen und andere dafür zu begeistern.
B9: Anforderungsmanagement | C9: Die Kompetenz Bedürfnisse und Erwartungen der Stakeholder zu analysieren und daraus Anforderungen für ein System festzulegen. | D9: Prozess: Die Teilnehmer können Bedarfe, Stakeholderanforderung, Systemanforderung, und System-Element-Anforderungen unterscheiden. Sie kennen die Bedeutung von Traceability und verstehen warum Werkzeuge /Tools) dafür notwendig sind, Methode: Die Teilnehmer kennen den grundlegenden Ablauf, des Anforderungsmanagements. Dazu gehört das indetifizieren, formulieren, ableiten und analysieren von Anforderungen Tool: Die Teilnehmer wissen, das es ein Werkzeug für das Anforderungsmanagement gibt. | E9: Prozess: Die Teilnehmer verstehen wie Anforderungsquellen identifiziert, Anforderungen hergeleitet, geschrieben werden. Sie kennen die unterschiedlichen Arten und Ebenen von Anforderungen Methode: Die Teilnehmer können Anforderung-dokumenten oder -modellen lesen (verknüpfungen etc.). Sie können Kontextbeschreibungen und Schnittstellenspezifikationen lesen und verstehen Tool: Die Teilnehmer können im Anforderungswerkzeug lesen und Anforderungn anschauen und kommentieren/reviewen. | F9: Prozess: Der Teilnehmer kann selbständig Anforderungsquellen identifizieren, Anforderungen daraus ableiten, schreiben, in Anforderungsdokumenten oder -modellen dokumentieren, verknüpfen, ableiten analysieren. Methode: Die Teilnehmer können selbständig Anforderungsdokumente oder -modelle dokumentieren, verknüpfen und analysieren. Sie können Kontextbeschreibungen und Schnittstellenspezifikationen erstellen und analysieren Tool: Die Teilnehmer können in einem Anforderungswerkzeug Anforderungn definieren, verknüpfen und analysieren. | G9: Prozess: Die Teilnehmer sind in der Lage Unzulänglichkeiten im Prozess zu erkennen und Verbesserungsvorschläge zu erarbeiten. Methode: Er ist in der Lage Kontext- und Schnittstellenbeschreibungen zu erstellen und diese mit Stakeholdern zu diskutieren. Tool: Die Teilnehmer können in einem Anforderungswerkzeug erweiterte Funktionen nutzen und neue Templates, Attribute und Features anlegen.
B10: System-Architekturgestaltung | C10: Die Kompetenz die zu einem System zugehörigen Elemente, ihrer Hierarchie, sowie ihrer Schnittstellen oder ihres Verhaltens und der damit verbundenen abgeleiteten Anforderungen zur Entwicklung einer implementierbaren Lösung zu definieren. | D10: Prozess: Die Teilnehmer kennen den Zweck von Architekturmodellen. Sie können Sie grob in den Entwicklungsprozess einordnen. Methode: Die Teilnehmer wissen, das es eine dedizierte Methodik und Modellierungssprache zur Architekturmodellierung gibt. Tool: Die Teilnehmer wissen, das es ein dediziertes Werkzeug für das Viewing und ggf. die Bearbeitung von Architekturmodellen gibt. | E10: Prozess: Die Teilnehmer können nachvollziehen, warum Architekturmodelle als In- und Outputs des Entwicklungsprozesses relevant sind. Methode: Die Teilnehmer können Architekturmodelle lesen und daraus für sie relevante Informationen entnehmen. Tool: Die Teilnehmer können Architekturmodelle in einem Werkzeug anschauen und kommentieren/reviewen. | F10: Prozess: Die Teilnehmer kennen relevante Prozessschritte für Architekturmodelle und wissen woher im Entwicklungsprozess ihre Inputs kommen und welche Outputs sie darin produzieren. Methode: Die Teilnehmer können Architekturmodelle von durchschnittlicher Komplexität erstellen. Sie sind in der Lage für sie relevante Informationen reproduzierbar und im Einklang mit der Methode und Modellierungssprache abbilden zu können. Tool: Die Teilnehmer können Architekturmodelle in einem Werkzeug erstellen und analysieren. | G10: Prozess: Die Teilnehmer sind in der Lage Unzulänglichkeiten im Prozess zu erkennen und Verbesserungsvorschläge zu erarbeiten. Methode: Die Teilnehmer sind in der Lage, Modelle von hoher Komplexität zu erstellen und zu verwalten. Sie können Unzulänglichkeiten in der Methode oder der Modellierungssprache zu erkennen und Verbesserungsvorschläge zu erarbeiten. Tool: Die Teilnehmer können erweiterte Funktionen nutzen und Templates anlegen.
B11: Integration, Verifikation & Validierung | C11: Die Kompetenz eine Menge von Systemelementen zu einer verifizier- oder validierbaren Einheit zu integrieren bzw. den objektiven Nachweis, das ein System die spezifizierten Anforderungen erfüllt (Validierung), oder seiner beabsichtigten Eigenschaften in der vorgesehenen Einsatzumgebung erreicht (Validierung), durchzuführen. | D11: Der Teilnehmer kennt die Ziele der Verifikation und Validierung sowie kennt verschiedene Arten und Vorgehensweisen der V&V. | E11: Der Teilnehmer kann Testpläne, Testfälle und -ergebnisse lesen und verstehen. | F11: Der Teilnehmer kann Testpläne erstellen. Er ist in der Lage die Tests und Simulationen durchzuführen und zu dokumentieren. | G11: Der Teilnehmer ist in der Lage selbständig und frühzeitig eine Teststrategie sowie einen Erprobungsplan aufzusetzen. Anhand der Anforderungen und Verifikation / Validierungskriterien kann er notwendige Testfälle ableiten. Er ist in der Lage die Tests und Simulationen zu orchestrieren und zu dokumentieren.
B12: Betrieb, Service und Instandhaltung | C12: Die Kompetenz das System in Betrieb zu nehmen, zu betreiben und seine Fähigkeiten/Funktionalitäten über seine Lebensdauer aufrechterhalten wird. | D12: Die Teilnehmer kennen die Zeile der Betriebs-, Service- und Instandhaltungsphase. Sie wissen das diese bereits in der Entwicklung berücksichtigung finden und das es Tätigkeiten in der jewieligen Phase gibt. | E12: Die Teilnehmer verstehen, wie die Phasen Betrieb, Service und Instandhaltung in der Enwtcikllung berücksichtigt werden. Sie sind in der Lage die Tätigkeiten die im Rahmen des Lebenszyklus notwendig sind zu nennen. | F12: Die Teilnehmer verstehen, wie die Phasen Betrieb, Service und Instandhaltung in der Enwtcikllung berücksichtigt werden. Sie sind in der Lage die Phasen abzuwickelon und für zukünftige Projekte verbesserungen zu identifizieren. | G12: Die Teilnehmer sind in der Lage die Organisationsprozesse für den Betrieb, die Wartung und die Instandhaltung zu definieren.,
B13: Agile Methodenkompetenz | C13: Die Kompetenz Methoden anzuwenden, welche die Agilenwerte im Projektkontext unterstützen und paralleles arbeiten ermöglichen | D13: Methode: Der Teilnehmer kennt die Agilen Werte und die relevanten agilen Methoden | E13: Methode: Der Teilnehmer versteht die Grundlagen der agilen Arbeitsweisen und versteht wie sich die agilen Methoden in einem Entwicklungsprozess anwenden lassen. | F13: Methode: der Teilnehmer kann in einem agilen Umfeld arbeiten. Er ist in der Lage die dafür notwedigen Methoden anzuwenden. | G13: Der Teilnehmer kann für ein projekt die relevanten agilen Methoden definieren und umsetzen. Der Teilnehmer ist überzeigt davon agile Methoden gewinnbringend eizusetzen und kann andere dazu motivieren.
B14: Selbstorganisation | C14: Die Kompetenz sich selbst zu organisieren und Aufgaben | D14: Die Teilnehmer kennen die Konzepte der Selbstorganisation. | E14: Die Teilnehmer verstrehen wie die Konzepte der Selbstorganisation ihren Arbeitsalltag beeinflussen | F14: Die Teilnehmer sind in der Lage selbstorganisiert Projekte, Prozesse und Aufgaben abzuarbeiten. | G14: Die Teilnehmer sind in der Lage selbstorganisiert Projekte, Prozesse und Aufgaben abzuarbeiten.
B15: Kommunikation & Zusammenarbeit | C15: Die Kompetenz konstruktiv, effizient und bewusst, auch domaineübergreifend, zu kommunizieren und dabei die Gefühle anderer Menschen zu erfassen und zu berücksichtzigen sowie Beziehungen zu Kollegen und Vorgesetzten nachhaltig und fair zu gestalten. | D15: Teilnehmer kennt die Notwendigkeit dieser Kompetenzen | E15: Teilnehmer erkennt und versteht die Relevanz dieser Kompetenz, insbesondere in Hinblick auf die Anwendung von SE | F15: Teilnehmer ist in der Lage konstruktiv und effizient zu kommunizieren und gleichzeitig empathisch gegenüber seinem Kommunikationspartner zu sein. | G15: Teilnehmer ist darüber hinaus in der Lage, seine Beziehungen zu Kollegen und Vorgesetzen nachhaltig und fair zu gestalten.
B16: Führen | C16: Die Kompetenz geeignete Ziele für ein System bzw. Systemelement auszuwählen, bei Bedarf zu verhandeln und mit einem Team effizient zu erreichen und dabei ggf. Teammitglieder bei der Lösung von Problemen anzuleiten. | D16: Teilnehmer kennt die Notwendigkeit dieser Kompetenzen | E16: Teilnehmer versteht die Relevanz bzgl. der Definition von Zielen für ein System und kann diese für das gesamte Team verständlich definieren | F16: Teilnehmer ist in der Lage, die Ziele mit dem Team zu verhandeln und einen effizienten Weg zu Erreichung dieser zu finden. | G16: Teilnehmer ist in der Lage, Teammitglieder strategisch weiterzuentwickeln, sodass diese sich bei Lösungsfindung weiterentwickeln
... B20: Konfigurationsmanagement | C20: Die Fähigkeit Systemfunktionen, Leistung und physikalischen Eigenschaften über den Lebenszyklus stimmig zu gestalten und die Konsistenz sicherzustellen. | D20: Porzess. Der TN versteht die Notwendgkeit des Konfigurationsmanagements Tool: Der TN weiß, in wechen Werkzeugen knfigurationen zu bilden sind. | E20: Prozess: Der Teilnehmer versteht das Vorgehen zur Festlegung von Konfigurationsitems. Er ist fähig die für ihn relevanten Konfigurationsitems zu erkennen und eine integre Konfiguration für seine relevanten Umfänge zu bilden. Tool: Der TN ist in der Lage in dem(n) Werkzeug(en) für seine Umfänge zu bilden | F20: Prozess: Der Teilnehmer kann sinnvolle Konfigurationsitems definieren. Er ist fähig die für ihn relevanten Konfigurationsitems zu erkennen und eine integre Konfiguration für seine relevanten Umfänge zu bilden. Tool: Der TN ist in der Lage in dem(n) Werkzeug(en) Konfigurationsitems zu definieren und für seine Umfänge zu bilden | G20: Prozess: Er ist fähig alle relevanten Konfigurationsitems zu erkennen und eine integre Konfiguration über alle Konfigurationsitems zu bilden. Er ist in der Lage Verbesserungen zu indetifizieren und Lösungsvorschläge herauszuarbeiten. Er kann andere beim bilden von Konfigurationen unterstützen. Tool: Der TN ist in der Lage in dem(n) Werkzeug(en) Konfigurationsitems zu definieren und für alle Umfänge eine Konfiguration zu bilden.
B21: Implementierung | C21: Die Fähigkeit ein System, Subsystem, Komponente entsprechend der Vorgaben zu realisieren.

Sheet Modulübersicht
A2: ID | B2: Modul | C2: Kompetenz | D2: Niveau | F2: Übergeordnete Lernziele | G2: Inhaltse | H2: Methoden | I2: Übungen | J2: Format Empfehlung | K2: Archetyp
A3: M-Ein | B3: Einstieg
A4: M-Mot | B4: Motivation
A5: M-Term | B5: Grundbegriffe des Systems Engineerings | C5: Systemisches Denken
A6: M_Kon | B6: Konzepte des Systems Engineerings | C6: Systemisches Denken, Berücksichtigung von Systemlebenszyklusphasen | G6: V-Modell, Lebenszyklusphasen
A7: M_Norm | B7: Normen und Standards, ASPICE
A8: M-Anf-G | B8: Anforderungsmanagement Grundlagen | C8: Anforderungsmanagement, Systemmodellierung und -analyse, Kunden-Nutzenorientierung Systemisches Denken
A9: M-Anf-Anw | B9: Anforderungsmanagement Anwenden | C9: Anforderungsmanagement, Systemmodellierung und -analyse, Kunden-Nutzenorientierung Systemisches Denken
A10: M-Arch-G | B10: Architektur & Design inkl Implementierung Grundlagen | C10: Systemarchitekturgestaltung, Systemmodellierung und - analyse, Implementierung Systemisches Denken
A11: M-Arch-Anw | B11: Architektur & Design Anwenden | C11: Systemarchitekturgestaltung, Systemmodellierung und - analyse, Implementierung Systemisches Denken
A12: M-IVV-G | B12: Integration, Verifikation & Validierung | C12: Integration, Verifikation & Validierung
A13: M-IVV-Anw | B13: Integration, Verifikation & Validierung Anwenden | C13: Integration, Verifikation & Validierung
A14: M-Serv | B14: Betrieb, Service und Instandhaltung | C14: Betrieb, Service und Instandhaltung, Berücksichtigung von Systemlebenszyklusphasen
A15: M-MBSE | B15: MBSE | C15: Systemmodellierung und -analyse
A16: M-Proj | B16: Projektplanung und -steuerung | C16: Agile Methodenkompetenz, Projektmanagement
A17: M-Entsch | B17: Entscheidungs- und Konfigurationsmanagement | C17: Entscheidungsmanagement, Konfigurationsmanagement
A18: M-Entsch-anw | B18: Entscheidungs- und Konfigurationsmanagement | C18: Entscheidungsmanagement, Konfigurationsmanagement
A19: M-TechM | B19: technisches Management
A20: M-Org_ | B20: Organization-Enaling-Processes | C20: Informationsmanagement
A21: M-Ums | B21: Umsetzungsplanung von SE
A22: M-Soft | B22: Soft-Skills | C22: Kommunikation & Zusammenarbeit, Führen, Selbstorganisation

Sheet Tabelle2
B3: 0
B4: 1
B5: 2
B6: 3

Sheet Input INCOSE Kompetenzen
D1: Unterscheidung: Fähigkeit und Kompetenz: | G1: 5 | H1: Unerlässliche Kompetenz
D2: Fähigkeit: angebordene oder konkret erlernte Fertigeit | G2: 4
D3: Kompetenz: Wissensbestände (Erfahrung) und Denkmethoden | G3: 3 | H3: sinnvolle Kompetenz
G4: 2
C5: Quelle: | D5: INCOSE SE-Competency Framework | G5: 1 | H5: nicht relevante Kompetenz | Y5: Vertrags-Prozesse | AA5: Organisatorische Projektbefähigungs-Prozesse | AG5: Technischen Management Prozesse | AO5: Technische Prozesse | BC5: (INCOSE) Systems Engineering Professional Zertifizierung Programm | BR5: Agilität
C6: Kompetenzcluster | D6: Definition | E6: Kompetenz | F6: Definition | G6: Bewertung Joerg | H6: Bewertung Vivien | I6: Bewertung Ulf | J6: Ähnliche Kompetenz / Zusammenzuführen mit | K6: Steckbrief Nr. 1: Kundenvertreter | L6: Steckbrief Nr. 2: Projektleiter | M6: Steckbrief Nr. 3: Systementwickler | N6: Steckbrief Nr. 4: Fachentwickler | O6: Steckbrief Nr. 5: Produktionsplaner | P6: Steckbrief Nr. 6: Produktionsmitarbeiter | Q6: Steckbrief Nr. 7: Qualitätsmanager | R6: Steckbrief Nr. 8: Interner Support | S6: Steckbrief Nr. 9: Prozess- und Richtlinien-verantwortlicher | T6: Steckbrief Nr. 10: Servicetechniker | U6: Steckbrief Nr. 11: Innovations- und Strategiemanager | V6: Steckbrief Nr. 12: Management | W6: Steckbrief Nr. 13: V & V | X6: Steckbrief Nr. 14: Kunde | Y6: Akquisition | Z6: Lieferung | AA6: Lebenszyklus-Modell-Management | AB6: Verwaltung der Infrastruktur | AC6: Portfoliomanagement | AD6: Personalwesen-Management | AE6: Qualitätsmanagement | AF6: Wissensmanagement | AG6: Projektierung | AH6: Projektbewertung und Steuerung | AI6: Entscheidungsmanagement | AJ6: Risiko-Management | AK6: Konfigurationsmanagement | AL6: Informationsmanagement | AM6: Messung | AN6: Qualitätssicherungsprozess | AO6: Geschäfts- oder Einsatzanalyse | AP6: Definition von Bedürfnissen und Anforderungen der Stakeholder | AQ6: Definition der Systemanforderungen | AR6: Definition der Architektur | AS6: Entwurfsdefinition | AT6: System-Analyse | AU6: Implementierung | AV6: Integration | AW6: Verifizierung | AX6: Überleitung | AY6: Validierung | AZ6: Betrieb | BA6: Wartung | BB6: Entsorgung | BC6: Anforderungsanalyse | BD6: System- und Entscheidungsanalyse | BE6: Architektur-/Designentwicklung | BF6: System-Integration | BG6: Verifizierung und Validierung | BH6: Systembetrieb und Wartung | BI6: Technische Planung | BJ6: Technische Überwachung und Steuerung | BK6: Beschaffung und Versorgung | BL6: Informations- und Konfigurationsmanagement | BM6: Risiko- und Chancenmanagement | BN6: Definition und Verwaltung von Lebenszyklusprozessen | BO6: Spezialisierte Technik | BP6: Organisatorische projektbegleitende Aktivitäten | BQ6: Andere | BR6: Transformation und Veränderung | BS6: Agile Projektplanung und -durchführung
